Workbook

Sheet DASHBOARD
B3: TAHUN | D3: Penjualan | E3: Barang Keluar | G3: Pembelian | H3: Barang Masuk | J3: Laba Kotor | K3: Pengeluaran Tercatat | L3: Laba Bersih
B4: 2026 | D4: =SUMIFS('SELLING CASH'!$I:$I, 'SELLING CASH'!$C:$C, ">=" & DATE($B$4, 1, 1), 'SELLING CASH'!$C:$C, "<=" & DATE($B$4, 12, 31), 'SELLING CASH'!$R:$R, "<>OIL") + SUMIFS('SELLING CREDIT'!$P:$P, 'SELLING CREDIT'!$C:$C, ">=" & DATE($B$4, 1, 1), 'SELLING CREDIT'!$C:$C, "<=" & DATE($B$4, 12, 31), 'SELLING CREDIT'!$S:$S, "<>OIL") -> 3771168000 | E4: =SUMIFS('SELLING CASH'!$F:$F, 'SELLING CASH'!$C:$C, ">=" & DATE($B$4, 1, 1), 'SELLING CASH'!$C:$C, "<=" & DATE($B$4, 12, 31), 'SELLING CASH'!$R:$R, "TIRE") + SUMIFS('SELLING CREDIT'!$G:$G, 'SELLING CREDIT'!$C:$C, ">=" & DATE($B$4, 1, 1), 'SELLING CREDIT'!$C:$C, "<=" & DATE($B$4, 12, 31), 'SELLING CREDIT'!$S:$S, "TIRE") -> 4341 | G4: =SUMIFS(PURCHASE!$N:$N, PURCHASE!$C:$C, ">=" & DATE($B$4, 1, 1), PURCHASE!$C:$C, "<=" & DATE($B$4, 12, 31), PURCHASE!$P:$P, "TIRE") -> 2908967163 | H4: =SUMIFS(PURCHASE!$J:$J, PURCHASE!$C:$C, ">=" & DATE($B$4, 1, 1), PURCHASE!$C:$C, "<=" & DATE($B$4, 12, 31), PURCHASE!$P:$P, "TIRE") -> 3875 | J4: =SUMIFS('SELLING CASH'!$N:$N, 'SELLING CASH'!$C:$C, ">=" & DATE($B$4, 1, 1), 'SELLING CASH'!$C:$C, "<=" & DATE($B$4, 12, 31), 'SELLING CASH'!$R:$R, "<>OIL", 'SELLING CASH'!$R:$R, "<>SERVICE") + SUMIFS('PAYMENT CREDIT'!$G:$G, 'PAYMENT CREDIT'!$C:$C, ">=" & DATE($B$4, 1, 1), 'PAYMENT CREDIT'!$C:$C, "<=" & DATE($B$4, 12, 31)) -> 447263000 | K4: =SUMIFS(EXPENSES!$D:$D, EXPENSES!$C:$C, ">=" & DATE($B$4, 1, 1), EXPENSES!$C:$C, "<=" & DATE($B$4, 12, 31)) -> 435942091 | L4: =J4-K4 -> 11320909

Sheet DAILY REPORT
A1: -
A2: 27375 | E2: 46290 | L2: Month | M2: September
A3: 22500 | P3: =SUM(P6:P36) -> 3810000 | Q3: GRAND TOTAL | S3: =SUM(S6:S40) -> 290510000 | T3: =SUM(T6:T40) -> 38538000 | U3: =SUM(U6:U40) -> 10160000 | V3: =SUM(V6:V40) -> 339208000 | W3: =SUM(W6:W40) -> 12645000 | Y3: BIAN
A4: 0 | L4: Tanggal | M4: CASH | Q4: TEMPO | S4: Jumlah | V4: TOTAL | W4: oil | Y4: =sum(Y7:Y37) -> 2075000 | Z4: =sum(Z7:Z37) -> 1480000
D5: Report | E5: =E2 -> 46290 | G5: Detail | M5: Modal | N5: Laba | O5: Spooring | P5: Service fee | Q5: Modal | R5: Laba | S5: Modal | T5: Laba | U5: Spooring | Y5: Modal | Z5: Laba
D6: Revenue | E6: =sumifs('SELLING CASH'!I:I,'SELLING CASH'!C:C,E5,'SELLING CASH'!R:R,"<>OIL") -> 15025000 | G6: Toko | H6: =E15-(H7+H8) -> 7623000 | L6: 46266 | M6: =sumifs('SELLING CASH'!I:I,'SELLING CASH'!C:C,L6,'SELLING CASH'!R:R,"<>OIL")-(N6+O6+P6) -> 12555000 | N6: =sumifs('SELLING CASH'!N:N,'SELLING CASH'!C:C,L6,'SELLING CASH'!R:R,"<>SERVICE",'SELLING CASH'!R:R, "<>OIL") -> 1445000 | O6: =sumifs('SELLING CASH'!N:N,'SELLING CASH'!C:C,L6,'SELLING CASH'!R:R,"SERVICE") -> 490000 | P6: =sumif('SELLING CASH'!C:C,L6,'SELLING CASH'!J:J) -> 95000 | Q6: =SUMIF('PAYMENT CREDIT'!C:C,L6,'PAYMENT CREDIT'!F:F)-R6 -> 4400000 | R6: =SUMIF('PAYMENT CREDIT'!C:C,L6,'PAYMENT CREDIT'!G:G) -> 600000 | S6: =M6+Q6 -> 16955000 | T6: =N6+R6 -> 2045000 | U6: =O6 -> 490000 | V6: =SUM(S6:U6) -> 19490000 | W6: =SUMIFS('SELLING CASH'!I:I,'SELLING CASH'!C:C,L6,'SELLING CASH'!R:R,"OIL") -> 885000
D7: Receivable Revenue | E7: =sumif('PAYMENT CREDIT'!C:C,E5,'PAYMENT CREDIT'!F:F) -> 0 | G7: Profit | H7: =SUMIFS('SELLING CASH'!N:N, 'SELLING CASH'!C:C, E5, 'SELLING CASH'!R:R, "<>SERVICE", 'SELLING CASH'!R:R, "<>OIL") + SUMIF('PAYMENT CREDIT'!C:C, E5, 'PAYMENT CREDIT'!G:G)- E10-E14-SUMIF('SELLING CREDIT'!C:C,E5,'SELLING CREDIT'!K:K) -> 1380000 | L7: 46267 | M7: =sumifs('SELLING CASH'!I:I,'SELLING CASH'!C:C,L7,'SELLING CASH'!R:R,"<>OIL")-(N7+O7+P7) -> 7760000 | N7: =sumifs('SELLING CASH'!N:N,'SELLING CASH'!C:C,L7,'SELLING CASH'!R:R,"<>SERVICE",'SELLING CASH'!R:R, "<>OIL") -> 1365000 | O7: =sumifs('SELLING CASH'!N:N,'SELLING CASH'!C:C,L7,'SELLING CASH'!R:R,"SERVICE") -> 355000 | P7: =sumif('SELLING CASH'!C:C,L7,'SELLING CASH'!J:J) -> 95000 | Q7: =SUMIF('PAYMENT CREDIT'!C:C,L7,'PAYMENT CREDIT'!F:F)-R7 -> 9545000 | R7: =SUMIF('PAYMENT CREDIT'!C:C,L7,'PAYMENT CREDIT'!G:G) -> 670000 | S7: =M7+Q7 -> 17305000 | T7: =N7+R7 -> 2035000 | U7: =O7 -> 355000 | V7: =SUM(S7:U7) -> 19695000 | W7: =SUMIFS('SELLING CASH'!I:I,'SELLING CASH'!C:C,L7,'SELLING CASH'!R:R,"OIL") -> 385000 | Y7: 1100000 | Z7: 180000
E8: =E6+E7 -> 15025000 | G8: Spooring | H8: =sumifs('SELLING CASH'!N:N,'SELLING CASH'!C:C,E5,'SELLING CASH'!R:R,"SERVICE")+SUMIF('SELLING CREDIT'!C:C,E5,'SELLING CREDIT'!K:K) -> 775000 | L8: 46268 | M8: =sumifs('SELLING CASH'!I:I,'SELLING CASH'!C:C,L8,'SELLING CASH'!R:R,"<>OIL")-(N8+O8+P8) -> 5465000 | N8: =sumifs('SELLING CASH'!N:N,'SELLING CASH'!C:C,L8,'SELLING CASH'!R:R,"<>SERVICE",'SELLING CASH'!R:R, "<>OIL") -> 830000 | O8: =sumifs('SELLING CASH'!N:N,'SELLING CASH'!C:C,L8,'SELLING CASH'!R:R,"SERVICE") -> 365000 | P8: =sumif('SELLING CASH'!C:C,L8,'SELLING CASH'!J:J) -> 130000 | Q8: =SUMIF('PAYMENT CREDIT'!C:C,L8,'PAYMENT CREDIT'!F:F)-R8 -> 900000 | R8: =SUMIF('PAYMENT CREDIT'!C:C,L8,'PAYMENT CREDIT'!G:G) -> 0 | S8: =M8+Q8 -> 6365000 | T8: =N8+R8 -> 830000 | U8: =O8 -> 365000 | V8: =SUM(S8:U8) -> 7560000 | W8: =SUMIFS('SELLING CASH'!I:I,'SELLING CASH'!C:C,L8,'SELLING CASH'!R:R,"OIL") -> 750000
D9: Transfer Payment | E9: =SUMif(TRANSFER!C:C,E2,TRANSFER!D:D) -> 4447000 | G9: Oil | H9: =SUMIFS('SELLING CASH'!I:I,'SELLING CASH'!C:C,E5,'SELLING CASH'!R:R,"OIL") -> 0 | L9: 46269 | M9: =sumifs('SELLING CASH'!I:I,'SELLING CASH'!C:C,L9,'SELLING CASH'!R:R,"<>OIL")-(N9+O9+P9) -> 11725000 | N9: =sumifs('SELLING CASH'!N:N,'SELLING CASH'!C:C,L9,'SELLING CASH'!R:R,"<>SERVICE",'SELLING CASH'!R:R, "<>OIL") -> 1750000 | O9: =sumifs('SELLING CASH'!N:N,'SELLING CASH'!C:C,L9,'SELLING CASH'!R:R,"SERVICE") -> 280000 | P9: =sumif('SELLING CASH'!C:C,L9,'SELLING CASH'!J:J) -> 20000 | Q9: =SUMIF('PAYMENT CREDIT'!C:C,L9,'PAYMENT CREDIT'!F:F)-R9 -> 4320000 | R9: =SUMIF('PAYMENT CREDIT'!C:C,L9,'PAYMENT CREDIT'!G:G) -> 400000 | S9: =M9+Q9 -> 16045000 | T9: =N9+R9 -> 2150000 | U9: =O9 -> 280000 | V9: =SUM(S9:U9) -> 18475000 | W9: =SUMIFS('SELLING CASH'!I:I,'SELLING CASH'!C:C,L9,'SELLING CASH'!R:R,"OIL") -> 370000
D10: Expenses | E10: =sumifS(EXPENSES!D:D,EXPENSES!C:C,E5,EXPENSES!G:G,"Cashier") -> 15000 | L10: 46270 | M10: =sumifs('SELLING CASH'!I:I,'SELLING CASH'!C:C,L10,'SELLING CASH'!R:R,"<>OIL")-(N10+O10+P10) -> 9135000 | N10: =sumifs('SELLING CASH'!N:N,'SELLING CASH'!C:C,L10,'SELLING CASH'!R:R,"<>SERVICE",'SELLING CASH'!R:R, "<>OIL") -> 835000 | O10: =sumifs('SELLING CASH'!N:N,'SELLING CASH'!C:C,L10,'SELLING CASH'!R:R,"SERVICE") -> 0 | P10: =sumif('SELLING CASH'!C:C,L10,'SELLING CASH'!J:J) -> 0 | Q10: =SUMIF('PAYMENT CREDIT'!C:C,L10,'PAYMENT CREDIT'!F:F)-R10 -> 4420000 | R10: =SUMIF('PAYMENT CREDIT'!C:C,L10,'PAYMENT CREDIT'!G:G) -> 600000 | S10: =M10+Q10 -> 13555000 | T10: =N10+R10 -> 1435000 | U10: =O10 -> 0 | V10: =SUM(S10:U10) -> 14990000 | W10: =SUMIFS('SELLING CASH'!I:I,'SELLING CASH'!C:C,L10,'SELLING CASH'!R:R,"OIL") -> 0
D11: Service Fee | E11: =sumif('SELLING CASH'!C:C,E5,'SELLING CASH'!J:J)+sumif('SELLING CREDIT'!C:C,E5,'SELLING CREDIT'!K:K) -> 125000 | G11: Detail Transfer | L11: 46271 | M11: =sumifs('SELLING CASH'!I:I,'SELLING CASH'!C:C,L11,'SELLING CASH'!R:R,"<>OIL")-(N11+O11+P11) -> 8520000 | N11: =sumifs('SELLING CASH'!N:N,'SELLING CASH'!C:C,L11,'SELLING CASH'!R:R,"<>SERVICE",'SELLING CASH'!R:R, "<>OIL") -> 1420000 | O11: =sumifs('SELLING CASH'!N:N,'SELLING CASH'!C:C,L11,'SELLING CASH'!R:R,"SERVICE") -> 480000 | P11: =sumif('SELLING CASH'!C:C,L11,'SELLING CASH'!J:J) -> 125000 | Q11: =SUMIF('PAYMENT CREDIT'!C:C,L11,'PAYMENT CREDIT'!F:F)-R11 -> 0 | R11: =SUMIF('PAYMENT CREDIT'!C:C,L11,'PAYMENT CREDIT'!G:G) -> 0 | S11: =M11+Q11 -> 8520000 | T11: =N11+R11 -> 1420000 | U11: =O11 -> 480000 | V11: =SUM(S11:U11) -> 10420000 | W11: =SUMIFS('SELLING CASH'!I:I,'SELLING CASH'!C:C,L11,'SELLING CASH'!R:R,"OIL") -> 1150000 | Y11: 75000 | Z11: 100000
D12: Nett cash | E12: =E8-(E9+E10+E11) -> 10438000 | G12: BCA | H12: =SUMIFS(TRANSFER!D:D,TRANSFER!C:C,$E$5,TRANSFER!E:E,G12) -> 3240000 | L12: 46272 | M12: =sumifs('SELLING CASH'!I:I,'SELLING CASH'!C:C,L12,'SELLING CASH'!R:R,"<>OIL")-(N12+O12+P12) -> 21520000 | N12: =sumifs('SELLING CASH'!N:N,'SELLING CASH'!C:C,L12,'SELLING CASH'!R:R,"<>SERVICE",'SELLING CASH'!R:R, "<>OIL") -> 1985000 | O12: =sumifs('SELLING CASH'!N:N,'SELLING CASH'!C:C,L12,'SELLING CASH'!R:R,"SERVICE") -> 0 | P12: =sumif('SELLING CASH'!C:C,L12,'SELLING CASH'!J:J) -> 0 | Q12: =SUMIF('PAYMENT CREDIT'!C:C,L12,'PAYMENT CREDIT'!F:F)-R12 -> 1525000 | R12: =SUMIF('PAYMENT CREDIT'!C:C,L12,'PAYMENT CREDIT'!G:G) -> 200000 | S12: =M12+Q12 -> 23045000 | T12: =N12+R12 -> 2185000 | U12: =O12 -> 0 | V12: =SUM(S12:U12) -> 25230000 | W12: =SUMIFS('SELLING CASH'!I:I,'SELLING CASH'!C:C,L12,'SELLING CASH'!R:R,"OIL") -> 0
D13: MODAL BIAN | E13: 570000 | G13: BRI | H13: =SUMIFS(TRANSFER!D:D,TRANSFER!C:C,$E$5,TRANSFER!E:E,G13) -> 0 | L13: 46273 | M13: =sumifs('SELLING CASH'!I:I,'SELLING CASH'!C:C,L13,'SELLING CASH'!R:R,"<>OIL")-(N13+O13+P13) -> 14835000 | N13: =sumifs('SELLING CASH'!N:N,'SELLING CASH'!C:C,L13,'SELLING CASH'!R:R,"<>SERVICE",'SELLING CASH'!R:R, "<>OIL") -> 1370000 | O13: =sumifs('SELLING CASH'!N:N,'SELLING CASH'!C:C,L13,'SELLING CASH'!R:R,"SERVICE") -> 520000 | P13: =sumif('SELLING CASH'!C:C,L13,'SELLING CASH'!J:J) -> 165000 | Q13: =SUMIF('PAYMENT CREDIT'!C:C,L13,'PAYMENT CREDIT'!F:F)-R13 -> 2960000 | R13: =SUMIF('PAYMENT CREDIT'!C:C,L13,'PAYMENT CREDIT'!G:G) -> 420000 | S13: =M13+Q13 -> 17795000 | T13: =N13+R13 -> 1790000 | U13: =O13 -> 520000 | V13: =SUM(S13:U13) -> 20105000 | W13: =SUMIFS('SELLING CASH'!I:I,'SELLING CASH'!C:C,L13,'SELLING CASH'!R:R,"OIL") -> 250000
D14: LABA bian | E14: 90000 | G14: DANAMON | H14: =SUMIFS(TRANSFER!D:D,TRANSFER!C:C,$E$5,TRANSFER!E:E,G14) -> 0 | L14: 46274 | M14: =sumifs('SELLING CASH'!I:I,'SELLING CASH'!C:C,L14,'SELLING CASH'!R:R,"<>OIL")-(N14+O14+P14) -> 14030000 | N14: =sumifs('SELLING CASH'!N:N,'SELLING CASH'!C:C,L14,'SELLING CASH'!R:R,"<>SERVICE",'SELLING CASH'!R:R, "<>OIL") -> 1790000 | O14: =sumifs('SELLING CASH'!N:N,'SELLING CASH'!C:C,L14,'SELLING CASH'!R:R,"SERVICE") -> 555000 | P14: =sumif('SELLING CASH'!C:C,L14,'SELLING CASH'!J:J) -> 250000 | Q14: =SUMIF('PAYMENT CREDIT'!C:C,L14,'PAYMENT CREDIT'!F:F)-R14 -> 1415000 | R14: =SUMIF('PAYMENT CREDIT'!C:C,L14,'PAYMENT CREDIT'!G:G) -> 565000 | S14: =M14+Q14 -> 15445000 | T14: =N14+R14 -> 2355000 | U14: =O14 -> 555000 | V14: =SUM(S14:U14) -> 18355000 | W14: =SUMIFS('SELLING CASH'!I:I,'SELLING CASH'!C:C,L14,'SELLING CASH'!R:R,"OIL") -> 490000 | Y14: 75000 | Z14: 100000
D15: Nett cash | E15: =E12-(E13+E14) -> 9778000 | G15: BNI | H15: =SUMIFS(TRANSFER!D:D,TRANSFER!C:C,$E$5,TRANSFER!E:E,G15) -> 0 | L15: 46275 | M15: =sumifs('SELLING CASH'!I:I,'SELLING CASH'!C:C,L15,'SELLING CASH'!R:R,"<>OIL")-(N15+O15+P15) -> 21410000 | N15: =sumifs('SELLING CASH'!N:N,'SELLING CASH'!C:C,L15,'SELLING CASH'!R:R,"<>SERVICE",'SELLING CASH'!R:R, "<>OIL") -> 3755000 | O15: =sumifs('SELLING CASH'!N:N,'SELLING CASH'!C:C,L15,'SELLING CASH'!R:R,"SERVICE") -> 895000 | P15: =sumif('SELLING CASH'!C:C,L15,'SELLING CASH'!J:J) -> 405000 | Q15: =SUMIF('PAYMENT CREDIT'!C:C,L15,'PAYMENT CREDIT'!F:F)-R15 -> 2830000 | R15: =SUMIF('PAYMENT CREDIT'!C:C,L15,'PAYMENT CREDIT'!G:G) -> 430000 | S15: =M15+Q15 -> 24240000 | T15: =N15+R15 -> 4185000 | U15: =O15 -> 895000 | V15: =SUM(S15:U15) -> 29320000 | W15: =SUMIFS('SELLING CASH'!I:I,'SELLING CASH'!C:C,L15,'SELLING CASH'!R:R,"OIL")+210000 -> 210000
G16: EDC | H16: =SUMIFS(TRANSFER!D:D,TRANSFER!C:C,$E$5,TRANSFER!E:E,G16) -> 1207000 | L16: 46276 | M16: =sumifs('SELLING CASH'!I:I,'SELLING CASH'!C:C,L16,'SELLING CASH'!R:R,"<>OIL")-(N16+O16+P16) -> 10600000 | N16: =sumifs('SELLING CASH'!N:N,'SELLING CASH'!C:C,L16,'SELLING CASH'!R:R,"<>SERVICE",'SELLING CASH'!R:R, "<>OIL") -> 1240000 | O16: =sumifs('SELLING CASH'!N:N,'SELLING CASH'!C:C,L16,'SELLING CASH'!R:R,"SERVICE") -> 190000 | P16: =sumif('SELLING CASH'!C:C,L16,'SELLING CASH'!J:J) -> 85000 | Q16: =SUMIF('PAYMENT CREDIT'!C:C,L16,'PAYMENT CREDIT'!F:F)-R16 -> 0 | R16: =SUMIF('PAYMENT CREDIT'!C:C,L16,'PAYMENT CREDIT'!G:G) -> 0 | S16: =M16+Q16 -> 10600000 | T16: =N16+R16 -> 1240000 | U16: =O16 -> 190000 | V16: =SUM(S16:U16) -> 12030000 | W16: =SUMIFS('SELLING CASH'!I:I,'SELLING CASH'!C:C,L16,'SELLING CASH'!R:R,"OIL")+360000 -> 360000
G17: QRIS | H17: =SUMIFS(TRANSFER!D:D,TRANSFER!C:C,$E$5,TRANSFER!E:E,G17) -> 0 | L17: 46277 | M17: =sumifs('SELLING CASH'!I:I,'SELLING CASH'!C:C,L17,'SELLING CASH'!R:R,"<>OIL")-(N17+O17+P17) -> 5530000 | N17: =sumifs('SELLING CASH'!N:N,'SELLING CASH'!C:C,L17,'SELLING CASH'!R:R,"<>SERVICE",'SELLING CASH'!R:R, "<>OIL") -> 735000 | O17: =sumifs('SELLING CASH'!N:N,'SELLING CASH'!C:C,L17,'SELLING CASH'!R:R,"SERVICE") -> 140000 | P17: =sumif('SELLING CASH'!C:C,L17,'SELLING CASH'!J:J) -> 10000 | Q17: =SUMIF('PAYMENT CREDIT'!C:C,L17,'PAYMENT CREDIT'!F:F)-R17 -> 1560000 | R17: =SUMIF('PAYMENT CREDIT'!C:C,L17,'PAYMENT CREDIT'!G:G) -> 200000 | S17: =M17+Q17 -> 7090000 | T17: =N17+R17 -> 935000 | U17: =O17 -> 140000 | V17: =SUM(S17:U17) -> 8165000 | W17: =SUMIFS('SELLING CASH'!I:I,'SELLING CASH'!C:C,L17,'SELLING CASH'!R:R,"OIL") -> 885000
L18: 46278 | M18: =sumifs('SELLING CASH'!I:I,'SELLING CASH'!C:C,L18,'SELLING CASH'!R:R,"<>OIL")-(N18+O18+P18) -> 0 | N18: =sumifs('SELLING CASH'!N:N,'SELLING CASH'!C:C,L18,'SELLING CASH'!R:R,"<>SERVICE",'SELLING CASH'!R:R, "<>OIL") -> 0 | O18: =sumifs('SELLING CASH'!N:N,'SELLING CASH'!C:C,L18,'SELLING CASH'!R:R,"SERVICE") -> 0 | P18: =sumif('SELLING CASH'!C:C,L18,'SELLING CASH'!J:J) -> 0 | Q18: =SUMIF('PAYMENT CREDIT'!C:C,L18,'PAYMENT CREDIT'!F:F)-R18 -> 0 | R18: =SUMIF('PAYMENT CREDIT'!C:C,L18,'PAYMENT CREDIT'!G:G) -> 0 | S18: =M18+Q18 -> 0 | T18: =N18+R18 -> 0 | U18: =O18 -> 0 | V18: =SUM(S18:U18) -> 0 | W18: =SUMIFS('SELLING CASH'!I:I,'SELLING CASH'!C:C,L18,'SELLING CASH'!R:R,"OIL") -> 0
L19: 46279 | M19: =sumifs('SELLING CASH'!I:I,'SELLING CASH'!C:C,L19,'SELLING CASH'!R:R,"<>OIL")-(N19+O19+P19) -> 3620000 | N19: =sumifs('SELLING CASH'!N:N,'SELLING CASH'!C:C,L19,'SELLING CASH'!R:R,"<>SERVICE",'SELLING CASH'!R:R, "<>OIL") -> 690000 | O19: =sumifs('SELLING CASH'!N:N,'SELLING CASH'!C:C,L19,'SELLING CASH'!R:R,"SERVICE") -> 470000 | P19: =sumif('SELLING CASH'!C:C,L19,'SELLING CASH'!J:J) -> 315000 | Q19: =SUMIF('PAYMENT CREDIT'!C:C,L19,'PAYMENT CREDIT'!F:F)-R19 -> 0 | R19: =SUMIF('PAYMENT CREDIT'!C:C,L19,'PAYMENT CREDIT'!G:G) -> 0 | S19: =M19+Q19 -> 3620000 | T19: =N19+R19 -> 690000 | U19: =O19 -> 470000 | V19: =SUM(S19:U19) -> 4780000 | W19: =SUMIFS('SELLING CASH'!I:I,'SELLING CASH'!C:C,L19,'SELLING CASH'!R:R,"OIL") -> 875000 | Y19: 150000 | Z19: 200000
L20: 46280 | M20: =sumifs('SELLING CASH'!I:I,'SELLING CASH'!C:C,L20,'SELLING CASH'!R:R,"<>OIL")-(N20+O20+P20) -> 16095000 | N20: =sumifs('SELLING CASH'!N:N,'SELLING CASH'!C:C,L20,'SELLING CASH'!R:R,"<>SERVICE",'SELLING CASH'!R:R, "<>OIL") -> 2330000 | O20: =sumifs('SELLING CASH'!N:N,'SELLING CASH'!C:C,L20,'SELLING CASH'!R:R,"SERVICE") -> 340000 | P20: =sumif('SELLING CASH'!C:C,L20,'SELLING CASH'!J:J) -> 165000 | Q20: =SUMIF('PAYMENT CREDIT'!C:C,L20,'PAYMENT CREDIT'!F:F)-R20 -> 0 | R20: =SUMIF('PAYMENT CREDIT'!C:C,L20,'PAYMENT CREDIT'!G:G) -> 0 | S20: =M20+Q20 -> 16095000 | T20: =N20+R20 -> 2330000 | U20: =O20 -> 340000 | V20: =SUM(S20:U20) -> 18765000 | W20: =SUMIFS('SELLING CASH'!I:I,'SELLING CASH'!C:C,L20,'SELLING CASH'!R:R,"OIL") -> 385000
D21: NOTE UANG THEO | E21: Jumlah | G21: Modal | H21: Laba | L21: 46281 | M21: =sumifs('SELLING CASH'!I:I,'SELLING CASH'!C:C,L21,'SELLING CASH'!R:R,"<>OIL")-(N21+O21+P21) -> 4965000 | N21: =sumifs('SELLING CASH'!N:N,'SELLING CASH'!C:C,L21,'SELLING CASH'!R:R,"<>SERVICE",'SELLING CASH'!R:R, "<>OIL") -> 943000 | O21: =sumifs('SELLING CASH'!N:N,'SELLING CASH'!C:C,L21,'SELLING CASH'!R:R,"SERVICE") -> 555000 | P21: =sumif('SELLING CASH'!C:C,L21,'SELLING CASH'!J:J) -> 310000 | Q21: =SUMIF('PAYMENT CREDIT'!C:C,L21,'PAYMENT CREDIT'!F:F)-R21 -> 0 | R21: =SUMIF('PAYMENT CREDIT'!C:C,L21,'PAYMENT CREDIT'!G:G) -> 0 | S21: =M21+Q21 -> 4965000 | T21: =N21+R21 -> 943000 | U21: =O21 -> 555000 | V21: =SUM(S21:U21) -> 6463000 | W21: =SUMIFS('SELLING CASH'!I:I,'SELLING CASH'!C:C,L21,'SELLING CASH'!R:R,"OIL") -> 525000 | Y21: 75000 | Z21: 100000
D22: 45964 | G22: =J22*75000 -> 150000 | H22: =J22*100000 -> 200000 | J22: 2 | L22: 46282 | M22: =sumifs('SELLING CASH'!I:I,'SELLING CASH'!C:C,L22,'SELLING CASH'!R:R,"<>OIL")-(N22+O22+P22) -> 14335000 | N22: =sumifs('SELLING CASH'!N:N,'SELLING CASH'!C:C,L22,'SELLING CASH'!R:R,"<>SERVICE",'SELLING CASH'!R:R, "<>OIL") -> 1740000 | O22: =sumifs('SELLING CASH'!N:N,'SELLING CASH'!C:C,L22,'SELLING CASH'!R:R,"SERVICE") -> 325000 | P22: =sumif('SELLING CASH'!C:C,L22,'SELLING CASH'!J:J) -> 150000 | Q22: =SUMIF('PAYMENT CREDIT'!C:C,L22,'PAYMENT CREDIT'!F:F)-R22 -> 0 | R22: =SUMIF('PAYMENT CREDIT'!C:C,L22,'PAYMENT CREDIT'!G:G) -> 0 | S22: =M22+Q22 -> 14335000 | T22: =N22+R22 -> 1740000 | U22: =O22 -> 325000 | V22: =SUM(S22:U22) -> 16400000 | W22: =SUMIFS('SELLING CASH'!I:I,'SELLING CASH'!C:C,L22,'SELLING CASH'!R:R,"OIL") -> 385000 | Y22: 75000 | Z22: 100000
D23: 45965 | E23: 350000 | G23: =J23*75000 -> 150000 | H23: =J23*100000 -> 200000 | J23: 2 | L23: 46283 | M23: =sumifs('SELLING CASH'!I:I,'SELLING CASH'!C:C,L23,'SELLING CASH'!R:R,"<>OIL")-(N23+O23+P23) -> 10310000 | N23: =sumifs('SELLING CASH'!N:N,'SELLING CASH'!C:C,L23,'SELLING CASH'!R:R,"<>SERVICE",'SELLING CASH'!R:R, "<>OIL") -> 1250000 | O23: =sumifs('SELLING CASH'!N:N,'SELLING CASH'!C:C,L23,'SELLING CASH'!R:R,"SERVICE") -> 440000 | P23: =sumif('SELLING CASH'!C:C,L23,'SELLING CASH'!J:J) -> 255000 | Q23: =SUMIF('PAYMENT CREDIT'!C:C,L23,'PAYMENT CREDIT'!F:F)-R23 -> 0 | R23: =SUMIF('PAYMENT CREDIT'!C:C,L23,'PAYMENT CREDIT'!G:G) -> 0 | S23: =M23+Q23 -> 10310000 | T23: =N23+R23 -> 1250000 | U23: =O23 -> 440000 | V23: =SUM(S23:U23) -> 12000000 | W23: =SUMIFS('SELLING CASH'!I:I,'SELLING CASH'!C:C,L23,'SELLING CASH'!R:R,"OIL") -> 0 | Y23: 150000 | Z23: 200000
E24: 350000 | G24: =J24*75000 -> 150000 | H24: =J24*100000 -> 200000 | J24: 2 | L24: 46284 | M24: =sumifs('SELLING CASH'!I:I,'SELLING CASH'!C:C,L24,'SELLING CASH'!R:R,"<>OIL")-(N24+O24+P24) -> 3615000 | N24: =sumifs('SELLING CASH'!N:N,'SELLING CASH'!C:C,L24,'SELLING CASH'!R:R,"<>SERVICE",'SELLING CASH'!R:R, "<>OIL") -> 810000 | O24: =sumifs('SELLING CASH'!N:N,'SELLING CASH'!C:C,L24,'SELLING CASH'!R:R,"SERVICE") -> 465000 | P24: =sumif('SELLING CASH'!C:C,L24,'SELLING CASH'!J:J) -> 225000 | Q24: =SUMIF('PAYMENT CREDIT'!C:C,L24,'PAYMENT CREDIT'!F:F)-R24 -> 13620000 | R24: =SUMIF('PAYMENT CREDIT'!C:C,L24,'PAYMENT CREDIT'!G:G) -> 1800000 | S24: =M24+Q24 -> 17235000 | T24: =N24+R24 -> 2610000 | U24: =O24 -> 465000 | V24: =SUM(S24:U24) -> 20310000 | W24: =SUMIFS('SELLING CASH'!I:I,'SELLING CASH'!C:C,L24,'SELLING CASH'!R:R,"OIL")+210000 -> 1435000 | Y24: 150000 | Z24: 200000
E25: 350000 | H25: =J25*100000 -> 200000 | J25: 2 | L25: 46285 | M25: =sumifs('SELLING CASH'!I:I,'SELLING CASH'!C:C,L25,'SELLING CASH'!R:R,"<>OIL")-(N25+O25+P25) -> 2425000 | N25: =sumifs('SELLING CASH'!N:N,'SELLING CASH'!C:C,L25,'SELLING CASH'!R:R,"<>SERVICE",'SELLING CASH'!R:R, "<>OIL") -> 375000 | O25: =sumifs('SELLING CASH'!N:N,'SELLING CASH'!C:C,L25,'SELLING CASH'!R:R,"SERVICE") -> 0 | P25: =sumif('SELLING CASH'!C:C,L25,'SELLING CASH'!J:J) -> 0 | Q25: =SUMIF('PAYMENT CREDIT'!C:C,L25,'PAYMENT CREDIT'!F:F)-R25 -> 0 | R25: =SUMIF('PAYMENT CREDIT'!C:C,L25,'PAYMENT CREDIT'!G:G) -> 0 | S25: =M25+Q25 -> 2425000 | T25: =N25+R25 -> 375000 | U25: =O25 -> 0 | V25: =SUM(S25:U25) -> 2800000 | W25: =SUMIFS('SELLING CASH'!I:I,'SELLING CASH'!C:C,L25,'SELLING CASH'!R:R,"OIL") -> 1020000
D26: 45970 | E26: 175000 | G26: =J26*75000 -> 75000 | H26: =J26*100000 -> 100000 | J26: 1 | L26: 46286 | M26: =sumifs('SELLING CASH'!I:I,'SELLING CASH'!C:C,L26,'SELLING CASH'!R:R,"<>OIL")-(N26+O26+P26) -> 5000000 | N26: =sumifs('SELLING CASH'!N:N,'SELLING CASH'!C:C,L26,'SELLING CASH'!R:R,"<>SERVICE",'SELLING CASH'!R:R, "<>OIL") -> 715000 | O26: =sumifs('SELLING CASH'!N:N,'SELLING CASH'!C:C,L26,'SELLING CASH'!R:R,"SERVICE") -> 555000 | P26: =sumif('SELLING CASH'!C:C,L26,'SELLING CASH'!J:J) -> 175000 | Q26: =SUMIF('PAYMENT CREDIT'!C:C,L26,'PAYMENT CREDIT'!F:F)-R26 -> 0 | R26: =SUMIF('PAYMENT CREDIT'!C:C,L26,'PAYMENT CREDIT'!G:G) -> 0 | S26: =M26+Q26 -> 5000000 | T26: =N26+R26 -> 715000 | U26: =O26 -> 555000 | V26: =SUM(S26:U26) -> 6270000 | W26: =SUMIFS('SELLING CASH'!I:I,'SELLING CASH'!C:C,L26,'SELLING CASH'!R:R,"OIL")+600000 -> 600000 | Y26: 150000 | Z26: 200000
D27: 45972 | E27: 350000 | G27: =J27*75000+G28 -> 225000 | H27: =J27*100000 -> 200000 | J27: 2 | L27: 46287 | M27: =sumifs('SELLING CASH'!I:I,'SELLING CASH'!C:C,L27,'SELLING CASH'!R:R,"<>OIL")-(N27+O27+P27) -> 3980000 | N27: =sumifs('SELLING CASH'!N:N,'SELLING CASH'!C:C,L27,'SELLING CASH'!R:R,"<>SERVICE",'SELLING CASH'!R:R, "<>OIL") -> 715000 | O27: =sumifs('SELLING CASH'!N:N,'SELLING CASH'!C:C,L27,'SELLING CASH'!R:R,"SERVICE") -> 590000 | P27: =sumif('SELLING CASH'!C:C,L27,'SELLING CASH'!J:J) -> 165000 | Q27: =SUMIF('PAYMENT CREDIT'!C:C,L27,'PAYMENT CREDIT'!F:F)-R27 -> 0 | R27: =SUMIF('PAYMENT CREDIT'!C:C,L27,'PAYMENT CREDIT'!G:G) -> 0 | S27: =M27+Q27 -> 3980000 | T27: =N27+R27 -> 715000 | U27: =O27 -> 590000 | V27: =SUM(S27:U27) -> 5285000 | W27: =SUMIFS('SELLING CASH'!I:I,'SELLING CASH'!C:C,L27,'SELLING CASH'!R:R,"OIL")+120000 -> 390000
D28: 45973 | E28: 175000 | G28: =J28*75000 -> 75000 | H28: =J28*100000 -> 100000 | J28: 1 | L28: 46288 | M28: =sumifs('SELLING CASH'!I:I,'SELLING CASH'!C:C,L28,'SELLING CASH'!R:R,"<>OIL")-(N28+O28+P28) -> 10125000 | N28: =sumifs('SELLING CASH'!N:N,'SELLING CASH'!C:C,L28,'SELLING CASH'!R:R,"<>SERVICE",'SELLING CASH'!R:R, "<>OIL") -> 1345000 | O28: =sumifs('SELLING CASH'!N:N,'SELLING CASH'!C:C,L28,'SELLING CASH'!R:R,"SERVICE") -> 835000 | P28: =sumif('SELLING CASH'!C:C,L28,'SELLING CASH'!J:J) -> 345000 | Q28: =SUMIF('PAYMENT CREDIT'!C:C,L28,'PAYMENT CREDIT'!F:F)-R28 -> 0 | R28: =SUMIF('PAYMENT CREDIT'!C:C,L28,'PAYMENT CREDIT'!G:G) -> 0 | S28: =M28+Q28 -> 10125000 | T28: =N28+R28 -> 1345000 | U28: =O28 -> 835000 | V28: =SUM(S28:U28) -> 12305000 | W28: =SUMIFS('SELLING CASH'!I:I,'SELLING CASH'!C:C,L28,'SELLING CASH'!R:R,"OIL") -> 1295000 | Y28: 75000 | Z28: 100000
D29: 45975 | E29: 350000 | G29: =J29*75000 -> 150000 | H29: =J29*100000 -> 200000 | J29: 2 | L29: 46289 | M29: =sumifs('SELLING CASH'!I:I,'SELLING CASH'!C:C,L29,'SELLING CASH'!R:R,"<>OIL")-(N29+O29+P29) -> 10840000 | N29: =sumifs('SELLING CASH'!N:N,'SELLING CASH'!C:C,L29,'SELLING CASH'!R:R,"<>SERVICE",'SELLING CASH'!R:R, "<>OIL") -> 1535000 | O29: =sumifs('SELLING CASH'!N:N,'SELLING CASH'!C:C,L29,'SELLING CASH'!R:R,"SERVICE") -> 540000 | P29: =sumif('SELLING CASH'!C:C,L29,'SELLING CASH'!J:J) -> 200000 | Q29: =SUMIF('PAYMENT CREDIT'!C:C,L29,'PAYMENT CREDIT'!F:F)-R29 -> 1980000 | R29: =SUMIF('PAYMENT CREDIT'!C:C,L29,'PAYMENT CREDIT'!G:G) -> 200000 | S29: =M29+Q29 -> 12820000 | T29: =N29+R29 -> 1735000 | U29: =O29 -> 540000 | V29: =SUM(S29:U29) -> 15095000 | W29: =SUMIFS('SELLING CASH'!I:I,'SELLING CASH'!C:C,L29,'SELLING CASH'!R:R,"OIL") -> 0
D30: 45978 | E30: =3*175000 -> 525000 | G30: =J30*75000 -> 225000 | H30: =J30*100000 -> 300000 | J30: 3 | L30: 46290 | M30: =sumifs('SELLING CASH'!I:I,'SELLING CASH'!C:C,L30,'SELLING CASH'!R:R,"<>OIL")-(N30+O30+P30) -> 12640000 | N30: =sumifs('SELLING CASH'!N:N,'SELLING CASH'!C:C,L30,'SELLING CASH'!R:R,"<>SERVICE",'SELLING CASH'!R:R, "<>OIL") -> 1485000 | O30: =sumifs('SELLING CASH'!N:N,'SELLING CASH'!C:C,L30,'SELLING CASH'!R:R,"SERVICE") -> 775000 | P30: =sumif('SELLING CASH'!C:C,L30,'SELLING CASH'!J:J) -> 125000 | Q30: =SUMIF('PAYMENT CREDIT'!C:C,L30,'PAYMENT CREDIT'!F:F)-R30 -> 0 | R30: =SUMIF('PAYMENT CREDIT'!C:C,L30,'PAYMENT CREDIT'!G:G) -> 0 | S30: =M30+Q30 -> 12640000 | T30: =N30+R30 -> 1485000 | U30: =O30 -> 775000 | V30: =SUM(S30:U30) -> 14900000 | W30: =SUMIFS('SELLING CASH'!I:I,'SELLING CASH'!C:C,L30,'SELLING CASH'!R:R,"OIL") -> 0
D31: 45978 | E31: 175000 | G31: =J31*75000 -> 75000 | H31: z | J31: 1 | L31: 46291 | M31: =sumifs('SELLING CASH'!I:I,'SELLING CASH'!C:C,L31,'SELLING CASH'!R:R,"<>OIL")-(N31+O31+P31) -> 0 | N31: =sumifs('SELLING CASH'!N:N,'SELLING CASH'!C:C,L31,'SELLING CASH'!R:R,"<>SERVICE",'SELLING CASH'!R:R, "<>OIL") -> 0 | O31: =sumifs('SELLING CASH'!N:N,'SELLING CASH'!C:C,L31,'SELLING CASH'!R:R,"SERVICE") -> 0 | P31: =sumif('SELLING CASH'!C:C,L31,'SELLING CASH'!J:J) -> 0 | Q31: =SUMIF('PAYMENT CREDIT'!C:C,L31,'PAYMENT CREDIT'!F:F)-R31 -> 0 | R31: =SUMIF('PAYMENT CREDIT'!C:C,L31,'PAYMENT CREDIT'!G:G) -> 0 | S31: =M31+Q31 -> 0 | T31: =N31+R31 -> 0 | U31: =O31 -> 0 | V31: =SUM(S31:U31) -> 0 | W31: =SUMIFS('SELLING CASH'!I:I,'SELLING CASH'!C:C,L31,'SELLING CASH'!R:R,"OIL") -> 0
D32: 45982 | E32: 175000 | G32: =J32*75000 -> 75000 | H32: =J32*100000 -> 100000 | J32: 1 | L32: 46292 | M32: =sumifs('SELLING CASH'!I:I,'SELLING CASH'!C:C,L32,'SELLING CASH'!R:R,"<>OIL")-(N32+O32+P32) -> 0 | N32: =sumifs('SELLING CASH'!N:N,'SELLING CASH'!C:C,L32,'SELLING CASH'!R:R,"<>SERVICE",'SELLING CASH'!R:R, "<>OIL") -> 0 | O32: =sumifs('SELLING CASH'!N:N,'SELLING CASH'!C:C,L32,'SELLING CASH'!R:R,"SERVICE") -> 0 | P32: =sumif('SELLING CASH'!C:C,L32,'SELLING CASH'!J:J) -> 0 | Q32: =SUMIF('PAYMENT CREDIT'!C:C,L32,'PAYMENT CREDIT'!F:F)-R32 -> 0 | R32: =SUMIF('PAYMENT CREDIT'!C:C,L32,'PAYMENT CREDIT'!G:G) -> 0 | S32: =M32+Q32 -> 0 | T32: =N32+R32 -> 0 | U32: =O32 -> 0 | V32: =SUM(S32:U32) -> 0 | W32: =SUMIFS('SELLING CASH'!I:I,'SELLING CASH'!C:C,L32,'SELLING CASH'!R:R,"OIL") -> 0
D33: 45983 | E33: 175000 | G33: =J33*75000 -> 75000 | H33: =J33*100000 -> 100000 | J33: 1 | L33: 46293 | M33: =sumifs('SELLING CASH'!I:I,'SELLING CASH'!C:C,L33,'SELLING CASH'!R:R,"<>OIL")-(N33+O33+P33) -> 0 | N33: =sumifs('SELLING CASH'!N:N,'SELLING CASH'!C:C,L33,'SELLING CASH'!R:R,"<>SERVICE",'SELLING CASH'!R:R, "<>OIL") -> 0 | O33: =sumifs('SELLING CASH'!N:N,'SELLING CASH'!C:C,L33,'SELLING CASH'!R:R,"SERVICE") -> 0 | P33: =sumif('SELLING CASH'!C:C,L33,'SELLING CASH'!J:J) -> 0 | Q33: =SUMIF('PAYMENT CREDIT'!C:C,L33,'PAYMENT CREDIT'!F:F)-R33 -> 0 | R33: =SUMIF('PAYMENT CREDIT'!C:C,L33,'PAYMENT CREDIT'!G:G) -> 0 | S33: =M33+Q33 -> 0 | T33: =N33+R33 -> 0 | U33: =O33 -> 0 | V33: =SUM(S33:U33) -> 0 | W33: =SUMIFS('SELLING CASH'!I:I,'SELLING CASH'!C:C,L33,'SELLING CASH'!R:R,"OIL") -> 0
D34: 45985 | E34: 200000 | G34: =J34*75000 -> 150000 | H34: =J34*100000 -> 200000 | J34: 2 | L34: 46294 | M34: =sumifs('SELLING CASH'!I:I,'SELLING CASH'!C:C,L34,'SELLING CASH'!R:R,"<>OIL")-(N34+O34+P34) -> 0 | N34: =sumifs('SELLING CASH'!N:N,'SELLING CASH'!C:C,L34,'SELLING CASH'!R:R,"<>SERVICE",'SELLING CASH'!R:R, "<>OIL") -> 0 | O34: =sumifs('SELLING CASH'!N:N,'SELLING CASH'!C:C,L34,'SELLING CASH'!R:R,"SERVICE") -> 0 | P34: =sumif('SELLING CASH'!C:C,L34,'SELLING CASH'!J:J) -> 0 | Q34: =SUMIF('PAYMENT CREDIT'!C:C,L34,'PAYMENT CREDIT'!F:F)-R34 -> 0 | R34: =SUMIF('PAYMENT CREDIT'!C:C,L34,'PAYMENT CREDIT'!G:G) -> 0 | S34: =M34+Q34 -> 0 | T34: =N34+R34 -> 0 | U34: =O34 -> 0 | V34: =SUM(S34:U34) -> 0 | W34: =SUMIFS('SELLING CASH'!I:I,'SELLING CASH'!C:C,L34,'SELLING CASH'!R:R,"OIL") -> 0
D35: 45986 | E35: 330000 | G35: 230000 | H35: =J35*100000 -> 100000 | J35: 1 | L35: 46295 | M35: =sumifs('SELLING CASH'!I:I,'SELLING CASH'!C:C,L35,'SELLING CASH'!R:R,"<>OIL")-(N35+O35+P35) -> 0 | N35: =sumifs('SELLING CASH'!N:N,'SELLING CASH'!C:C,L35,'SELLING CASH'!R:R,"<>SERVICE",'SELLING CASH'!R:R, "<>OIL") -> 0 | O35: =sumifs('SELLING CASH'!N:N,'SELLING CASH'!C:C,L35,'SELLING CASH'!R:R,"SERVICE") -> 0 | P35: =sumif('SELLING CASH'!C:C,L35,'SELLING CASH'!J:J) -> 0 | Q35: =SUMIF('PAYMENT CREDIT'!C:C,L35,'PAYMENT CREDIT'!F:F)-R35 -> 0 | R35: =SUMIF('PAYMENT CREDIT'!C:C,L35,'PAYMENT CREDIT'!G:G) -> 0 | S35: =M35+Q35 -> 0 | T35: =N35+R35 -> 0 | U35: =O35 -> 0 | V35: =SUM(S35:U35) -> 0 | W35: =SUMIFS('SELLING CASH'!I:I,'SELLING CASH'!C:C,L35,'SELLING CASH'!R:R,"OIL") -> 0
D36: 45987 | E36: 350000 | G36: =J36*75000 -> 150000 | H36: =J36*100000 -> 200000 | J36: 2 | M36: =sumifs('SELLING CASH'!I:I,'SELLING CASH'!C:C,L36,'SELLING CASH'!R:R,"<>OIL")-(N36+O36+P36) -> 0 | N36: =sumifs('SELLING CASH'!N:N,'SELLING CASH'!C:C,L36,'SELLING CASH'!R:R,"<>SERVICE",'SELLING CASH'!R:R, "<>OIL") -> 0 | O36: =sumifs('SELLING CASH'!N:N,'SELLING CASH'!C:C,L36,'SELLING CASH'!R:R,"SERVICE") -> 0 | P36: =sumif('SELLING CASH'!C:C,L36,'SELLING CASH'!J:J) -> 0 | Q36: =SUMIF('PAYMENT CREDIT'!C:C,L36,'PAYMENT CREDIT'!F:F)-R36 -> 0 | R36: =SUMIF('PAYMENT CREDIT'!C:C,L36,'PAYMENT CREDIT'!G:G) -> 0 | S36: =M36+Q36 -> 0 | T36: =N36+R36 -> 0 | U36: =O36 -> 0 | V36: =SUM(S36:U36) -> 0 | W36: =SUMIFS('SELLING CASH'!I:I,'SELLING CASH'!C:C,L36,'SELLING CASH'!R:R,"OIL") -> 0
D37: 45988 | E37: 325000 | G37: =J37*75000 -> 75000 | H37: =J37*100000 -> 100000 | J37: 1
D38: 45989 | E38: 350000 | G38: =J38*75000 -> 150000 | H38: =J38*100000 -> 200000 | J38: 2
D39: 45990 | E39: 330000 | G39: 230000 | H39: 100000 | J39: 1
D40: 45991 | E40: 175000 | G40: =J40*75000 -> 75000 | H40: =J40*100000 -> 100000 | J40: 1
D41: 45992 | E41: 820000 | G41: =E41-H41 -> 440000 | H41: =300000+80000 -> 380000 | J41: 3
D42: 45993 | E42: 1145000 | G42: =E42-H42 -> 910000 | H42: 235000
D43: 45995 | E43: 175000 | G43: 75000 | H43: 100000 | J43: 1 | K43: Laba ibu dipotongnya hari sabtu
D44: 45996 | E44: 175000 | G44: 75000 | H44: 100000 | J44: 1
D45: 45997 | E45: 325000 | G45: =J45*75000 -> 75000 | H45: =J45*100000 -> 100000 | J45: 1
D46: 45999 | E46: 800000 | G46: =E46-H46 -> 660000 | H46: 140000 | J46: 4
D47: 46001 | E47: 175000 | G47: 75000 | H47: 100000 | J47: 1
D48: 46002 | E48: 175000 | G48: 75000 | H48: 100000 | J48: 1
D49: 46003 | E49: 800000 | G49: 300000 | H49: 140000
D50: 46004 | E50: 175000 | G50: 75000 | H50: 100000 | J50: 1
D51: 46006 | E51: 175000 | G51: 75000 | H51: 100000 | J51: 1
D52: 46014 | E52: 175000 | G52: 75000 | H52: 100000 | J52: 1
D53: 46013 | E53: 175000 | G53: 75000 | H53: 100000 | J53: 1
D54: 46011 | E54: 200000 | G54: 145000 | H54: 55000 | J54: 1
D55: 46009 | E55: 150000 | G55: 150000
D56: 46008 | E56: 175000 | G56: 75000 | H56: 100000 | J56: 1
D57: 46007 | E57: 350000 | G57: =J57*75000 -> 150000 | H57: =J57*100000 -> 200000 | J57: 2
D58: 46015 | E58: 200000 | G58: 145000 | H58: 55000 | J58: 1
D59: 46018 | E59: 175000 | G59: 150000 | H59: 200000 | J59: 2
D60: 46020 | E60: 350000 | G60: 150000 | H60: 200000 | J60: 2
D61: 46021 | E61: 175000 | G61: 75000 | H61: 100000 | J61: 1
D62: 46025 | E62: 175000 | G62: 75000 | H62: 100000 | J62: 1
D63: 46026 | E63: 350000 | G63: 150000 | H63: 200000 | J63: 2
D64: 46027 | E64: 175000 | G64: 75000 | H64: 100000 | J64: 1
D65: 46028 | E65: 175000 | G65: 75000 | H65: 100000 | J65: 1
D66: 46036 | E66: 175000 | G66: 75000 | H66: 100000
D67: 46037 | E67: 175000 | G67: 75000 | H67: 100000
D68: 46038 | E68: 175000 | G68: 75000 | H68: 100000
D69: 46039 | E69: 175000 | G69: 75000 | H69: 100000
D70: 46043 | E70: 175000 | G70: 75000 | H70: 100000

Sheet DATABASE
C1: Item | D1: Size | E1: Tipe | F1: Brand | G1: Stock | H1: Selling Price | I1: Cost Price | J1: Owned by | K1: TAX | L1: Service Fee | M1: Category | N1: IN | O1: CASH | P1: Credit | Q1: FINAL | R1: =counta(F:F) -> 474 | V1: code | W1: Customer Name | X1: Credit | Y1: Payment | Z1: Out Standing Balance | AA1: =counta(V:V) -> 113 | AD1: D-0022 | AE1: Bapak Velg | AF1: Purchase | AG1: Payment | AH1: Out Standing Balance | AI1: =counta(AD:AD) -> 23
C2: Accelera 165/60 14 eco plush | D2: 165/60 14 | E2: eco plush | F2: Accelera | G2: 0 | H2: 535000 | I2: 431000 | J2: BIAN | K2: 1 | L2: 0 | M2: Tire | N2: =sumif(PURCHASE!I:I,C2,PURCHASE!J:J) -> 0 | O2: =sumif('SELLING CASH'!E:E,C2,'SELLING CASH'!F:F) -> 0 | P2: =sumif('SELLING CREDIT'!F:F,C2,'SELLING CREDIT'!G:G) -> 0 | Q2: =(N2+G2)-(O2+P2) -> 0 | V2: C-0001 | W2: Aartijaya Velvet | X2: =sumif('SELLING CREDIT'!E:E,W2,'SELLING CREDIT'!P:P) -> 60160000 | Y2: =sumif('PAYMENT CREDIT'!E:E,W2,'PAYMENT CREDIT'!F:F) -> 60220000 | Z2: =X2-Y2 -> -60000 | AC2: 1 | AD2: D-0001 | AE2: KHARISMA MAKMUR ABADI/PAK DADI | AF2: =sumif(PURCHASE!E:E,AE2,PURCHASE!N:N) -> 2476950800 | AG2: =sumif('PAYMENT SUPPLIER'!D:D,AE2,'PAYMENT SUPPLIER'!E:E)+sumifs(PURCHASE!N:N,PURCHASE!E:E,AE2,PURCHASE!M:M,"Cash") -> 2207165603 | AH2: =AF2-AG2 -> 269785197
C3: Accelera 165/65 13 | D3: 165/65 13 | F3: Accelera | G3: 0 | H3: 455000 | I3: 375000 | J3: BIAN | K3: 1 | L3: 0 | M3: Tire | N3: =sumif(PURCHASE!I:I,C3,PURCHASE!J:J) -> 0 | O3: =sumif('SELLING CASH'!E:E,C3,'SELLING CASH'!F:F) -> 0 | P3: =sumif('SELLING CREDIT'!F:F,C3,'SELLING CREDIT'!G:G) -> 0 | Q3: =(N3+G3)-(O3+P3) -> 0 | V3: C-0002 | W3: Bpk. Abah Agus/PACRT | X3: =sumif('SELLING CREDIT'!E:E,W3,'SELLING CREDIT'!P:P) -> 0 | Y3: =sumif('PAYMENT CREDIT'!E:E,W3,'PAYMENT CREDIT'!F:F) -> 0 | Z3: =X3-Y3 -> 0 | AC3: 1 | AD3: D-0002 | AE3: TS. SUDIRMAN/NAUFAL | AF3: =sumif(PURCHASE!E:E,AE3,PURCHASE!N:N) -> 1496642952 | AG3: =sumif('PAYMENT SUPPLIER'!D:D,AE3,'PAYMENT SUPPLIER'!E:E)+sumifs(PURCHASE!N:N,PURCHASE!E:E,AE3,PURCHASE!M:M,"Cash") -> 1350798512 | AH3: =AF3-AG3 -> 1.4584444e+08
C4: Accelera 165/80 13 | D4: 165/80 13 | F4: Accelera | G4: 0 | H4: 480000 | I4: 400000 | J4: BIAN | K4: 1 | L4: 0 | M4: Tire | N4: =sumif(PURCHASE!I:I,C4,PURCHASE!J:J) -> 0 | O4: =sumif('SELLING CASH'!E:E,C4,'SELLING CASH'!F:F) -> 0 | P4: =sumif('SELLING CREDIT'!F:F,C4,'SELLING CREDIT'!G:G) -> 0 | Q4: =(N4+G4)-(O4+P4) -> 0 | V4: C-0003 | W4: Bpk. Acep Cibeureum | X4: =sumif('SELLING CREDIT'!E:E,W4,'SELLING CREDIT'!P:P) -> 0 | Y4: =sumif('PAYMENT CREDIT'!E:E,W4,'PAYMENT CREDIT'!F:F) -> 0 | Z4: =X4-Y4 -> 0 | AC4: 1 | AD4: D-0003 | AE4: CV. MEKAR BARU/CI NOVI | AF4: =sumif(PURCHASE!E:E,AE4,PURCHASE!N:N) -> 783659910 | AG4: =sumif('PAYMENT SUPPLIER'!D:D,AE4,'PAYMENT SUPPLIER'!E:E)+sumifs(PURCHASE!N:N,PURCHASE!E:E,AE4,PURCHASE!M:M,"Cash") -> 746139510 | AH4: =AF4-AG4 -> 37520400
C5: Accelera 175/13 | D5: 175/13 | F5: Accelera | G5: 1 | H5: 640000 | I5: 531000 | J5: BIAN | K5: 1 | L5: 0 | M5: Tire | N5: =sumif(PURCHASE!I:I,C5,PURCHASE!J:J) -> 0 | O5: =sumif('SELLING CASH'!E:E,C5,'SELLING CASH'!F:F) -> 0 | P5: =sumif('SELLING CREDIT'!F:F,C5,'SELLING CREDIT'!G:G) -> 0 | Q5: =(N5+G5)-(O5+P5) -> 1 | V5: C-0004 | W5: Bpk. Aden Fahri/Cibeureum | X5: =sumif('SELLING CREDIT'!E:E,W5,'SELLING CREDIT'!P:P) -> 43810000 | Y5: =sumif('PAYMENT CREDIT'!E:E,W5,'PAYMENT CREDIT'!F:F) -> 42070000 | Z5: =X5-Y5 -> 1740000 | AC5: 1 | AD5: D-0004 | AE5: SAMUDERA GEMILANG/PAK KEMAN | AF5: =sumif(PURCHASE!E:E,AE5,PURCHASE!N:N) -> 1460388496 | AG5: =sumif('PAYMENT SUPPLIER'!D:D,AE5,'PAYMENT SUPPLIER'!E:E)+sumifs(PURCHASE!N:N,PURCHASE!E:E,AE5,PURCHASE!M:M,"Cash") -> 1323087976 | AH5: =AF5-AG5 -> 137300520
C6: Accelera 175/65 14 | D6: 175/65 14 | F6: Accelera | G6: 0 | H6: 520000 | I6: 435000 | J6: BIAN | K6: 1 | L6: 0 | M6: Tire | N6: =sumif(PURCHASE!I:I,C6,PURCHASE!J:J) -> 0 | O6: =sumif('SELLING CASH'!E:E,C6,'SELLING CASH'!F:F) -> 6 | P6: =sumif('SELLING CREDIT'!F:F,C6,'SELLING CREDIT'!G:G) -> 0 | Q6: =(N6+G6)-(O6+P6) -> -6 | V6: C-0005 | W6: Bpk. Adin Texas/Balekambang | X6: =sumif('SELLING CREDIT'!E:E,W6,'SELLING CREDIT'!P:P) -> 57435000 | Y6: =sumif('PAYMENT CREDIT'!E:E,W6,'PAYMENT CREDIT'!F:F) -> 57665000 | Z6: =X6-Y6 -> -230000 | AC6: 1 | AD6: D-0005 | AE6: MAJU BERSAMA MOTOR/ANDRI | AF6: =sumif(PURCHASE!E:E,AE6,PURCHASE!N:N) -> 7588800 | AG6: =sumif('PAYMENT SUPPLIER'!D:D,AE6,'PAYMENT SUPPLIER'!E:E)+sumifs(PURCHASE!N:N,PURCHASE!E:E,AE6,PURCHASE!M:M,"Cash") -> 7588800 | AH6: =AF6-AG6 -> 0
C7: Accelera 175/70 13 | D7: 175/70 13 | F7: Accelera | G7: 0 | H7: 475000 | I7: 395000 | J7: BIAN | K7: 1 | L7: 0 | M7: Tire | N7: =sumif(PURCHASE!I:I,C7,PURCHASE!J:J) -> 0 | O7: =sumif('SELLING CASH'!E:E,C7,'SELLING CASH'!F:F) -> 0 | P7: =sumif('SELLING CREDIT'!F:F,C7,'SELLING CREDIT'!G:G) -> 0 | Q7: =(N7+G7)-(O7+P7) -> 0 | V7: C-0006 | W7: Bpk. Agus Antasalam | X7: =sumif('SELLING CREDIT'!E:E,W7,'SELLING CREDIT'!P:P) -> 22030000 | Y7: =sumif('PAYMENT CREDIT'!E:E,W7,'PAYMENT CREDIT'!F:F) -> 22030000 | Z7: =X7-Y7 -> 0 | AC7: 1 | AD7: D-0006 | AE7: MUSTIKA ADI SEJAHTERA/PAK TEDDY | AF7: =sumif(PURCHASE!E:E,AE7,PURCHASE!N:N) -> 0 | AG7: =sumif('PAYMENT SUPPLIER'!D:D,AE7,'PAYMENT SUPPLIER'!E:E)+sumifs(PURCHASE!N:N,PURCHASE!E:E,AE7,PURCHASE!M:M,"Cash") -> 34845000 | AH7: =AF7-AG7 -> -34845000
C8: Accelera 185/14 | D8: 185/14 | F8: Accelera | G8: 0 | H8: 700000 | I8: 600000 | J8: BIAN | K8: 1 | L8: 0 | M8: Tire | N8: =sumif(PURCHASE!I:I,C8,PURCHASE!J:J) -> 0 | O8: =sumif('SELLING CASH'!E:E,C8,'SELLING CASH'!F:F) -> 0 | P8: =sumif('SELLING CREDIT'!F:F,C8,'SELLING CREDIT'!G:G) -> 0 | Q8: =(N8+G8)-(O8+P8) -> 0 | V8: C-0007 | W8: Bpk. Aji Cibodas Solokan jeruk | X8: =sumif('SELLING CREDIT'!E:E,W8,'SELLING CREDIT'!P:P) -> 0 | Y8: =sumif('PAYMENT CREDIT'!E:E,W8,'PAYMENT CREDIT'!F:F) -> 0 | Z8: =X8-Y8 -> 0 | AC8: 1 | AD8: D-0007 | AE8: CV. KHARISMA TIARA ABADI/DICKY | AF8: =sumif(PURCHASE!E:E,AE8,PURCHASE!N:N) -> 38011500 | AG8: =sumif('PAYMENT SUPPLIER'!D:D,AE8,'PAYMENT SUPPLIER'!E:E)+sumifs(PURCHASE!N:N,PURCHASE!E:E,AE8,PURCHASE!M:M,"Cash") -> 38011500 | AH8: =AF8-AG8 -> 0
C9: Accelera 185/70 14 | D9: 185/70 14 | F9: Accelera | G9: 10 | H9: 600000 | I9: 483960 | J9: BIAN | K9: 1 | L9: 0 | M9: Tire | N9: =sumif(PURCHASE!I:I,C9,PURCHASE!J:J) -> 0 | O9: =sumif('SELLING CASH'!E:E,C9,'SELLING CASH'!F:F) -> 10 | P9: =sumif('SELLING CREDIT'!F:F,C9,'SELLING CREDIT'!G:G) -> 0 | Q9: =(N9+G9)-(O9+P9) -> 0 | V9: C-0008 | W9: Bpk. Amal Cikawao | X9: =sumif('SELLING CREDIT'!E:E,W9,'SELLING CREDIT'!P:P) -> 4500000 | Y9: =sumif('PAYMENT CREDIT'!E:E,W9,'PAYMENT CREDIT'!F:F) -> 4500000 | Z9: =X9-Y9 -> 0 | AC9: 1 | AD9: D-0008 | AE9: PT. INDOTYRE MANDIRI SENTOSA | AF9: =sumif(PURCHASE!E:E,AE9,PURCHASE!N:N) -> 2457540 | AG9: =sumif('PAYMENT SUPPLIER'!D:D,AE9,'PAYMENT SUPPLIER'!E:E)+sumifs(PURCHASE!N:N,PURCHASE!E:E,AE9,PURCHASE!M:M,"Cash") -> 2457540 | AH9: =AF9-AG9 -> 0
C10: Accelera 195/15 | D10: 195/15 | F10: Accelera | G10: 3 | H10: 820000 | I10: 730000 | J10: BIAN | K10: 1 | L10: 0 | M10: Tire | N10: =sumif(PURCHASE!I:I,C10,PURCHASE!J:J) -> 0 | O10: =sumif('SELLING CASH'!E:E,C10,'SELLING CASH'!F:F) -> 0 | P10: =sumif('SELLING CREDIT'!F:F,C10,'SELLING CREDIT'!G:G) -> 0 | Q10: =(N10+G10)-(O10+P10) -> 3 | V10: C-0009 | W10: Bpk. Asep PSB/CIbeureum | X10: =sumif('SELLING CREDIT'!E:E,W10,'SELLING CREDIT'!P:P) -> 0 | Y10: =sumif('PAYMENT CREDIT'!E:E,W10,'PAYMENT CREDIT'!F:F) -> 0 | Z10: =X10-Y10 -> 0 | AC10: 1 | AD10: D-0009 | AE10: CV. MULTIPRIMA INTI NUSANTARA | AF10: =sumif(PURCHASE!E:E,AE10,PURCHASE!N:N) -> 107077000 | AG10: =sumif('PAYMENT SUPPLIER'!D:D,AE10,'PAYMENT SUPPLIER'!E:E)+sumifs(PURCHASE!N:N,PURCHASE!E:E,AE10,PURCHASE!M:M,"Cash") -> 107077000 | AH10: =AF10-AG10 -> 0
C11: Accelera 205/40 17 | D11: 205/40 17 | F11: Accelera | G11: 0 | H11: 820000 | I11: 690000 | J11: BIAN | K11: 1 | L11: 0 | M11: Tire | N11: =sumif(PURCHASE!I:I,C11,PURCHASE!J:J) -> 0 | O11: =sumif('SELLING CASH'!E:E,C11,'SELLING CASH'!F:F) -> 0 | P11: =sumif('SELLING CREDIT'!F:F,C11,'SELLING CREDIT'!G:G) -> 0 | Q11: =(N11+G11)-(O11+P11) -> 0 | V11: C-0010 | W11: Bpk. Bram | X11: =sumif('SELLING CREDIT'!E:E,W11,'SELLING CREDIT'!P:P) -> 37170000 | Y11: =sumif('PAYMENT CREDIT'!E:E,W11,'PAYMENT CREDIT'!F:F) -> 37270000 | Z11: =X11-Y11 -> -100000 | AC11: 1 | AD11: D-0010 | AE11: PT. DIRGAPUTRA EKAPRATAMA | AF11: =sumif(PURCHASE!E:E,AE11,PURCHASE!N:N) -> 68524013 | AG11: =sumif('PAYMENT SUPPLIER'!D:D,AE11,'PAYMENT SUPPLIER'!E:E)+sumifs(PURCHASE!N:N,PURCHASE!E:E,AE11,PURCHASE!M:M,"Cash") -> 57836381 | AH11: =AF11-AG11 -> 10687632
C12: ACCELERA 215/35 18 SIGMA | D12: 215/35 18 | E12: SIGMA | F12: ACCELERA | G12: 0 | H12: 870000 | I12: 760239 | J12: BIAN | K12: 1 | L12: 0 | M12: Tire | N12: =sumif(PURCHASE!I:I,C12,PURCHASE!J:J) -> 1 | O12: =sumif('SELLING CASH'!E:E,C12,'SELLING CASH'!F:F) -> 1 | P12: =sumif('SELLING CREDIT'!F:F,C12,'SELLING CREDIT'!G:G) -> 0 | Q12: =(N12+G12)-(O12+P12) -> 0 | V12: C-0011 | W12: Bpk. Cuplis | X12: =sumif('SELLING CREDIT'!E:E,W12,'SELLING CREDIT'!P:P) -> 26690000 | Y12: =sumif('PAYMENT CREDIT'!E:E,W12,'PAYMENT CREDIT'!F:F) -> 23840000 | Z12: =X12-Y12 -> 2850000 | AC12: 1 | AD12: D-0011 | AE12: CV. MEKAR PRATAMA BAN | AF12: =sumif(PURCHASE!E:E,AE12,PURCHASE!N:N) -> 0 | AG12: =sumif('PAYMENT SUPPLIER'!D:D,AE12,'PAYMENT SUPPLIER'!E:E)+sumifs(PURCHASE!N:N,PURCHASE!E:E,AE12,PURCHASE!M:M,"Cash") -> 0 | AH12: =AF12-AG12 -> 0
C13: Accelera 215/55 17 | D13: 215/55 17 | F13: Accelera | G13: 0 | H13: 930000 | I13: 805000 | J13: BIAN | K13: 1 | L13: 0 | M13: Tire | N13: =sumif(PURCHASE!I:I,C13,PURCHASE!J:J) -> 1 | O13: =sumif('SELLING CASH'!E:E,C13,'SELLING CASH'!F:F) -> 1 | P13: =sumif('SELLING CREDIT'!F:F,C13,'SELLING CREDIT'!G:G) -> 0 | Q13: =(N13+G13)-(O13+P13) -> 0 | V13: C-0012 | W13: Bpk. Dani Darmawan/Garduh Jaya | X13: =sumif('SELLING CREDIT'!E:E,W13,'SELLING CREDIT'!P:P) -> 33145000 | Y13: =sumif('PAYMENT CREDIT'!E:E,W13,'PAYMENT CREDIT'!F:F) -> 33145000 | Z13: =X13-Y13 -> 0 | AC13: 1 | AD13: D-0012 | AE13: PT. Astra Otoparts Tbk | AF13: =sumif(PURCHASE!E:E,AE13,PURCHASE!N:N) -> 11909978 | AG13: =sumif('PAYMENT SUPPLIER'!D:D,AE13,'PAYMENT SUPPLIER'!E:E)+sumifs(PURCHASE!N:N,PURCHASE!E:E,AE13,PURCHASE!M:M,"Cash") -> 12288515 | AH13: =AF13-AG13 -> -378537
C14: Accelera 225/40 19 | D14: 225/40 19 | F14: Accelera | G14: 0 | H14: 1270000 | I14: 1117000 | J14: BIAN | K14: 1 | L14: 0 | M14: Tire | N14: =sumif(PURCHASE!I:I,C14,PURCHASE!J:J) -> 0 | O14: =sumif('SELLING CASH'!E:E,C14,'SELLING CASH'!F:F) -> 0 | P14: =sumif('SELLING CREDIT'!F:F,C14,'SELLING CREDIT'!G:G) -> 0 | Q14: =(N14+G14)-(O14+P14) -> 0 | V14: C-0013 | W14: Bpk. Dani Jembar Mukti | X14: =sumif('SELLING CREDIT'!E:E,W14,'SELLING CREDIT'!P:P) -> 18830000 | Y14: =sumif('PAYMENT CREDIT'!E:E,W14,'PAYMENT CREDIT'!F:F) -> 18830000 | Z14: =X14-Y14 -> 0 | AC14: 1 | AD14: D-0013 | AE14: PT. DAYTECH TETRA SINDO | AF14: =sumif(PURCHASE!E:E,AE14,PURCHASE!N:N) -> 3683000 | AG14: =sumif('PAYMENT SUPPLIER'!D:D,AE14,'PAYMENT SUPPLIER'!E:E)+sumifs(PURCHASE!N:N,PURCHASE!E:E,AE14,PURCHASE!M:M,"Cash") -> 3683000 | AH14: =AF14-AG14 -> 0
C15: Accelera 235/75 15 at omicron | D15: 235/75 15 | E15: omicron at | F15: Accelera | G15: 0 | H15: 1040000 | I15: 920000 | J15: BIAN | K15: 1 | L15: 0 | M15: Tire | N15: =sumif(PURCHASE!I:I,C15,PURCHASE!J:J) -> 1 | O15: =sumif('SELLING CASH'!E:E,C15,'SELLING CASH'!F:F) -> 1 | P15: =sumif('SELLING CREDIT'!F:F,C15,'SELLING CREDIT'!G:G) -> 0 | Q15: =(N15+G15)-(O15+P15) -> 0 | V15: C-0014 | W15: Bpk. Dede DP/Pasanggrahan | X15: =sumif('SELLING CREDIT'!E:E,W15,'SELLING CREDIT'!P:P) -> 10180000 | Y15: =sumif('PAYMENT CREDIT'!E:E,W15,'PAYMENT CREDIT'!F:F) -> 10180000 | Z15: =X15-Y15 -> 0 | AC15: 1 | AD15: D-0014 | AE15: PT. RODA ARTHA | AF15: =sumif(PURCHASE!E:E,AE15,PURCHASE!N:N) -> 1181180000 | AG15: =sumif('PAYMENT SUPPLIER'!D:D,AE15,'PAYMENT SUPPLIER'!E:E)+sumifs(PURCHASE!N:N,PURCHASE!E:E,AE15,PURCHASE!M:M,"Cash") -> 977975000 | AH15: =AF15-AG15 -> 203205000
C16: =F16&" "&D16&" "&E16 -> Advance 1000/20 GL662A+ | D16: 1000/20 | E16: GL662A+ | F16: Advance | G16: 0 | H16: 4450000 | I16: 4200000 | J16: BIAN | K16: 1 | L16: 0 | M16: Tire | N16: =sumif(PURCHASE!I:I,C16,PURCHASE!J:J) -> 5 | O16: =sumif('SELLING CASH'!E:E,C16,'SELLING CASH'!F:F) -> 6 | P16: =sumif('SELLING CREDIT'!F:F,C16,'SELLING CREDIT'!G:G) -> 0 | Q16: =(N16+G16)-(O16+P16) -> -1 | V16: C-0015 | W16: Bpk. Deden Putra Walahir | X16: =sumif('SELLING CREDIT'!E:E,W16,'SELLING CREDIT'!P:P) -> 77230000 | Y16: =sumif('PAYMENT CREDIT'!E:E,W16,'PAYMENT CREDIT'!F:F) -> 74690000 | Z16: =X16-Y16 -> 2540000 | AC16: 1 | AD16: D-0015 | AE16: PT. RODA GAMA | AF16: =sumif(PURCHASE!E:E,AE16,PURCHASE!N:N) -> 53192000 | AG16: =sumif('PAYMENT SUPPLIER'!D:D,AE16,'PAYMENT SUPPLIER'!E:E)+sumifs(PURCHASE!N:N,PURCHASE!E:E,AE16,PURCHASE!M:M,"Cash") -> 54948000 | AH16: =AF16-AG16 -> -1756000
C17: Advance 750/15 radial fullset | D17: 750/15 | E17: radial fullset | F17: Advance | G17: 0 | H17: 1865000 | I17: 1765000 | J17: BIAN | K17: 1 | L17: 0 | M17: Tire | N17: =sumif(PURCHASE!I:I,C17,PURCHASE!J:J) -> 2 | O17: =sumif('SELLING CASH'!E:E,C17,'SELLING CASH'!F:F) -> 2 | P17: =sumif('SELLING CREDIT'!F:F,C17,'SELLING CREDIT'!G:G) -> 1 | Q17: =(N17+G17)-(O17+P17) -> -1 | V17: C-0016 | W17: Bpk. Deden Putra Walahir | X17: =sumif('SELLING CREDIT'!E:E,W17,'SELLING CREDIT'!P:P) -> 77230000 | Y17: =sumif('PAYMENT CREDIT'!E:E,W17,'PAYMENT CREDIT'!F:F) -> 74690000 | Z17: =X17-Y17 -> 2540000 | AC17: 1 | AD17: D-0016 | AE17: PT. VETRON SAILUN | AF17: =sumif(PURCHASE!E:E,AE17,PURCHASE!N:N) -> 61608400 | AG17: =sumif('PAYMENT SUPPLIER'!D:D,AE17,'PAYMENT SUPPLIER'!E:E)+sumifs(PURCHASE!N:N,PURCHASE!E:E,AE17,PURCHASE!M:M,"Cash") -> 57448400 | AH17: =AF17-AG17 -> 4160000
C18: ADVANCE 750/16 GL279A+ CACING | D18: 750/16 | E18: GL279A+ CACING | F18: ADVANCE | G18: 1 | H18: 1950000 | I18: 1840000 | J18: BIAN | K18: 1 | L18: 0 | M18: Tire | N18: =sumif(PURCHASE!I:I,C18,PURCHASE!J:J) -> 0 | O18: =sumif('SELLING CASH'!E:E,C18,'SELLING CASH'!F:F) -> 1 | P18: =sumif('SELLING CREDIT'!F:F,C18,'SELLING CREDIT'!G:G) -> 0 | Q18: =(N18+G18)-(O18+P18) -> 0 | V18: C-0017 | W18: Bpk. Dedi CRW | X18: =sumif('SELLING CREDIT'!E:E,W18,'SELLING CREDIT'!P:P) -> 6170000 | Y18: =sumif('PAYMENT CREDIT'!E:E,W18,'PAYMENT CREDIT'!F:F) -> 6170000 | Z18: =X18-Y18 -> 0 | AC18: 1 | AD18: D-0017 | AE18: PT BANCORE SENTRAL UTAMA | AF18: =sumif(PURCHASE!E:E,AE18,PURCHASE!N:N) -> 71382000 | AG18: =sumif('PAYMENT SUPPLIER'!D:D,AE18,'PAYMENT SUPPLIER'!E:E)+sumifs(PURCHASE!N:N,PURCHASE!E:E,AE18,PURCHASE!M:M,"Cash") -> 62414000 | AH18: =AF18-AG18 -> 8968000
C19: Advance 750/16 GL672D | D19: 750/16 | E19: G72D | F19: Advance | G19: 4 | H19: 2080000 | I19: 1980000 | J19: BIAN | K19: 1 | L19: 0 | M19: Tire | N19: =sumif(PURCHASE!I:I,C19,PURCHASE!J:J) -> 135 | O19: =sumif('SELLING CASH'!E:E,C19,'SELLING CASH'!F:F) -> 31 | P19: =sumif('SELLING CREDIT'!F:F,C19,'SELLING CREDIT'!G:G) -> 115 | Q19: =(N19+G19)-(O19+P19) -> -7 | V19: C-0018 | W19: Bpk. Dinar Sudi | X19: =sumif('SELLING CREDIT'!E:E,W19,'SELLING CREDIT'!P:P) -> 31250000 | Y19: =sumif('PAYMENT CREDIT'!E:E,W19,'PAYMENT CREDIT'!F:F) -> 31250000 | Z19: =X19-Y19 -> 0 | AC19: 1 | AD19: D-0018 | AE19: PT. Prestasi Pelumasindo Unggul | AF19: =sumif(PURCHASE!E:E,AE19,PURCHASE!N:N) -> 90698229 | AG19: =sumif('PAYMENT SUPPLIER'!D:D,AE19,'PAYMENT SUPPLIER'!E:E)+sumifs(PURCHASE!N:N,PURCHASE!E:E,AE19,PURCHASE!M:M,"Cash") -> 20137800 | AH19: =AF19-AG19 -> 70560429
C20: Advance 750/16 GLG71A+ | D20: 750/16 | E20: GL71A+ | F20: Advance | G20: 8 | H20: 1985000 | I20: 1885000 | J20: BIAN | K20: 1 | L20: 0 | M20: Tire | N20: =sumif(PURCHASE!I:I,C20,PURCHASE!J:J) -> 113 | O20: =sumif('SELLING CASH'!E:E,C20,'SELLING CASH'!F:F) -> 40 | P20: =sumif('SELLING CREDIT'!F:F,C20,'SELLING CREDIT'!G:G) -> 81 | Q20: =(N20+G20)-(O20+P20) -> 0 | V20: C-0019 | W20: Bpk. Dudung Cikoneng | X20: =sumif('SELLING CREDIT'!E:E,W20,'SELLING CREDIT'!P:P) -> 10195000 | Y20: =sumif('PAYMENT CREDIT'!E:E,W20,'PAYMENT CREDIT'!F:F) -> 10195000 | Z20: =X20-Y20 -> 0 | AC20: 1 | AD20: D-0019 | AE20: PT. Limas Raga Inti | AF20: =sumif(PURCHASE!E:E,AE20,PURCHASE!N:N) -> 11745923 | AG20: =sumif('PAYMENT SUPPLIER'!D:D,AE20,'PAYMENT SUPPLIER'!E:E)+sumifs(PURCHASE!N:N,PURCHASE!E:E,AE20,PURCHASE!M:M,"Cash") -> 9760000 | AH20: =AF20-AG20 -> 1985923.1
C21: Advance 750/16 k. tahu GL909A | D21: 750/16 | E21: GL909A | F21: Advance | G21: 12 | H21: 2260000 | I21: 2160000 | J21: BIAN | K21: 1 | L21: 0 | M21: Tire | N21: =sumif(PURCHASE!I:I,C21,PURCHASE!J:J) -> 152 | O21: =sumif('SELLING CASH'!E:E,C21,'SELLING CASH'!F:F) -> 28 | P21: =sumif('SELLING CREDIT'!F:F,C21,'SELLING CREDIT'!G:G) -> 126 | Q21: =(N21+G21)-(O21+P21) -> 10 | V21: C-0020 | W21: Bpk. Egi/Ganjar Pasirkukun | X21: =sumif('SELLING CREDIT'!E:E,W21,'SELLING CREDIT'!P:P) -> 7750000 | Y21: =sumif('PAYMENT CREDIT'!E:E,W21,'PAYMENT CREDIT'!F:F) -> 5950000 | Z21: =X21-Y21 -> 1800000 | AC21: 1 | AD21: D-0020 | AE21: Pak Wang Pentil | AF21: =sumif(PURCHASE!E:E,AE21,PURCHASE!N:N) -> 13942000 | AG21: =sumif('PAYMENT SUPPLIER'!D:D,AE21,'PAYMENT SUPPLIER'!E:E)+sumifs(PURCHASE!N:N,PURCHASE!E:E,AE21,PURCHASE!M:M,"Cash") -> 18149500 | AH21: =AF21-AG21 -> -4207500
C22: Aeolus 750/16 | D22: 750/16 | F22: Aeolus | G22: 0 | H22: 2200000 | I22: 2050000 | J22: BIAN | K22: 0 | L22: 0 | M22: Tire | N22: =sumif(PURCHASE!I:I,C22,PURCHASE!J:J) -> 0 | O22: =sumif('SELLING CASH'!E:E,C22,'SELLING CASH'!F:F) -> 0 | P22: =sumif('SELLING CREDIT'!F:F,C22,'SELLING CREDIT'!G:G) -> 0 | Q22: =(N22+G22)-(O22+P22) -> 0 | V22: C-0021 | W22: Bpk. Endang RSJ Sudi | X22: =sumif('SELLING CREDIT'!E:E,W22,'SELLING CREDIT'!P:P) -> 62285000 | Y22: =sumif('PAYMENT CREDIT'!E:E,W22,'PAYMENT CREDIT'!F:F) -> 64055000 | Z22: =X22-Y22 -> -1770000 | AC22: 1 | AD22: D-0021 | AE22: PT. Arta Batrindo | AF22: =sumif(PURCHASE!E:E,AE22,PURCHASE!N:N) -> 5000000 | AG22: =sumif('PAYMENT SUPPLIER'!D:D,AE22,'PAYMENT SUPPLIER'!E:E)+sumifs(PURCHASE!N:N,PURCHASE!E:E,AE22,PURCHASE!M:M,"Cash") -> 5000000 | AH22: =AF22-AG22 -> 0
C23: =F23&" "&D23&" "&E23 -> Aspira Filter Oli Avaza-Agya | E23: Filter Oli Avaza-Agya | F23: Aspira | G23: 0 | H23: 25000 | I23: 19200 | J23: BIAN | K23: 0 | L23: 0 | M23: COMPLEMENTARY | N23: =sumif(PURCHASE!I:I,C23,PURCHASE!J:J) -> 20 | O23: =sumif('SELLING CASH'!E:E,C23,'SELLING CASH'!F:F) -> 56 | P23: =sumif('SELLING CREDIT'!F:F,C23,'SELLING CREDIT'!G:G) -> 0 | Q23: =(N23+G23)-(O23+P23) -> -36 | V23: C-0022 | W23: Bpk. Eye | X23: =sumif('SELLING CREDIT'!E:E,W23,'SELLING CREDIT'!P:P) -> 3495000 | Y23: =sumif('PAYMENT CREDIT'!E:E,W23,'PAYMENT CREDIT'!F:F) -> 2985000 | Z23: =X23-Y23 -> 510000 | AD23: D-0022 | AE23: SURYA LESTARI/PAK IWAN | AF23: =sumif(PURCHASE!E:E,AE23,PURCHASE!N:N) -> 5159200 | AG23: =sumif('PAYMENT SUPPLIER'!D:D,AE23,'PAYMENT SUPPLIER'!E:E)+sumifs(PURCHASE!N:N,PURCHASE!E:E,AE23,PURCHASE!O:O,"LUNAS") -> 3813500 | AH23: =AF23-AG23 -> 1345700
C24: Aspira 750/16 Halus | D24: 750/16 | E24: Halus | F24: Aspira | G24: 0 | H24: 1730000 | I24: 1610000 | J24: BIAN | K24: 0 | L24: 0 | M24: Tire | N24: =sumif(PURCHASE!I:I,C24,PURCHASE!J:J) -> 2 | O24: =sumif('SELLING CASH'!E:E,C24,'SELLING CASH'!F:F) -> 0 | P24: =sumif('SELLING CREDIT'!F:F,C24,'SELLING CREDIT'!G:G) -> 3 | Q24: =(N24+G24)-(O24+P24) -> -1 | V24: C-0023 | W24: Bpk. Fauzan | X24: =sumif('SELLING CREDIT'!E:E,W24,'SELLING CREDIT'!P:P) -> 0 | Y24: =sumif('PAYMENT CREDIT'!E:E,W24,'PAYMENT CREDIT'!F:F) -> 0 | Z24: =X24-Y24 -> 0
C25: Aspira 750/16 Kasar | D25: 750/16 | E25: Kasar | F25: Aspira | G25: 0 | H25: 1850000 | I25: 1725000 | J25: BIAN | K25: 0 | L25: 0 | M25: Tire | N25: =sumif(PURCHASE!I:I,C25,PURCHASE!J:J) -> 0 | O25: =sumif('SELLING CASH'!E:E,C25,'SELLING CASH'!F:F) -> 1 | P25: =sumif('SELLING CREDIT'!F:F,C25,'SELLING CREDIT'!G:G) -> 1 | Q25: =(N25+G25)-(O25+P25) -> -2 | V25: C-0024 | W25: Bpk. H Entang | X25: =sumif('SELLING CREDIT'!E:E,W25,'SELLING CREDIT'!P:P) -> 70800000 | Y25: =sumif('PAYMENT CREDIT'!E:E,W25,'PAYMENT CREDIT'!F:F) -> 68210000 | Z25: =X25-Y25 -> 2590000
C26: Balancing 30 | D26: - | F26: Balancing | G26: 100000 | H26: 30000 | I26: 10000 | J26: BIAN | K26: 0 | L26: 0 | M26: COMPLEMENTARY | N26: =sumif(PURCHASE!I:I,C26,PURCHASE!J:J) -> 205 | O26: =sumif('SELLING CASH'!E:E,C26,'SELLING CASH'!F:F) -> 1858 | P26: =sumif('SELLING CREDIT'!F:F,C26,'SELLING CREDIT'!G:G) -> 12 | Q26: =(N26+G26)-(O26+P26) -> 98335 | V26: C-0025 | W26: Bpk. H Odang Pelered | X26: =sumif('SELLING CREDIT'!E:E,W26,'SELLING CREDIT'!P:P) -> 6855000 | Y26: =sumif('PAYMENT CREDIT'!E:E,W26,'PAYMENT CREDIT'!F:F) -> 5975000 | Z26: =X26-Y26 -> 880000
C27: Balancing 60 | D27: -- | F27: Balancing | G27: 9997344 | H27: 60000 | I27: 15000 | J27: BIAN | K27: 0 | L27: 0 | M27: COMPLEMENTARY | N27: =sumif(PURCHASE!I:I,C27,PURCHASE!J:J) -> 0 | O27: =sumif('SELLING CASH'!E:E,C27,'SELLING CASH'!F:F) -> 21 | P27: =sumif('SELLING CREDIT'!F:F,C27,'SELLING CREDIT'!G:G) -> 4 | Q27: =(N27+G27)-(O27+P27) -> 9997319 | V27: C-0026 | W27: Bpk. H. Alit Cibeureum | X27: =sumif('SELLING CREDIT'!E:E,W27,'SELLING CREDIT'!P:P) -> 10980000 | Y27: =sumif('PAYMENT CREDIT'!E:E,W27,'PAYMENT CREDIT'!F:F) -> 10980000 | Z27: =X27-Y27 -> 0
C28: Baut Camber | D28: - | F28: Baut Camber | G28: 360 | H28: 250000 | I28: 75000 | J28: BIAN | K28: 0 | L28: 75000 | M28: COMPLEMENTARY | N28: =sumif(PURCHASE!I:I,C28,PURCHASE!J:J) -> 259 | O28: =sumif('SELLING CASH'!E:E,C28,'SELLING CASH'!F:F) -> 585 | P28: =sumif('SELLING CREDIT'!F:F,C28,'SELLING CREDIT'!G:G) -> 2 | Q28: =(N28+G28)-(O28+P28) -> 32 | V28: C-0027 | W28: Bpk. H. Amin Cibeureum | X28: =sumif('SELLING CREDIT'!E:E,W28,'SELLING CREDIT'!P:P) -> 99660000 | Y28: =sumif('PAYMENT CREDIT'!E:E,W28,'PAYMENT CREDIT'!F:F) -> 99660000 | Z28: =X28-Y28 -> 0
C29: Baut Camber 17 | D29: - | F29: Baut Camber 17 | G29: 999285 | H29: 250000 | I29: 75000 | J29: BIAN | K29: 0 | L29: 75000 | M29: COMPLEMENTARY | N29: =sumif(PURCHASE!I:I,C29,PURCHASE!J:J) -> 0 | O29: =sumif('SELLING CASH'!E:E,C29,'SELLING CASH'!F:F) -> 0 | P29: =sumif('SELLING CREDIT'!F:F,C29,'SELLING CREDIT'!G:G) -> 0 | Q29: =(N29+G29)-(O29+P29) -> 999285 | V29: C-0028 | W29: Bpk. H. Anang/Ciparay barujati | X29: =sumif('SELLING CREDIT'!E:E,W29,'SELLING CREDIT'!P:P) -> 2010000 | Y29: =sumif('PAYMENT CREDIT'!E:E,W29,'PAYMENT CREDIT'!F:F) -> 2010000 | Z29: =X29-Y29 -> 0
C30: Baut Camber ss-carry | D30: - | F30: Baut Camber ss-carry | G30: 10000 | H30: 200000 | I30: 75000 | J30: BIAN | K30: 0 | L30: 25000 | M30: COMPLEMENTARY | N30: =sumif(PURCHASE!I:I,C30,PURCHASE!J:J) -> 0 | O30: =sumif('SELLING CASH'!E:E,C30,'SELLING CASH'!F:F) -> 156 | P30: =sumif('SELLING CREDIT'!F:F,C30,'SELLING CREDIT'!G:G) -> 1 | Q30: =(N30+G30)-(O30+P30) -> 9843 | V30: C-0029 | W30: Bpk. H. Ikhsan/Cibeureum | X30: =sumif('SELLING CREDIT'!E:E,W30,'SELLING CREDIT'!P:P) -> 77200000 | Y30: =sumif('PAYMENT CREDIT'!E:E,W30,'PAYMENT CREDIT'!F:F) -> 68980000 | Z30: =X30-Y30 -> 8220000
C31: Baut Roda 12x1.5 | D31: - | F31: Baut | G31: 0 | H31: 15000 | I31: 10000 | J31: IBU | K31: 0 | L31: 0 | M31: COMPLEMENTARY | N31: =sumif(PURCHASE!I:I,C31,PURCHASE!J:J) -> 0 | O31: =sumif('SELLING CASH'!E:E,C31,'SELLING CASH'!F:F) -> 49 | P31: =sumif('SELLING CREDIT'!F:F,C31,'SELLING CREDIT'!G:G) -> 0 | Q31: =(N31+G31)-(O31+P31) -> -49 | V31: C-0030 | W31: Bpk. H. Iwan | X31: =sumif('SELLING CREDIT'!E:E,W31,'SELLING CREDIT'!P:P) -> 4300000 | Y31: =sumif('PAYMENT CREDIT'!E:E,W31,'PAYMENT CREDIT'!F:F) -> 4300000 | Z31: =X31-Y31 -> 0
C32: BD 1000 Bridgestone | D32: 1000 | E32: Bridgestone | F32: BD | G32: 2 | H32: 600000 | I32: 535000 | J32: IBU | K32: 1 | L32: 0 | M32: Tire | N32: =sumif(PURCHASE!I:I,C32,PURCHASE!J:J) -> 0 | O32: =sumif('SELLING CASH'!E:E,C32,'SELLING CASH'!F:F) -> 3 | P32: =sumif('SELLING CREDIT'!F:F,C32,'SELLING CREDIT'!G:G) -> 0 | Q32: =(N32+G32)-(O32+P32) -> -1 | V32: C-0031 | W32: Bpk. H. Jamil/Butul | X32: =sumif('SELLING CREDIT'!E:E,W32,'SELLING CREDIT'!P:P) -> 0 | Y32: =sumif('PAYMENT CREDIT'!E:E,W32,'PAYMENT CREDIT'!F:F) -> 0 | Z32: =X32-Y32 -> 0
C33: BD 1000 GT | D33: 1000 | E33: GT | F33: BD | G33: 0 | H33: 460000 | I33: 405000 | J33: BIAN | K33: 1 | L33: 0 | M33: Tire | N33: =sumif(PURCHASE!I:I,C33,PURCHASE!J:J) -> 2 | O33: =sumif('SELLING CASH'!E:E,C33,'SELLING CASH'!F:F) -> 0 | P33: =sumif('SELLING CREDIT'!F:F,C33,'SELLING CREDIT'!G:G) -> 2 | Q33: =(N33+G33)-(O33+P33) -> 0 | V33: C-0032 | W33: Bpk. H. Samin/Sudi | X33: =sumif('SELLING CREDIT'!E:E,W33,'SELLING CREDIT'!P:P) -> 0 | Y33: =sumif('PAYMENT CREDIT'!E:E,W33,'PAYMENT CREDIT'!F:F) -> 0 | Z33: =X33-Y33 -> 0
C34: BD 1000*20 | D34: 1000*20 | F34: BD | G34: 0 | H34: 0 | I34: 0 | J34: BIAN | K34: 1 | L34: 0 | M34: Tire | N34: =sumif(PURCHASE!I:I,C34,PURCHASE!J:J) -> 0 | O34: =sumif('SELLING CASH'!E:E,C34,'SELLING CASH'!F:F) -> 0 | P34: =sumif('SELLING CREDIT'!F:F,C34,'SELLING CREDIT'!G:G) -> 2 | Q34: =(N34+G34)-(O34+P34) -> -2 | V34: C-0033 | W34: Bpk. H. Syahro Dangdang | X34: =sumif('SELLING CREDIT'!E:E,W34,'SELLING CREDIT'!P:P) -> 18550000 | Y34: =sumif('PAYMENT CREDIT'!E:E,W34,'PAYMENT CREDIT'!F:F) -> 18550000 | Z34: =X34-Y34 -> 0
C35: BD 12 Aspira | D35: 12 | E35: Aspira | F35: BD | G35: 3 | H35: 100000 | I35: 51000 | J35: BIAN | K35: 1 | L35: 0 | M35: Tire | N35: =sumif(PURCHASE!I:I,C35,PURCHASE!J:J) -> 0 | O35: =sumif('SELLING CASH'!E:E,C35,'SELLING CASH'!F:F) -> 0 | P35: =sumif('SELLING CREDIT'!F:F,C35,'SELLING CREDIT'!G:G) -> 0 | Q35: =(N35+G35)-(O35+P35) -> 3 | V35: C-0034 | W35: Bpk. H. tarlan Cibeureum | X35: =sumif('SELLING CREDIT'!E:E,W35,'SELLING CREDIT'!P:P) -> 3250000 | Y35: =sumif('PAYMENT CREDIT'!E:E,W35,'PAYMENT CREDIT'!F:F) -> 3250000 | Z35: =X35-Y35 -> 0
C36: BD 12 NYB | D36: 12 | E36: NYB | F36: BD | G36: 13 | H36: 100000 | I36: 47000 | J36: BIAN | K36: 1 | L36: 0 | M36: Tire | N36: =sumif(PURCHASE!I:I,C36,PURCHASE!J:J) -> 0 | O36: =sumif('SELLING CASH'!E:E,C36,'SELLING CASH'!F:F) -> 18 | P36: =sumif('SELLING CREDIT'!F:F,C36,'SELLING CREDIT'!G:G) -> 0 | Q36: =(N36+G36)-(O36+P36) -> -5 | V36: C-0035 | W36: Bpk. H. Wido | X36: =sumif('SELLING CREDIT'!E:E,W36,'SELLING CREDIT'!P:P) -> 28610000 | Y36: =sumif('PAYMENT CREDIT'!E:E,W36,'PAYMENT CREDIT'!F:F) -> 33010000 | Z36: =X36-Y36 -> -4400000
C37: BD 13 Aspira | D37: 13 | E37: Aspira | F37: BD | G37: 0 | H37: 90000 | I37: 57000 | J37: BIAN | K37: 1 | L37: 0 | M37: Tire | N37: =sumif(PURCHASE!I:I,C37,PURCHASE!J:J) -> 0 | O37: =sumif('SELLING CASH'!E:E,C37,'SELLING CASH'!F:F) -> 0 | P37: =sumif('SELLING CREDIT'!F:F,C37,'SELLING CREDIT'!G:G) -> 0 | Q37: =(N37+G37)-(O37+P37) -> 0 | V37: C-0036 | W37: Bpk. Hadi Cikitu | X37: =sumif('SELLING CREDIT'!E:E,W37,'SELLING CREDIT'!P:P) -> 19790000 | Y37: =sumif('PAYMENT CREDIT'!E:E,W37,'PAYMENT CREDIT'!F:F) -> 15040000 | Z37: =X37-Y37 -> 4750000
C38: BD 13 Eversave | D38: 13 | E38: Eversave | F38: BD | G38: 0 | H38: 120000 | I38: 72000 | J38: BIAN | K38: 1 | L38: 0 | M38: Tire | N38: =sumif(PURCHASE!I:I,C38,PURCHASE!J:J) -> 0 | O38: =sumif('SELLING CASH'!E:E,C38,'SELLING CASH'!F:F) -> 0 | P38: =sumif('SELLING CREDIT'!F:F,C38,'SELLING CREDIT'!G:G) -> 0 | Q38: =(N38+G38)-(O38+P38) -> 0 | V38: C-0037 | W38: Bpk. Hasyim Pacet | X38: =sumif('SELLING CREDIT'!E:E,W38,'SELLING CREDIT'!P:P) -> 35270000 | Y38: =sumif('PAYMENT CREDIT'!E:E,W38,'PAYMENT CREDIT'!F:F) -> 35270000 | Z38: =X38-Y38 -> 0
C39: BD 13 GT | D39: 13 | E39: GT | F39: BD | G39: 10 | H39: 135000 | I39: 102000 | J39: BIAN | K39: 1 | L39: 0 | M39: Tire | N39: =sumif(PURCHASE!I:I,C39,PURCHASE!J:J) -> 125 | O39: =sumif('SELLING CASH'!E:E,C39,'SELLING CASH'!F:F) -> 122 | P39: =sumif('SELLING CREDIT'!F:F,C39,'SELLING CREDIT'!G:G) -> 2 | Q39: =(N39+G39)-(O39+P39) -> 11 | V39: C-0038 | W39: Bpk. Heri Sapan | X39: =sumif('SELLING CREDIT'!E:E,W39,'SELLING CREDIT'!P:P) -> 0 | Y39: =sumif('PAYMENT CREDIT'!E:E,W39,'PAYMENT CREDIT'!F:F) -> 0 | Z39: =X39-Y39 -> 0
C40: BD 13 IBK | D40: 13 | E40: IBK | F40: BD | G40: 3 | H40: 85000 | I40: 45439.582 | J40: BIAN | K40: 1 | L40: 0 | M40: Tire | N40: =sumif(PURCHASE!I:I,C40,PURCHASE!J:J) -> 255 | O40: =sumif('SELLING CASH'!E:E,C40,'SELLING CASH'!F:F) -> 229 | P40: =sumif('SELLING CREDIT'!F:F,C40,'SELLING CREDIT'!G:G) -> 1 | Q40: =(N40+G40)-(O40+P40) -> 28 | V40: C-0039 | W40: Bpk. Iwan Pajaten | X40: =sumif('SELLING CREDIT'!E:E,W40,'SELLING CREDIT'!P:P) -> 11200000 | Y40: =sumif('PAYMENT CREDIT'!E:E,W40,'PAYMENT CREDIT'!F:F) -> 11200000 | Z40: =X40-Y40 -> 0
C41: BD 13 NYB | D41: 13 | E41: NYB | F41: BD | G41: 32 | H41: 110000 | I41: 50000 | J41: BIAN | K41: 1 | L41: 0 | M41: Tire | N41: =sumif(PURCHASE!I:I,C41,PURCHASE!J:J) -> 0 | O41: =sumif('SELLING CASH'!E:E,C41,'SELLING CASH'!F:F) -> 0 | P41: =sumif('SELLING CREDIT'!F:F,C41,'SELLING CREDIT'!G:G) -> 0 | Q41: =(N41+G41)-(O41+P41) -> 32 | V41: C-0040 | W41: Bpk. Iyep/Butul | X41: =sumif('SELLING CREDIT'!E:E,W41,'SELLING CREDIT'!P:P) -> 18510000 | Y41: =sumif('PAYMENT CREDIT'!E:E,W41,'PAYMENT CREDIT'!F:F) -> 17380000 | Z41: =X41-Y41 -> 1130000
C42: BD 13 Truckoor | D42: 13 | E42: Truckoor | F42: BD | G42: 2 | H42: 120000 | I42: 61600 | J42: BIAN | K42: 1 | L42: 0 | M42: Tire | N42: =sumif(PURCHASE!I:I,C42,PURCHASE!J:J) -> 0 | O42: =sumif('SELLING CASH'!E:E,C42,'SELLING CASH'!F:F) -> 12 | P42: =sumif('SELLING CREDIT'!F:F,C42,'SELLING CREDIT'!G:G) -> 0 | Q42: =(N42+G42)-(O42+P42) -> -10 | V42: C-0041 | W42: Bpk. Jajang/Sapan | X42: =sumif('SELLING CREDIT'!E:E,W42,'SELLING CREDIT'!P:P) -> 111690000 | Y42: =sumif('PAYMENT CREDIT'!E:E,W42,'PAYMENT CREDIT'!F:F) -> 110830000 | Z42: =X42-Y42 -> 860000
C43: BD 14 Aspira | D43: 14 | E43: Aspira | F43: BD | G43: 2 | H43: 135000 | I43: 83000 | J43: BIAN | K43: 1 | L43: 0 | M43: Tire | N43: =sumif(PURCHASE!I:I,C43,PURCHASE!J:J) -> 0 | O43: =sumif('SELLING CASH'!E:E,C43,'SELLING CASH'!F:F) -> 2 | P43: =sumif('SELLING CREDIT'!F:F,C43,'SELLING CREDIT'!G:G) -> 0 | Q43: =(N43+G43)-(O43+P43) -> 0 | V43: C-0042 | W43: Bpk. Kiki Tapak Serang | X43: =sumif('SELLING CREDIT'!E:E,W43,'SELLING CREDIT'!P:P) -> 0 | Y43: =sumif('PAYMENT CREDIT'!E:E,W43,'PAYMENT CREDIT'!F:F) -> 0 | Z43: =X43-Y43 -> 0
C44: BD 14 GT | D44: 14 | E44: GT | F44: BD | G44: 17 | H44: 170000 | I44: 124000 | J44: BIAN | K44: 1 | L44: 0 | M44: Tire | N44: =sumif(PURCHASE!I:I,C44,PURCHASE!J:J) -> 100 | O44: =sumif('SELLING CASH'!E:E,C44,'SELLING CASH'!F:F) -> 87 | P44: =sumif('SELLING CREDIT'!F:F,C44,'SELLING CREDIT'!G:G) -> 6 | Q44: =(N44+G44)-(O44+P44) -> 24 | V44: C-0043 | W44: Bpk. Koko | X44: =sumif('SELLING CREDIT'!E:E,W44,'SELLING CREDIT'!P:P) -> 30960000 | Y44: =sumif('PAYMENT CREDIT'!E:E,W44,'PAYMENT CREDIT'!F:F) -> 29760000 | Z44: =X44-Y44 -> 1200000
C45: BD 14 IBK | D45: 14 | E45: IBK | F45: BD | G45: 26 | H45: 100000 | I45: 58371.27 | J45: BIAN | K45: 1 | L45: 0 | M45: Tire | N45: =sumif(PURCHASE!I:I,C45,PURCHASE!J:J) -> 75 | O45: =sumif('SELLING CASH'!E:E,C45,'SELLING CASH'!F:F) -> 65 | P45: =sumif('SELLING CREDIT'!F:F,C45,'SELLING CREDIT'!G:G) -> 0 | Q45: =(N45+G45)-(O45+P45) -> 36 | V45: C-0044 | W45: Bpk. Nanang/Dandang | X45: =sumif('SELLING CREDIT'!E:E,W45,'SELLING CREDIT'!P:P) -> 0 | Y45: =sumif('PAYMENT CREDIT'!E:E,W45,'PAYMENT CREDIT'!F:F) -> 0 | Z45: =X45-Y45 -> 0
C46: BD 14 NYB | D46: 14 | E46: NYB | F46: BD | G46: 15 | H46: 120000 | I46: 60500 | J46: BIAN | K46: 1 | L46: 0 | M46: Tire | N46: =sumif(PURCHASE!I:I,C46,PURCHASE!J:J) -> 20 | O46: =sumif('SELLING CASH'!E:E,C46,'SELLING CASH'!F:F) -> 22 | P46: =sumif('SELLING CREDIT'!F:F,C46,'SELLING CREDIT'!G:G) -> 0 | Q46: =(N46+G46)-(O46+P46) -> 13 | V46: C-0045 | W46: Bpk. Novi ciparay | X46: =sumif('SELLING CREDIT'!E:E,W46,'SELLING CREDIT'!P:P) -> 2900000 | Y46: =sumif('PAYMENT CREDIT'!E:E,W46,'PAYMENT CREDIT'!F:F) -> 3490000 | Z46: =X46-Y46 -> -590000
... C56: BD 15 Truckoor | D56: 15 | E56: Truckoor | F56: BD | G56: 0 | H56: 170000 | I56: 120960 | J56: BIAN | K56: 1 | L56: 0 | M56: Tire | N56: =sumif(PURCHASE!I:I,C56,PURCHASE!J:J) -> 0 | O56: =sumif('SELLING CASH'!E:E,C56,'SELLING CASH'!F:F) -> 32 | P56: =sumif('SELLING CREDIT'!F:F,C56,'SELLING CREDIT'!G:G) -> 5 | Q56: =(N56+G56)-(O56+P56) -> -37 | V56: C-0055 | W56: Bpk. Ujang Sundawangi/Cikawao | X56: =sumif('SELLING CREDIT'!E:E,W56,'SELLING CREDIT'!P:P) -> 0 | Y56: =sumif('PAYMENT CREDIT'!E:E,W56,'PAYMENT CREDIT'!F:F) -> 0 | Z56: =X56-Y56 -> 0
C57: BD 16 Aspira | D57: 16 | F57: BD | G57: 0 | H57: 180000 | I57: 141000 | J57: BIAN | K57: 1 | L57: 0 | M57: Tire | N57: =sumif(PURCHASE!I:I,C57,PURCHASE!J:J) -> 0 | O57: =sumif('SELLING CASH'!E:E,C57,'SELLING CASH'!F:F) -> 0 | P57: =sumif('SELLING CREDIT'!F:F,C57,'SELLING CREDIT'!G:G) -> 0 | Q57: =(N57+G57)-(O57+P57) -> 0 | V57: C-0056 | W57: Bpk. Ujang TJ | X57: =sumif('SELLING CREDIT'!E:E,W57,'SELLING CREDIT'!P:P) -> 0 | Y57: =sumif('PAYMENT CREDIT'!E:E,W57,'PAYMENT CREDIT'!F:F) -> 0 | Z57: =X57-Y57 -> 0
C58: BD 16 Bestone | D58: 16 | E58: Bestone | F58: BD | G58: 0 | H58: 185000 | I58: 135000 | J58: BIAN | K58: 1 | L58: 0 | M58: Tire | N58: =sumif(PURCHASE!I:I,C58,PURCHASE!J:J) -> 0 | O58: =sumif('SELLING CASH'!E:E,C58,'SELLING CASH'!F:F) -> 1 | P58: =sumif('SELLING CREDIT'!F:F,C58,'SELLING CREDIT'!G:G) -> 0 | Q58: =(N58+G58)-(O58+P58) -> -1 | V58: C-0057 | W58: Bpk. Usep Isma/Balekambang | X58: =sumif('SELLING CREDIT'!E:E,W58,'SELLING CREDIT'!P:P) -> 67770000 | Y58: =sumif('PAYMENT CREDIT'!E:E,W58,'PAYMENT CREDIT'!F:F) -> 60870000 | Z58: =X58-Y58 -> 6900000
C59: BD 16 Bridgestone | D59: 16 | E59: Bridgestone | F59: BD | G59: 27 | H59: 280000 | I59: 241001.6 | J59: IBU | K59: 1 | L59: 0 | M59: Tire | N59: =sumif(PURCHASE!I:I,C59,PURCHASE!J:J) -> 30 | O59: =sumif('SELLING CASH'!E:E,C59,'SELLING CASH'!F:F) -> 33 | P59: =sumif('SELLING CREDIT'!F:F,C59,'SELLING CREDIT'!G:G) -> 3 | Q59: =(N59+G59)-(O59+P59) -> 21 | V59: C-0058 | W59: Bpk. Usep Sri Rahayu | X59: =sumif('SELLING CREDIT'!E:E,W59,'SELLING CREDIT'!P:P) -> 8820000 | Y59: =sumif('PAYMENT CREDIT'!E:E,W59,'PAYMENT CREDIT'!F:F) -> 8820000 | Z59: =X59-Y59 -> 0
C60: BD 16 GT | D60: 16 | E60: GT | F60: BD | G60: 48 | H60: 230000 | I60: 182200 | J60: BIAN | K60: 1 | L60: 0 | M60: Tire | N60: =sumif(PURCHASE!I:I,C60,PURCHASE!J:J) -> 170 | O60: =sumif('SELLING CASH'!E:E,C60,'SELLING CASH'!F:F) -> 107 | P60: =sumif('SELLING CREDIT'!F:F,C60,'SELLING CREDIT'!G:G) -> 69 | Q60: =(N60+G60)-(O60+P60) -> 42 | V60: C-0059 | W60: Bpk. Uus | X60: =sumif('SELLING CREDIT'!E:E,W60,'SELLING CREDIT'!P:P) -> 12970000 | Y60: =sumif('PAYMENT CREDIT'!E:E,W60,'PAYMENT CREDIT'!F:F) -> 11400000 | Z60: =X60-Y60 -> 1570000
C61: BD 16 KCN | D61: 16 | E61: KCN | F61: BD | G61: 16 | H61: 200000 | I61: 140000 | J61: BIAN | K61: 1 | L61: 0 | M61: Tire | N61: =sumif(PURCHASE!I:I,C61,PURCHASE!J:J) -> 0 | O61: =sumif('SELLING CASH'!E:E,C61,'SELLING CASH'!F:F) -> 18 | P61: =sumif('SELLING CREDIT'!F:F,C61,'SELLING CREDIT'!G:G) -> 0 | Q61: =(N61+G61)-(O61+P61) -> -2 | V61: C-0060 | W61: Bpk. Wisnu Pangauban | X61: =sumif('SELLING CREDIT'!E:E,W61,'SELLING CREDIT'!P:P) -> 30840000 | Y61: =sumif('PAYMENT CREDIT'!E:E,W61,'PAYMENT CREDIT'!F:F) -> 28570000 | Z61: =X61-Y61 -> 2270000
C62: BD 16 NYB | D62: 16 | E62: NYB | F62: BD | G62: 3 | H62: 200000 | I62: 140000 | J62: BIAN | K62: 1 | L62: 0 | M62: Tire | N62: =sumif(PURCHASE!I:I,C62,PURCHASE!J:J) -> 0 | O62: =sumif('SELLING CASH'!E:E,C62,'SELLING CASH'!F:F) -> 3 | P62: =sumif('SELLING CREDIT'!F:F,C62,'SELLING CREDIT'!G:G) -> 0 | Q62: =(N62+G62)-(O62+P62) -> 0 | V62: C-0061 | W62: Bpk. Yana Wasnan/Pacet | X62: =sumif('SELLING CREDIT'!E:E,W62,'SELLING CREDIT'!P:P) -> 955000 | Y62: =sumif('PAYMENT CREDIT'!E:E,W62,'PAYMENT CREDIT'!F:F) -> 0 | Z62: =X62-Y62 -> 955000
C63: BD 16 SJ | D63: 16 | F63: BD | G63: 12 | H63: 200000 | I63: 145000 | J63: BIAN | K63: 1 | L63: 0 | M63: Tire | N63: =sumif(PURCHASE!I:I,C63,PURCHASE!J:J) -> 30 | O63: =sumif('SELLING CASH'!E:E,C63,'SELLING CASH'!F:F) -> 27 | P63: =sumif('SELLING CREDIT'!F:F,C63,'SELLING CREDIT'!G:G) -> 3 | Q63: =(N63+G63)-(O63+P63) -> 12 | V63: C-0062 | W63: Bpk. Yapi/Agus | X63: =sumif('SELLING CREDIT'!E:E,W63,'SELLING CREDIT'!P:P) -> 0 | Y63: =sumif('PAYMENT CREDIT'!E:E,W63,'PAYMENT CREDIT'!F:F) -> 0 | Z63: =X63-Y63 -> 0
C64: BD 16 Truckoor | D64: 16 | E64: Truckoor | F64: BD | G64: 11 | H64: 200000 | I64: 145180 | J64: BIAN | K64: 1 | L64: 0 | M64: Tire | N64: =sumif(PURCHASE!I:I,C64,PURCHASE!J:J) -> 30 | O64: =sumif('SELLING CASH'!E:E,C64,'SELLING CASH'!F:F) -> 32 | P64: =sumif('SELLING CREDIT'!F:F,C64,'SELLING CREDIT'!G:G) -> 8 | Q64: =(N64+G64)-(O64+P64) -> 1 | V64: C-0063 | W64: Bpk. Yayat Dojer Sapan | X64: =sumif('SELLING CREDIT'!E:E,W64,'SELLING CREDIT'!P:P) -> 45040000 | Y64: =sumif('PAYMENT CREDIT'!E:E,W64,'PAYMENT CREDIT'!F:F) -> 45040000 | Z64: =X64-Y64 -> 0
C65: =F65&" "&D65&" "&E65 -> BD 28X9 15 GT | D65: 28X9 15 | E65: GT | F65: BD | G65: 0 | H65: 250000 | I65: 204000 | J65: BIAN | K65: 1 | L65: 0 | M65: Tire | N65: =sumif(PURCHASE!I:I,C65,PURCHASE!J:J) -> 1 | O65: =sumif('SELLING CASH'!E:E,C65,'SELLING CASH'!F:F) -> 1 | P65: =sumif('SELLING CREDIT'!F:F,C65,'SELLING CREDIT'!G:G) -> 0 | Q65: =(N65+G65)-(O65+P65) -> 0 | V65: C-0064 | W65: Bpk. Yusup Koramil | X65: =sumif('SELLING CREDIT'!E:E,W65,'SELLING CREDIT'!P:P) -> 0 | Y65: =sumif('PAYMENT CREDIT'!E:E,W65,'PAYMENT CREDIT'!F:F) -> 0 | Z65: =X65-Y65 -> 0
C66: BD 600/9 D GT | D66: 600/9 | E66: Forklift GT | F66: BD | G66: 0 | H66: 135000 | I66: 92250 | J66: BIAN | K66: 1 | L66: 0 | M66: Tire | N66: =sumif(PURCHASE!I:I,C66,PURCHASE!J:J) -> 2 | O66: =sumif('SELLING CASH'!E:E,C66,'SELLING CASH'!F:F) -> 2 | P66: =sumif('SELLING CREDIT'!F:F,C66,'SELLING CREDIT'!G:G) -> 0 | Q66: =(N66+G66)-(O66+P66) -> 0 | V66: C-0065 | W66: Faliza | X66: =sumif('SELLING CREDIT'!E:E,W66,'SELLING CREDIT'!P:P) -> 1945000 | Y66: =sumif('PAYMENT CREDIT'!E:E,W66,'PAYMENT CREDIT'!F:F) -> 0 | Z66: =X66-Y66 -> 1945000
C67: BD 650/10 GT | D67: 650/10 | E67: GT | F67: BD | G67: 0 | H67: 175000 | I67: 123000 | J67: BIAN | K67: 1 | L67: 0 | M67: Tire | N67: =sumif(PURCHASE!I:I,C67,PURCHASE!J:J) -> 3 | O67: =sumif('SELLING CASH'!E:E,C67,'SELLING CASH'!F:F) -> 3 | P67: =sumif('SELLING CREDIT'!F:F,C67,'SELLING CREDIT'!G:G) -> 0 | Q67: =(N67+G67)-(O67+P67) -> 0 | V67: C-0066 | W67: Family Sejati | X67: =sumif('SELLING CREDIT'!E:E,W67,'SELLING CREDIT'!P:P) -> 38310000 | Y67: =sumif('PAYMENT CREDIT'!E:E,W67,'PAYMENT CREDIT'!F:F) -> 38310000 | Z67: =X67-Y67 -> 0
C68: BD 650/700 15 Bridgestone | D68: 650/700 15 | E68: Bridgestone | F68: BD | G68: 0 | H68: 260000 | I68: 230000 | J68: IBU | K68: 1 | L68: 0 | M68: Tire | N68: =sumif(PURCHASE!I:I,C68,PURCHASE!J:J) -> 0 | O68: =sumif('SELLING CASH'!E:E,C68,'SELLING CASH'!F:F) -> 0 | P68: =sumif('SELLING CREDIT'!F:F,C68,'SELLING CREDIT'!G:G) -> 0 | Q68: =(N68+G68)-(O68+P68) -> 0 | V68: C-0067 | W68: Ibu Dede/Maruyung | X68: =sumif('SELLING CREDIT'!E:E,W68,'SELLING CREDIT'!P:P) -> 25005000 | Y68: =sumif('PAYMENT CREDIT'!E:E,W68,'PAYMENT CREDIT'!F:F) -> 25005000 | Z68: =X68-Y68 -> 0
C69: BD 700/12 Powerclip GT | D69: 700/12 | E69: Forklift GT | F69: BD | G69: 0 | H69: 200000 | I69: 157500 | J69: BIAN | K69: 1 | L69: 0 | M69: Tire | N69: =sumif(PURCHASE!I:I,C69,PURCHASE!J:J) -> 3 | O69: =sumif('SELLING CASH'!E:E,C69,'SELLING CASH'!F:F) -> 3 | P69: =sumif('SELLING CREDIT'!F:F,C69,'SELLING CREDIT'!G:G) -> 0 | Q69: =(N69+G69)-(O69+P69) -> 0 | V69: C-0068 | W69: Ibu Dede/Sundawangi | X69: =sumif('SELLING CREDIT'!E:E,W69,'SELLING CREDIT'!P:P) -> 27570000 | Y69: =sumif('PAYMENT CREDIT'!E:E,W69,'PAYMENT CREDIT'!F:F) -> 25460000 | Z69: =X69-Y69 -> 2110000
C70: =F70&" "&D70&" "&E70 -> BD 8.25 Bestone | D70: 8.25 | E70: Bestone | F70: BD | G70: 8 | H70: 190000 | I70: 160000 | J70: BIAN | K70: 1 | L70: 0 | M70: Tire | N70: =sumif(PURCHASE!I:I,C70,PURCHASE!J:J) -> 0 | O70: =sumif('SELLING CASH'!E:E,C70,'SELLING CASH'!F:F) -> 0 | P70: =sumif('SELLING CREDIT'!F:F,C70,'SELLING CREDIT'!G:G) -> 8 | Q70: =(N70+G70)-(O70+P70) -> 0 | V70: C-0069 | W70: Ibu Hajah Usu | X70: =sumif('SELLING CREDIT'!E:E,W70,'SELLING CREDIT'!P:P) -> 0 | Y70: =sumif('PAYMENT CREDIT'!E:E,W70,'PAYMENT CREDIT'!F:F) -> 0 | Z70: =X70-Y70 -> 0
C71: BD 8.25 TRUCKOOR | D71: 8.25 | E71: Truckoor | F71: BD | G71: 10 | H71: 220000 | I71: 184150 | J71: BIAN | K71: 1 | L71: 0 | M71: Tire | N71: =sumif(PURCHASE!I:I,C71,PURCHASE!J:J) -> 40 | O71: =sumif('SELLING CASH'!E:E,C71,'SELLING CASH'!F:F) -> 1 | P71: =sumif('SELLING CREDIT'!F:F,C71,'SELLING CREDIT'!G:G) -> 13 | Q71: =(N71+G71)-(O71+P71) -> 36 | V71: C-0070 | W71: Ibu Hj. Oneng | X71: =sumif('SELLING CREDIT'!E:E,W71,'SELLING CREDIT'!P:P) -> 0 | Y71: =sumif('PAYMENT CREDIT'!E:E,W71,'PAYMENT CREDIT'!F:F) -> 0 | Z71: =X71-Y71 -> 0
C72: BD 900* 20 GT | D72: 900* 20 | E72: GT | F72: BD | G72: 8 | H72: 398000 | I72: 348000 | J72: BIAN | K72: 1 | L72: 0 | M72: Tire | N72: =sumif(PURCHASE!I:I,C72,PURCHASE!J:J) -> 10 | O72: =sumif('SELLING CASH'!E:E,C72,'SELLING CASH'!F:F) -> 0 | P72: =sumif('SELLING CREDIT'!F:F,C72,'SELLING CREDIT'!G:G) -> 4 | Q72: =(N72+G72)-(O72+P72) -> 14 | V72: C-0071 | W72: Ibu Komala/Munjul | X72: =sumif('SELLING CREDIT'!E:E,W72,'SELLING CREDIT'!P:P) -> 16820000 | Y72: =sumif('PAYMENT CREDIT'!E:E,W72,'PAYMENT CREDIT'!F:F) -> 16320000 | Z72: =X72-Y72 -> 500000
C73: BD 900*20 Bridgestone | D73: 900*20 | E73: Bridgestone | F73: BD | G73: 0 | H73: 525000 | I73: 415000 | J73: IBU | K73: 1 | L73: 0 | M73: Tire | N73: =sumif(PURCHASE!I:I,C73,PURCHASE!J:J) -> 1 | O73: =sumif('SELLING CASH'!E:E,C73,'SELLING CASH'!F:F) -> 1 | P73: =sumif('SELLING CREDIT'!F:F,C73,'SELLING CREDIT'!G:G) -> 0 | Q73: =(N73+G73)-(O73+P73) -> 0 | V73: C-0072 | W73: Ibu Lilis Hayam | X73: =sumif('SELLING CREDIT'!E:E,W73,'SELLING CREDIT'!P:P) -> 1700000 | Y73: =sumif('PAYMENT CREDIT'!E:E,W73,'PAYMENT CREDIT'!F:F) -> 1700000 | Z73: =X73-Y73 -> 0
C74: BD 900*20 Bridgestone | D74: 900*20 | E74: Bridgestone | F74: BD | G74: 0 | H74: 525000 | I74: 436500 | J74: IBU | K74: 1 | L74: 0 | M74: Tire | N74: =sumif(PURCHASE!I:I,C74,PURCHASE!J:J) -> 1 | O74: =sumif('SELLING CASH'!E:E,C74,'SELLING CASH'!F:F) -> 1 | P74: =sumif('SELLING CREDIT'!F:F,C74,'SELLING CREDIT'!G:G) -> 0 | Q74: =(N74+G74)-(O74+P74) -> 0 | V74: C-0073 | W74: siapa? | X74: =sumif('SELLING CREDIT'!E:E,W74,'SELLING CREDIT'!P:P) -> 0 | Y74: =sumif('PAYMENT CREDIT'!E:E,W74,'PAYMENT CREDIT'!F:F) -> 0 | Z74: =X74-Y74 -> 0
C75: =F75&" "&D75&" "&E75 -> BD IBK 15 Pentil Pendek | D75: 15 | E75: Pentil Pendek | F75: BD IBK | G75: 0 | H75: 115000 | I75: 81000 | J75: BIAN | K75: 1 | L75: 0 | M75: Tire | N75: =sumif(PURCHASE!I:I,C75,PURCHASE!J:J) -> 30 | O75: =sumif('SELLING CASH'!E:E,C75,'SELLING CASH'!F:F) -> 18 | P75: =sumif('SELLING CREDIT'!F:F,C75,'SELLING CREDIT'!G:G) -> 0 | Q75: =(N75+G75)-(O75+P75) -> 12 | V75: C-0074 | W75: Ibu Yayah Pandex/Ciheulang | X75: =sumif('SELLING CREDIT'!E:E,W75,'SELLING CREDIT'!P:P) -> 34280000 | Y75: =sumif('PAYMENT CREDIT'!E:E,W75,'PAYMENT CREDIT'!F:F) -> 34380000 | Z75: =X75-Y75 -> -100000
C76: Bongkar Pasang | D76: - | F76: Bongkar Pasang | G76: 0 | H76: 35000 | I76: 0 | J76: IBU | K76: 0 | L76: 0 | M76: SERVICE | N76: =sumif(PURCHASE!I:I,C76,PURCHASE!J:J) -> 0 | O76: =sumif('SELLING CASH'!E:E,C76,'SELLING CASH'!F:F) -> 448 | P76: =sumif('SELLING CREDIT'!F:F,C76,'SELLING CREDIT'!G:G) -> 4 | Q76: =(N76+G76)-(O76+P76) -> -452 | V76: C-0075 | W76: Ibu. HJ. Eti | X76: =sumif('SELLING CREDIT'!E:E,W76,'SELLING CREDIT'!P:P) -> 13035000 | Y76: =sumif('PAYMENT CREDIT'!E:E,W76,'PAYMENT CREDIT'!F:F) -> 13035000 | Z76: =X76-Y76 -> 0
C77: Bongkar Pasang 17 | D77: - | F77: Bongkar Pasang 17 | G77: 99999296 | H77: 50000 | I77: 0 | J77: IBU | K77: 0 | L77: 0 | M77: SERVICE | N77: =sumif(PURCHASE!I:I,C77,PURCHASE!J:J) -> 0 | O77: =sumif('SELLING CASH'!E:E,C77,'SELLING CASH'!F:F) -> 75 | P77: =sumif('SELLING CREDIT'!F:F,C77,'SELLING CREDIT'!G:G) -> 0 | Q77: =(N77+G77)-(O77+P77) -> 99999221 | V77: C-0076 | W77: TRI PUTRA | X77: =sumif('SELLING CREDIT'!E:E,W77,'SELLING CREDIT'!P:P) -> 0 | Y77: =sumif('PAYMENT CREDIT'!E:E,W77,'PAYMENT CREDIT'!F:F) -> 0 | Z77: =X77-Y77 -> 0
C78: Bridgestone 1000*20 | D78: 1000*20 | F78: Bridgestone | G78: 4873 | H78: 3520000 | I78: 3365000 | J78: IBU | K78: 1 | L78: 0 | M78: Tire | N78: =sumif(PURCHASE!I:I,C78,PURCHASE!J:J) -> 2 | O78: =sumif('SELLING CASH'!E:E,C78,'SELLING CASH'!F:F) -> 2 | P78: =sumif('SELLING CREDIT'!F:F,C78,'SELLING CREDIT'!G:G) -> 0 | Q78: =(N78+G78)-(O78+P78) -> 4873 | V78: C-0077 | W78: PT. SANTOSA KURNIA JAYA | X78: =sumif('SELLING CREDIT'!E:E,W78,'SELLING CREDIT'!P:P) -> 4500000 | Y78: =sumif('PAYMENT CREDIT'!E:E,W78,'PAYMENT CREDIT'!F:F) -> 4500000 | Z78: =X78-Y78 -> 0
C79: Bridgestone 165/13 Duravis | D79: 165/13 | E79: Duravis | F79: Bridgestone | G79: 0 | H79: 765000 | I79: 675000 | J79: IBU | K79: 1 | L79: 0 | M79: Tire | N79: =sumif(PURCHASE!I:I,C79,PURCHASE!J:J) -> 105 | O79: =sumif('SELLING CASH'!E:E,C79,'SELLING CASH'!F:F) -> 95 | P79: =sumif('SELLING CREDIT'!F:F,C79,'SELLING CREDIT'!G:G) -> 0 | Q79: =(N79+G79)-(O79+P79) -> 10 | V79: C-0078 | W79: Bpk. H. Syukur/Ikhsan CIbeurreum | X79: =sumif('SELLING CREDIT'!E:E,W79,'SELLING CREDIT'!P:P) -> 22800000 | Y79: =sumif('PAYMENT CREDIT'!E:E,W79,'PAYMENT CREDIT'!F:F) -> 24800000 | Z79: =X79-Y79 -> -2000000
C80: Bridgestone 165/80 13 Ecopia | D80: 165/80 13 | E80: Ecopia | F80: Bridgestone | G80: 0 | H80: 645000 | I80: 542528 | J80: IBU | K80: 1 | L80: 0 | M80: Tire | N80: =sumif(PURCHASE!I:I,C80,PURCHASE!J:J) -> 27 | O80: =sumif('SELLING CASH'!E:E,C80,'SELLING CASH'!F:F) -> 26 | P80: =sumif('SELLING CREDIT'!F:F,C80,'SELLING CREDIT'!G:G) -> 0 | Q80: =(N80+G80)-(O80+P80) -> 1 | V80: C-0079 | W80: PUSPA JAYA | X80: =sumif('SELLING CREDIT'!E:E,W80,'SELLING CREDIT'!P:P) -> 0 | Y80: =sumif('PAYMENT CREDIT'!E:E,W80,'PAYMENT CREDIT'!F:F) -> 0 | Z80: =X80-Y80 -> 0
C81: Bridgestone 175/13 Duravis | D81: 175/13 | E81: Duravis | F81: Bridgestone | G81: 0 | H81: 800000 | I81: 710000 | J81: IBU | K81: 1 | L81: 0 | M81: Tire | N81: =sumif(PURCHASE!I:I,C81,PURCHASE!J:J) -> 160 | O81: =sumif('SELLING CASH'!E:E,C81,'SELLING CASH'!F:F) -> 157 | P81: =sumif('SELLING CREDIT'!F:F,C81,'SELLING CREDIT'!G:G) -> 4 | Q81: =(N81+G81)-(O81+P81) -> -1 | V81: C-0080 | W81: Bpk. Ate Paseh | X81: =sumif('SELLING CREDIT'!E:E,W81,'SELLING CREDIT'!P:P) -> 14530000 | Y81: =sumif('PAYMENT CREDIT'!E:E,W81,'PAYMENT CREDIT'!F:F) -> 12250000 | Z81: =X81-Y81 -> 2280000
C82: Bridgestone 175/65 14 Ecopia | D82: 175/65 14 | E82: Ecopia | F82: Bridgestone | G82: 8 | H82: 700000 | I82: 611109.16 | J82: IBU | K82: 1 | L82: 0 | M82: Tire | N82: =sumif(PURCHASE!I:I,C82,PURCHASE!J:J) -> 130 | O82: =sumif('SELLING CASH'!E:E,C82,'SELLING CASH'!F:F) -> 124 | P82: =sumif('SELLING CREDIT'!F:F,C82,'SELLING CREDIT'!G:G) -> 1 | Q82: =(N82+G82)-(O82+P82) -> 13 | V82: C-0081 | W82: Bpk. Felis | X82: =sumif('SELLING CREDIT'!E:E,W82,'SELLING CREDIT'!P:P) -> 6000000 | Y82: =sumif('PAYMENT CREDIT'!E:E,W82,'PAYMENT CREDIT'!F:F) -> 3000000 | Z82: =X82-Y82 -> 3000000
C83: Bridgestone 175/65 14 Techno | D83: 175/65 14 | E83: Techno | F83: Bridgestone | G83: 0 | H83: 670000 | I83: 571000 | J83: IBU | K83: 1 | L83: 0 | M83: Tire | N83: =sumif(PURCHASE!I:I,C83,PURCHASE!J:J) -> 0 | O83: =sumif('SELLING CASH'!E:E,C83,'SELLING CASH'!F:F) -> 0 | P83: =sumif('SELLING CREDIT'!F:F,C83,'SELLING CREDIT'!G:G) -> 0 | Q83: =(N83+G83)-(O83+P83) -> 0 | V83: C-0082 | W83: Bpk. Opang CIheulang | X83: =sumif('SELLING CREDIT'!E:E,W83,'SELLING CREDIT'!P:P) -> 34960000 | Y83: =sumif('PAYMENT CREDIT'!E:E,W83,'PAYMENT CREDIT'!F:F) -> 34960000 | Z83: =X83-Y83 -> 0
C84: Bridgestone 175/70 13 Ecopia | D84: 175/70 13 | E84: Ecopia | F84: Bridgestone | G84: 3 | H84: 750000 | I84: 634099.2 | J84: IBU | K84: 1 | L84: 0 | M84: Tire | N84: =sumif(PURCHASE!I:I,C84,PURCHASE!J:J) -> 4 | O84: =sumif('SELLING CASH'!E:E,C84,'SELLING CASH'!F:F) -> 7 | P84: =sumif('SELLING CREDIT'!F:F,C84,'SELLING CREDIT'!G:G) -> 0 | Q84: =(N84+G84)-(O84+P84) -> 0 | V84: C-0083 | W84: Bpk. Agus Jogor | X84: =sumif('SELLING CREDIT'!E:E,W84,'SELLING CREDIT'!P:P) -> 5960000 | Y84: =sumif('PAYMENT CREDIT'!E:E,W84,'PAYMENT CREDIT'!F:F) -> 5960000 | Z84: =X84-Y84 -> 0
C85: Bridgestone 185/14 Duravis | D85: 185/14 | E85: Duravis | F85: Bridgestone | G85: 1 | H85: 920000 | I85: 825000 | J85: IBU | K85: 1 | L85: 0 | M85: Tire | N85: =sumif(PURCHASE!I:I,C85,PURCHASE!J:J) -> 172 | O85: =sumif('SELLING CASH'!E:E,C85,'SELLING CASH'!F:F) -> 167 | P85: =sumif('SELLING CREDIT'!F:F,C85,'SELLING CREDIT'!G:G) -> 1 | Q85: =(N85+G85)-(O85+P85) -> 5 | V85: C-0084 | W85: Ibu. Amanah | X85: =sumif('SELLING CREDIT'!E:E,W85,'SELLING CREDIT'!P:P) -> 1530000 | Y85: =sumif('PAYMENT CREDIT'!E:E,W85,'PAYMENT CREDIT'!F:F) -> 1530000 | Z85: =X85-Y85 -> 0
C86: Bridgestone 185/55 15 Techno | D86: 185/55 15 | E86: Techno | F86: Bridgestone | G86: 0 | H86: 800000 | I86: 704346 | J86: IBU | K86: 1 | L86: 0 | M86: Tire | N86: =sumif(PURCHASE!I:I,C86,PURCHASE!J:J) -> 23 | O86: =sumif('SELLING CASH'!E:E,C86,'SELLING CASH'!F:F) -> 20 | P86: =sumif('SELLING CREDIT'!F:F,C86,'SELLING CREDIT'!G:G) -> 0 | Q86: =(N86+G86)-(O86+P86) -> 3 | V86: C-0085 | W86: Bpk. Endut | X86: =sumif('SELLING CREDIT'!E:E,W86,'SELLING CREDIT'!P:P) -> 6050000 | Y86: =sumif('PAYMENT CREDIT'!E:E,W86,'PAYMENT CREDIT'!F:F) -> 6050000 | Z86: =X86-Y86 -> 0
C87: Bridgestone 185/55 16 Techno Sport | D87: 185/55 16 | E87: Techno Sport | F87: Bridgestone | G87: 0 | H87: 875000 | I87: 773337.5 | J87: IBU | K87: 1 | L87: 0 | M87: Tire | N87: =sumif(PURCHASE!I:I,C87,PURCHASE!J:J) -> 17 | O87: =sumif('SELLING CASH'!E:E,C87,'SELLING CASH'!F:F) -> 17 | P87: =sumif('SELLING CREDIT'!F:F,C87,'SELLING CREDIT'!G:G) -> 0 | Q87: =(N87+G87)-(O87+P87) -> 0 | V87: C-0086 | W87: Bpk. Cuing/Leles | X87: =sumif('SELLING CREDIT'!E:E,W87,'SELLING CREDIT'!P:P) -> 9225000 | Y87: =sumif('PAYMENT CREDIT'!E:E,W87,'PAYMENT CREDIT'!F:F) -> 9195000 | Z87: =X87-Y87 -> 30000
C88: Bridgestone 185/60 15 Ecopia | D88: 185/60 15 | E88: Ecopia | F88: Bridgestone | G88: 6 | H88: 975000 | I88: 865000 | J88: IBU | K88: 1 | L88: 0 | M88: Tire | N88: =sumif(PURCHASE!I:I,C88,PURCHASE!J:J) -> 0 | O88: =sumif('SELLING CASH'!E:E,C88,'SELLING CASH'!F:F) -> 5 | P88: =sumif('SELLING CREDIT'!F:F,C88,'SELLING CREDIT'!G:G) -> 0 | Q88: =(N88+G88)-(O88+P88) -> 1 | V88: C-0087 | W88: Bpk. Fajar Kurnia | X88: =sumif('SELLING CREDIT'!E:E,W88,'SELLING CREDIT'!P:P) -> 10000000 | Y88: =sumif('PAYMENT CREDIT'!E:E,W88,'PAYMENT CREDIT'!F:F) -> 9000000 | Z88: =X88-Y88 -> 1000000
C89: Bridgestone 185/60 15 TECHNO | D89: 185/60 15 | E89: TECHNO | F89: Bridgestone | G89: 0 | H89: 775000 | I89: 671104 | J89: IBU | K89: 1 | L89: 0 | M89: Tire | N89: =sumif(PURCHASE!I:I,C89,PURCHASE!J:J) -> 4 | O89: =sumif('SELLING CASH'!E:E,C89,'SELLING CASH'!F:F) -> 4 | P89: =sumif('SELLING CREDIT'!F:F,C89,'SELLING CREDIT'!G:G) -> 0 | Q89: =(N89+G89)-(O89+P89) -> 0 | V89: C-0088 | W89: Bpk. Koko Cibeet | X89: =sumif('SELLING CREDIT'!E:E,W89,'SELLING CREDIT'!P:P) -> 10250000 | Y89: =sumif('PAYMENT CREDIT'!E:E,W89,'PAYMENT CREDIT'!F:F) -> 10250000 | Z89: =X89-Y89 -> 0
C90: Bridgestone 185/65 15 Ecopia | D90: 185/65 15 | E90: Ecopia | F90: Bridgestone | G90: 10 | H90: 845000 | I90: 754660.6 | J90: IBU | K90: 1 | L90: 0 | M90: Tire | N90: =sumif(PURCHASE!I:I,C90,PURCHASE!J:J) -> 113 | O90: =sumif('SELLING CASH'!E:E,C90,'SELLING CASH'!F:F) -> 109 | P90: =sumif('SELLING CREDIT'!F:F,C90,'SELLING CREDIT'!G:G) -> 0 | Q90: =(N90+G90)-(O90+P90) -> 14 | V90: C-0089 | W90: Bpk. H. Nundang | X90: =sumif('SELLING CREDIT'!E:E,W90,'SELLING CREDIT'!P:P) -> 1580000 | Y90: =sumif('PAYMENT CREDIT'!E:E,W90,'PAYMENT CREDIT'!F:F) -> 1580000 | Z90: =X90-Y90 -> 0
... C99: Bridgestone 195/14 Duravis | D99: 195/14 | E99: Duravis | F99: Bridgestone | G99: 1 | H99: 1030000 | I99: 930000 | J99: IBU | K99: 1 | L99: 0 | M99: Tire | N99: =sumif(PURCHASE!I:I,C99,PURCHASE!J:J) -> 0 | O99: =sumif('SELLING CASH'!E:E,C99,'SELLING CASH'!F:F) -> 0 | P99: =sumif('SELLING CREDIT'!F:F,C99,'SELLING CREDIT'!G:G) -> 1 | Q99: =(N99+G99)-(O99+P99) -> 0 | V99: C-0098 | W99: Bpk. Ujang Sp | X99: =sumif('SELLING CREDIT'!E:E,W99,'SELLING CREDIT'!P:P) -> 3500000 | Y99: =sumif('PAYMENT CREDIT'!E:E,W99,'PAYMENT CREDIT'!F:F) -> 0 | Z99: =X99-Y99 -> 3500000
C100: Bridgestone 195/15 | D100: 195/15 | F100: Bridgestone | G100: 3 | H100: 1100000 | I100: 980000 | J100: IBU | K100: 1 | L100: 0 | M100: Tire | N100: =sumif(PURCHASE!I:I,C100,PURCHASE!J:J) -> 0 | O100: =sumif('SELLING CASH'!E:E,C100,'SELLING CASH'!F:F) -> 2 | P100: =sumif('SELLING CREDIT'!F:F,C100,'SELLING CREDIT'!G:G) -> 1 | Q100: =(N100+G100)-(O100+P100) -> 0 | V100: C-0099 | W100: Bpk. Suyut | X100: =sumif('SELLING CREDIT'!E:E,W100,'SELLING CREDIT'!P:P) -> 2150000 | Y100: =sumif('PAYMENT CREDIT'!E:E,W100,'PAYMENT CREDIT'!F:F) -> 3200000 | Z100: =X100-Y100 -> -1050000
C101: Bridgestone 195/50 16 Techno | D101: 195/50 16 | E101: Techno | F101: Bridgestone | G101: 4 | H101: 885000 | I101: 784000 | J101: IBU | K101: 1 | L101: 0 | M101: Tire | N101: =sumif(PURCHASE!I:I,C101,PURCHASE!J:J) -> 4 | O101: =sumif('SELLING CASH'!E:E,C101,'SELLING CASH'!F:F) -> 4 | P101: =sumif('SELLING CREDIT'!F:F,C101,'SELLING CREDIT'!G:G) -> 0 | Q101: =(N101+G101)-(O101+P101) -> 4 | V101: C-0100 | W101: Bpk Nana Rancajigang | X101: =sumif('SELLING CREDIT'!E:E,W101,'SELLING CREDIT'!P:P) -> 3960000 | Y101: =sumif('PAYMENT CREDIT'!E:E,W101,'PAYMENT CREDIT'!F:F) -> 3960000 | Z101: =X101-Y101 -> 0
C102: Bridgestone 195/55 15 Techno | D102: 195/55 15 | E102: Techno | F102: Bridgestone | G102: 6 | H102: 920000 | I102: 834000 | J102: IBU | K102: 1 | L102: 0 | M102: Tire | N102: =sumif(PURCHASE!I:I,C102,PURCHASE!J:J) -> 0 | O102: =sumif('SELLING CASH'!E:E,C102,'SELLING CASH'!F:F) -> 6 | P102: =sumif('SELLING CREDIT'!F:F,C102,'SELLING CREDIT'!G:G) -> 0 | Q102: =(N102+G102)-(O102+P102) -> 0 | V102: C-0101 | W102: Bpk. Khairul Magung | X102: =sumif('SELLING CREDIT'!E:E,W102,'SELLING CREDIT'!P:P) -> 2305000 | Y102: =sumif('PAYMENT CREDIT'!E:E,W102,'PAYMENT CREDIT'!F:F) -> 2305000 | Z102: =X102-Y102 -> 0
C103: Bridgestone 195/55 16 Ecopia | D103: 195/55 16 | E103: Ecopia | F103: Bridgestone | G103: 0 | H103: 1050000 | I103: 960000 | J103: IBU | K103: 1 | L103: 0 | M103: Tire | N103: =sumif(PURCHASE!I:I,C103,PURCHASE!J:J) -> 0 | O103: =sumif('SELLING CASH'!E:E,C103,'SELLING CASH'!F:F) -> 0 | P103: =sumif('SELLING CREDIT'!F:F,C103,'SELLING CREDIT'!G:G) -> 0 | Q103: =(N103+G103)-(O103+P103) -> 0 | V103: C-0102 | W103: BPK EPUL/BPK A ADE | X103: =sumif('SELLING CREDIT'!E:E,W103,'SELLING CREDIT'!P:P) -> 8370000 | Y103: =sumif('PAYMENT CREDIT'!E:E,W103,'PAYMENT CREDIT'!F:F) -> 4620000 | Z103: =X103-Y103 -> 3750000
C104: Bridgestone 195/55 16 Techno Sport | D104: 195/55 16 | E104: Techno Sport | F104: Bridgestone | G104: 6 | H104: 940000 | I104: 844838.5 | J104: IBU | K104: 1 | L104: 0 | M104: Tire | N104: =sumif(PURCHASE!I:I,C104,PURCHASE!J:J) -> 12 | O104: =sumif('SELLING CASH'!E:E,C104,'SELLING CASH'!F:F) -> 20 | P104: =sumif('SELLING CREDIT'!F:F,C104,'SELLING CREDIT'!G:G) -> 0 | Q104: =(N104+G104)-(O104+P104) -> -2 | V104: C-0103 | W104: Bpk. H. Aep BCP Patrol | X104: =sumif('SELLING CREDIT'!E:E,W104,'SELLING CREDIT'!P:P) -> 53580000 | Y104: =SUMIF('PAYMENT CREDIT'!E:E,W104,'PAYMENT CREDIT'!F:F) -> 50980000 | Z104: =X104-Y104 -> 2600000
C105: Bridgestone 195/60 15 Techno | D105: 195/60 15 | E105: Techno | F105: Bridgestone | G105: 6 | H105: 810000 | I105: 715000 | J105: IBU | K105: 0 | L105: 0 | M105: Tire | N105: =sumif(PURCHASE!I:I,C105,PURCHASE!J:J) -> 4 | O105: =sumif('SELLING CASH'!E:E,C105,'SELLING CASH'!F:F) -> 9 | P105: =sumif('SELLING CREDIT'!F:F,C105,'SELLING CREDIT'!G:G) -> 0 | Q105: =(N105+G105)-(O105+P105) -> 1 | V105: C-0105 | W105: Bapak Velg | X105: =sumif('SELLING CREDIT'!E:E,W105,'SELLING CREDIT'!P:P) -> 1380000 | Y105: =SUMIF('PAYMENT CREDIT'!E:E,W105,'PAYMENT CREDIT'!F:F) -> 1380000 | Z105: =X105-Y105 -> 0
C106: Bridgestone 195/60 16 Ecopia | D106: 195/60 16 | E106: Ecopia | F106: Bridgestone | G106: 4 | H106: 1085000 | I106: 980542.4 | J106: IBU | K106: 1 | L106: 0 | M106: Tire | N106: =sumif(PURCHASE!I:I,C106,PURCHASE!J:J) -> 13 | O106: =sumif('SELLING CASH'!E:E,C106,'SELLING CASH'!F:F) -> 14 | P106: =sumif('SELLING CREDIT'!F:F,C106,'SELLING CREDIT'!G:G) -> 2 | Q106: =(N106+G106)-(O106+P106) -> 1 | V106: C-0106 | W106: Bpk. Pian Pakacangan | X106: =sumif('SELLING CREDIT'!E:E,W106,'SELLING CREDIT'!P:P) -> 1820000 | Y106: =SUMIF('PAYMENT CREDIT'!E:E,W106,'PAYMENT CREDIT'!F:F) -> 1825000 | Z106: =X106-Y106 -> -5000
C107: Bridgestone 195/65 15 Ecopia | D107: 195/65 15 | E107: Ecopia | F107: Bridgestone | G107: 4 | H107: 940000 | I107: 851110.38 | J107: IBU | K107: 1 | L107: 0 | M107: Tire | N107: =sumif(PURCHASE!I:I,C107,PURCHASE!J:J) -> 68 | O107: =sumif('SELLING CASH'!E:E,C107,'SELLING CASH'!F:F) -> 55 | P107: =sumif('SELLING CREDIT'!F:F,C107,'SELLING CREDIT'!G:G) -> 4 | Q107: =(N107+G107)-(O107+P107) -> 13 | V107: C-0107 | W107: Bpk. SS | X107: =sumif('SELLING CREDIT'!E:E,W107,'SELLING CREDIT'!P:P) -> 150000 | Y107: =SUMIF('PAYMENT CREDIT'!E:E,W107,'PAYMENT CREDIT'!F:F) -> 150000 | Z107: =X107-Y107 -> 0
C108: Bridgestone 195/70 14 Ecopia | D108: 195/70 14 | E108: Ecopia | F108: Bridgestone | G108: 4 | H108: 850000 | I108: 759539.2 | J108: IBU | K108: 1 | L108: 0 | M108: Tire | N108: =sumif(PURCHASE!I:I,C108,PURCHASE!J:J) -> 35 | O108: =sumif('SELLING CASH'!E:E,C108,'SELLING CASH'!F:F) -> 34 | P108: =sumif('SELLING CREDIT'!F:F,C108,'SELLING CREDIT'!G:G) -> 0 | Q108: =(N108+G108)-(O108+P108) -> 5 | V108: C-0108 | W108: Bpk. H Makmun KSM ELf | X108: =sumif('SELLING CREDIT'!E:E,W108,'SELLING CREDIT'!P:P) -> 2635000 | Y108: =SUMIF('PAYMENT CREDIT'!E:E,W108,'PAYMENT CREDIT'!F:F) -> 2635000 | Z108: =X108-Y108 -> 0
C109: Bridgestone 195/70 14 Techno | D109: 195/70 14 | E109: Techno | F109: Bridgestone | G109: 0 | H109: 760000 | I109: 660000 | J109: IBU | K109: 1 | L109: 0 | M109: Tire | N109: =sumif(PURCHASE!I:I,C109,PURCHASE!J:J) -> 0 | O109: =sumif('SELLING CASH'!E:E,C109,'SELLING CASH'!F:F) -> 0 | P109: =sumif('SELLING CREDIT'!F:F,C109,'SELLING CREDIT'!G:G) -> 0 | Q109: =(N109+G109)-(O109+P109) -> 0 | V109: C-0109 | X109: =sumif('SELLING CREDIT'!E:E,W109,'SELLING CREDIT'!P:P) -> 0 | Y109: =SUMIF('PAYMENT CREDIT'!E:E,W109,'PAYMENT CREDIT'!F:F) -> 0 | Z109: =X109-Y109 -> 0
A110: 1 | C110: Bridgestone 195/70 14 Turanza T005A | D110: 195/70 14 | E110: Turanza T005A | F110: Bridgestone | G110: 0 | H110: 995000 | I110: 873689.5 | J110: IBU | K110: 1 | L110: 0 | M110: Tire | N110: =sumif(PURCHASE!I:I,C110,PURCHASE!J:J) -> 2 | O110: =sumif('SELLING CASH'!E:E,C110,'SELLING CASH'!F:F) -> 2 | P110: =sumif('SELLING CREDIT'!F:F,C110,'SELLING CREDIT'!G:G) -> 0 | Q110: =(N110+G110)-(O110+P110) -> 0 | V110: C-0110 | W110: Ujang Samsu Sudi | X110: =sumif('SELLING CREDIT'!E:E,W110,'SELLING CREDIT'!P:P) -> 1820000 | Y110: =SUMIF('PAYMENT CREDIT'!E:E,W110,'PAYMENT CREDIT'!F:F) -> 1820000 | Z110: =X110-Y110 -> 0
C111: Bridgestone 205/45 17 Techno Sport | D111: 205/45 17 | E111: Techno Sport | F111: Bridgestone | G111: 4 | H111: 1000000 | I111: 799425 | J111: IBU | K111: 1 | L111: 0 | M111: Tire | N111: =sumif(PURCHASE!I:I,C111,PURCHASE!J:J) -> 1 | O111: =sumif('SELLING CASH'!E:E,C111,'SELLING CASH'!F:F) -> 5 | P111: =sumif('SELLING CREDIT'!F:F,C111,'SELLING CREDIT'!G:G) -> 0 | Q111: =(N111+G111)-(O111+P111) -> 0 | V111: C-0111 | W111: Fajar travel | X111: =sumif('SELLING CREDIT'!E:E,W111,'SELLING CREDIT'!P:P) -> 3150000 | Y111: =SUMIF('PAYMENT CREDIT'!E:E,W111,'PAYMENT CREDIT'!F:F) -> 0 | Z111: =X111-Y111 -> 3150000
C112: Bridgestone 205/55 16 Ecopia | D112: 205/55 16 | E112: Ecopia | F112: Bridgestone | G112: 0 | H112: 1250000 | I112: 1120000 | J112: IBU | K112: 1 | L112: 0 | M112: Tire | N112: =sumif(PURCHASE!I:I,C112,PURCHASE!J:J) -> 0 | O112: =sumif('SELLING CASH'!E:E,C112,'SELLING CASH'!F:F) -> 2 | P112: =sumif('SELLING CREDIT'!F:F,C112,'SELLING CREDIT'!G:G) -> 0 | Q112: =(N112+G112)-(O112+P112) -> -2 | V112: C-0112 | W112: Bpk. Iman Rohiman/baru jati | X112: =sumif('SELLING CREDIT'!E:E,W112,'SELLING CREDIT'!P:P) -> 1580000 | Y112: =SUMIF('PAYMENT CREDIT'!E:E,W112,'PAYMENT CREDIT'!F:F) -> 1580000 | Z112: =X112-Y112 -> 0
C113: Bridgestone 205/55 16 Techno Sport | D113: 205/55 16 | E113: Techno Sport | F113: Bridgestone | G113: 2 | H113: 980000 | I113: 889369.5 | J113: IBU | K113: 1 | L113: 0 | M113: Tire | N113: =sumif(PURCHASE!I:I,C113,PURCHASE!J:J) -> 14 | O113: =sumif('SELLING CASH'!E:E,C113,'SELLING CASH'!F:F) -> 15 | P113: =sumif('SELLING CREDIT'!F:F,C113,'SELLING CREDIT'!G:G) -> 0 | Q113: =(N113+G113)-(O113+P113) -> 1 | V113: C-0113 | W113: Bpk. Oman Majalaya | X113: =sumif('SELLING CREDIT'!E:E,W113,'SELLING CREDIT'!P:P) -> 3230000 | Y113: =SUMIF('PAYMENT CREDIT'!E:E,W113,'PAYMENT CREDIT'!F:F) -> 3230000 | Z113: =X113-Y113 -> 0
C114: Bridgestone 205/65 15 Ecopia | D114: 205/65 15 | E114: Ecopia | F114: Bridgestone | G114: 4 | H114: 1030000 | I114: 879567 | J114: IBU | K114: 1 | L114: 0 | M114: Tire | N114: =sumif(PURCHASE!I:I,C114,PURCHASE!J:J) -> 63 | O114: =sumif('SELLING CASH'!E:E,C114,'SELLING CASH'!F:F) -> 47 | P114: =sumif('SELLING CREDIT'!F:F,C114,'SELLING CREDIT'!G:G) -> 2 | Q114: =(N114+G114)-(O114+P114) -> 18
C115: Bridgestone 205/65 15 Turanza | D115: 205/65 15 | E115: Turanza | F115: Bridgestone | G115: 1 | H115: 1200000 | I115: 1085500 | J115: IBU | K115: 1 | L115: 0 | M115: Tire | N115: =sumif(PURCHASE!I:I,C115,PURCHASE!J:J) -> 5 | O115: =sumif('SELLING CASH'!E:E,C115,'SELLING CASH'!F:F) -> 4 | P115: =sumif('SELLING CREDIT'!F:F,C115,'SELLING CREDIT'!G:G) -> 5 | Q115: =(N115+G115)-(O115+P115) -> -3
C116: Bridgestone 205/65 15 Turanza T6 | D116: 205/65 15 | E116: Turanza | F116: Bridgestone | G116: 4 | H116: 1120000 | I116: 1027000 | J116: IBU | K116: 1 | L116: 0 | M116: Tire | N116: =sumif(PURCHASE!I:I,C116,PURCHASE!J:J) -> 5 | O116: =sumif('SELLING CASH'!E:E,C116,'SELLING CASH'!F:F) -> 6 | P116: =sumif('SELLING CREDIT'!F:F,C116,'SELLING CREDIT'!G:G) -> 0 | Q116: =(N116+G116)-(O116+P116) -> 3
C117: Bridgestone 205/65 16 Ecopia | D117: 205/65 16 | E117: Ecopia | F117: Bridgestone | G117: 2 | H117: 1020000 | I117: 943430.5 | J117: IBU | K117: 1 | L117: 0 | M117: Tire | N117: =sumif(PURCHASE!I:I,C117,PURCHASE!J:J) -> 28 | O117: =sumif('SELLING CASH'!E:E,C117,'SELLING CASH'!F:F) -> 30 | P117: =sumif('SELLING CREDIT'!F:F,C117,'SELLING CREDIT'!G:G) -> 0 | Q117: =(N117+G117)-(O117+P117) -> 0
...

Sheet EXPENSES
C1: Date | D1: Amount | E1: Explain | F1: Category | G1: Payment | H1: =counta(C:C) -> 1194 | I1: =SUM(D:D) -> 598098018 | K1: Date | L1: Amount | M1: Explain | N1: Category | O1: =sum(L:L) -> 457685000
C2: 45962 | D2: 60000 | E2: Rokok Bian ke Indaramayu | F2: Personal | G2: Cashier | K2: 45965 | L2: 100000 | M2: Admin mah nabil | N2: Store
C3: 45962 | D3: 200000 | E3: Ibu kasih ke PKL | F3: Personal | G3: Cashier | K3: 45965 | L3: 350000 | M3: Ibu bayar ke mamah nabil | N3: Personal
C4: 45962 | D4: 150000 | E4: Biaya service ka ade bian | F4: Personal | G4: Cashier | K4: 45968 | L4: 17000000 | M4: Ka Mah nabil | N4: Store
C5: 45963 | D5: 20000 | E5: Makanan burung | F5: Personal | G5: Cashier | K5: 45972 | L5: 8000000 | M5: Ka Mah nabil | N5: Store
C6: 45963 | D6: 20000 | E6: Tempe | F6: Personal | G6: Cashier | K6: 45976 | L6: 12000000 | M6: Ka Mah nabil | N6: Store
C7: 45964 | D7: 20000 | E7: Bensin Scoopy | F7: Personal | G7: Cashier | K7: 45978 | L7: 20000000 | M7: Ka Mah nabil | N7: Store
C8: 45965 | D8: 20000 | E8: Bian sarapan ciomay | F8: Personal | G8: Cashier | K8: 45979 | L8: 15000000 | M8: Ka Mah nabil | N8: Store
C9: 45965 | D9: 100000 | E9: Bian bensin | F9: Personal | G9: Cashier | K9: 45980 | L9: 10000000 | M9: Ka Mah nabil | N9: Store
C10: 45965 | D10: 15000 | E10: Cat rambut bian | F10: Personal | G10: Cashier | K10: 45981 | L10: 100000 | M10: Ka Mah nabil | N10: Store
C11: 45965 | D11: 20000 | E11: Kosentra/makanan ayam | F11: Personal | G11: Cashier | K11: 45981 | L11: 10000000 | M11: Ka Mah nabil | N11: Store
C12: 45965 | D12: 15000 | E12: nasi goreng bian | F12: Personal | G12: Cashier | K12: 45982 | L12: 20000000 | M12: Ka Mah nabil | N12: Store
C13: 45965 | D13: 32000 | E13: Shopeefood Bian | F13: Personal | G13: Cashier | K13: 45985 | L13: 10100000 | M13: Ka Mah nabil | N13: Store
C14: 45965 | D14: 350000 | E14: Paket yang mah angel | F14: Personal | G14: IBU | K14: 45986 | L14: 10100000 | M14: Ka Mah nabil | N14: Store
C15: 45965 | D15: 2500000 | E15: PAKET UANG ke mah nabil | F15: Personal | G15: IBU | H15: Link | K15: 45986 | L15: 7100000 | M15: Ka Mah nabil | N15: Store
C16: 45965 | D16: 700000 | E16: Shopee Ibu | F16: Personal | G16: IBU | K16: 45988 | L16: 3000000 | M16: Ka Mah nabil | N16: Store
C17: 45966 | D17: 13000 | E17: Bian sarapan ciomay | F17: Personal | G17: Cashier | K17: 45994 | L17: 10100000 | M17: Ka Mah nabil | N17: Store
C18: 45966 | D18: 50000 | E18: WD 1 | F18: Store | G18: Cashier | K18: 45995 | L18: 11000000 | M18: Ka Mah nabil | N18: Store
C19: 45966 | D19: 81000 | E19: BIAN COD | F19: Personal | G19: Cashier | K19: 45996 | L19: 15150000 | M19: Ka Mah nabil | N19: Store
C20: 45966 | D20: 15000 | E20: BIAN cat rambut | F20: Personal | G20: Cashier | K20: 45998 | L20: 10000000 | M20: Ka Mah nabil | N20: Store
C21: 45966 | D21: 446600 | E21: Ibu belanja ke borma | F21: Personal | G21: IBU | H21: Link | K21: 45999 | L21: 10000000 | M21: Ka Mah nabil | N21: Store
C22: 45966 | D22: 200000 | E22: Ibu belanja ke bu oo | F22: Personal | G22: IBU | K22: 46000 | L22: 10100000 | M22: Ka Mah nabil | N22: Store
C23: 45966 | D23: 275000 | E23: Dangdang | F23: Personal | G23: IBU | K23: 46001 | L23: 10100000 | M23: Ka Mah nabil | N23: Store
C24: 45966 | D24: 360000 | E24: Makanan Ayam | F24: Personal | G24: IBU | K24: 46002 | L24: 10100000 | M24: Ka Mah nabil | N24: Store
C25: 45966 | D25: 40000 | E25: Kispray | F25: Personal | G25: IBU | K25: 46003 | L25: 10100000 | M25: Ka Mah nabil | N25: Store
C26: 45966 | D26: 1003000 | E26: Isi token listrik | F26: Store | G26: IBU | K26: 46004 | L26: 10100000 | M26: Ka Mah nabil | N26: Store
C27: 45967 | D27: 20000 | E27: SUPIR G YEAR | F27: Store | G27: Cashier | K27: 46005 | L27: 2000000 | M27: Ka Mah nabil | N27: Store
C28: 45967 | D28: 40000 | E28: BENSIN SCOOPY FULL TANK | F28: Store | G28: Cashier | K28: 46005 | L28: 8000000 | M28: Ka Mah nabil | N28: Store
C29: 45967 | D29: 10000 | E29: BASO KUTIL | F29: Personal | G29: Cashier | K29: 46009 | L29: 10100000 | M29: Ka Mah nabil | N29: Store
C30: 45967 | D30: 7000 | E30: bIAN CIOMAY | F30: Personal | G30: Cashier | K30: 46010 | L30: 10100000 | M30: Ka Mah nabil | N30: Store
C31: 45968 | D31: 10000 | E31: Batagor Bian | F31: Personal | G31: Cashier | K31: 46012 | L31: 10100000 | M31: Ka Mah nabil | N31: Store
C32: 45968 | D32: 10000 | E32: Serbuk untuk minuman ayam | F32: Personal | G32: Cashier | K32: 46013 | L32: 10100000 | M32: Ka Mah nabil | N32: Store
C33: 45968 | D33: 36000 | E33: Bian makan | F33: Personal | G33: Cashier | K33: 46014 | L33: 11000000 | M33: Ka Mah nabil | N33: Store
C34: 45968 | D34: 10000 | E34: Ibu beli petis nitip ka a ade | F34: Personal | G34: Cashier | K34: 46015 | L34: 20000000 | M34: Ka Mah nabil | N34: Store
C35: 45968 | D35: 10000 | E35: BASO KUTIL | F35: Personal | G35: Cashier | H35: Link | K35: 46014 | L35: 10100000 | M35: Ka Mah nabil | N35: Store
C36: 45968 | D36: 20000 | E36: Bian ambil uang | F36: Personal | G36: Cashier | K36: 46024 | L36: 5000000 | M36: Ka Mah nabil | N36: Store
C37: 45968 | D37: 455380 | E37: Ibu belanja ke Griya buah bahu | F37: Personal | G37: IBU | K37: 46024 | L37: 10100000 | M37: Ka Mah nabil | N37: Store
C38: 45968 | D38: 2087900 | E38: Obat bulanan Ibu - Kimia Farma | F38: Personal | G38: IBU | K38: 46026 | L38: 20000000 | M38: Ka Mah nabil | N38: Store
C39: 45968 | D39: 35000 | E39: Ibu Jajan Donat kepang | F39: Personal | G39: IBU | K39: 46028 | L39: 15000000 | M39: Ka Mah nabil | N39: Store
C40: 45968 | D40: 408000 | E40: Solar Kijang | F40: Personal | G40: IBU | K40: 46030 | L40: 5000000 | M40: Ka Mah nabil | N40: Store
C41: 45968 | D41: 2000000 | E41: Sedekah bulanan rumah Yatim | F41: Personal | G41: IBU | H41: Link | K41: 46031 | L41: 10000000 | M41: Ka Mah nabil | N41: Store
C42: 45968 | D42: 1000000 | E42: Ibu TF ke Kakak | F42: Personal | G42: IBU | K42: 46032 | L42: 10810000 | M42: Ka Mah nabil | N42: Store
C43: 45968 | D43: 1000000 | E43: Ibu TF ke Kakak | F43: Personal | G43: IBU | K43: 46035 | L43: 15000000 | M43: Ka Mah nabil | N43: Store
C44: 45969 | D44: 40000 | E44: Makanan Anjing | F44: Personal | G44: Cashier | K44: 46036 | L44: 10000000 | M44: Ka Mah nabil | N44: Store
C45: 45969 | D45: 10000 | E45: Layer | F45: Personal | G45: Cashier | K45: 46036 | L45: 15675000 | M45: Ka Mah nabil | N45: Store
C46: 45969 | D46: 23000 | E46: Bian roti bakar | F46: Personal | G46: Cashier
C47: 45969 | D47: 20000 | E47: Bian seblak | F47: Personal | G47: Cashier | H47: Link
C48: 45969 | D48: 30000 | E48: Bian jajan | F48: Personal | G48: Cashier
C49: 45969 | D49: 50000 | E49: kampas rem depan belakang scoopy | F49: Personal | G49: Cashier | H49: Link
C50: 45969 | D50: 4050000 | E50: Gaji karyawan | F50: Toko | G50: IBU | H50: Link
C51: 45970 | D51: 210000 | E51: Gaji karyawan | F51: Toko | G51: IBU | H51: LInk
C52: 45971 | D52: 50000 | E52: Bian dan pak jejen ambil ban | F52: Personal | G52: Cashier | H52: Link
C53: 45971 | D53: 13000 | E53: Bian jajan makroni | F53: Personal | G53: Cashier | H53: Link
C54: 45971 | D54: 50000 | E54: Bensin SCOOPY | F54: Personal | G54: Cashier
C55: 45972 | D55: 27000 | E55: Cuangki | F55: Personal | G55: Cashier
C56: 45972 | D56: 20000 | E56: Supir Dunlop | F56: Personal | G56: Cashier
C57: 45972 | D57: 20000 | E57: Supir Advance | F57: Personal | G57: Cashier
C58: 45972 | D58: 900000 | E58: Pajak Oktober bian | F58: Personal | G58: IBU
C59: 45972 | D59: 280000 | E59: Minyak | F59: Personal | G59: IBU
C60: 45973 | D60: 180000 | E60: Timah balancing 2 | F60: Store | G60: Cashier
C61: 45973 | D61: 10000 | E61: BASO KUTIL | F61: Personal | G61: Cashier
C62: 45973 | D62: 40000 | E62: BIAN COD | F62: Personal | G62: Cashier
C63: 45973 | D63: 13000 | E63: Bian nasi goreng | F63: Personal | G63: Cashier
C64: 45974 | D64: 12000 | E64: Ciomay sarapan bian | F64: Personal | G64: Cashier
C65: 45974 | D65: 50000 | E65: Bian cukur rambut | F65: Personal | G65: Cashier
... C350: 46045 | D350: 175000 | E350: Tambang, kawat las dan gurinda | F350: Store | G350: Cashier
C351: 46045 | D351: 20000 | F351: Personal | G351: Cashier
C352: 46045 | D352: 50000 | E352: Bian cukur | F352: Personal | G352: Cashier
C353: 46046 | D353: 600000 | E353: Pentil | F353: Store | G353: Cashier
C354: 46046 | D354: 50000 | E354: makanan anjing | F354: Personal | G354: Cashier
C355: 46046 | D355: 4100000 | E355: Gaji karyawan | F355: Store | G355: IBU
C356: 46047 | D356: 210000 | E356: Gaji karyawan minggu | F356: Store | G356: IBU
C357: 46048 | D357: 85000 | E357: Kawat las dan stainless | F357: Personal | G357: Cashier
C358: 46048 | D358: 20000 | E358: Bensin scoopy | F358: Personal | G358: Cashier
C359: 46048 | D359: 65000 | E359: Bian COD | F359: Personal | G359: Cashier
C360: 46048 | D360: 39000 | E360: Gurinda | F360: Personal | G360: Cashier
C361: 46048 | D361: 20000 | E361: Bian cimol dan kebab | F361: Personal | G361: Cashier
C362: 46049 | D362: 20000 | E362: Pak Iyan ambil ban | F362: Store | G362: Cashier
C363: 46049 | D363: 100000 | E363: Bian beli etol | F363: Personal | G363: Cashier
... C542: 46109 | D542: 20000 | E542: Bensin scoopy | F542: Personal | G542: Cashier
C543: 46109 | D543: =420000+468000+625000+500000+213000+284000+300000 -> 2810000 | E543: Gaji Karyawan | F543: Personal | G543: IBU
C544: 46110 | D544: 270000 | E544: Gaji Karyawan minggu | F544: Personal | G544: IBU
C545: 46111 | D545: 92000 | E545: Bian COD | F545: Personal | G545: Cashier
C546: 46111 | D546: 100000 | E546: Ibu | F546: Personal | G546: Cashier
C547: 46111 | D547: 50000 | E547: Bian cukur | F547: Personal | G547: Cashier
C548: 46111 | D548: 20000 | E548: Bensin scoopy | F548: Personal | G548: Cashier
C549: 46111 | D549: 175000 | E549: Mas suryo belanja | F549: Personal | G549: Cashier
C550: 46111 | D550: 40000 | E550: Makanan Anjing | F550: Personal | G550: Cashier
C551: 46111 | D551: 80000 | E551: Bian shopeefood | F551: Personal | G551: Cashier
C552: 46112 | D552: 145000 | E552: COD kunci L tekiro | F552: Personal | G552: Cashier
C553: 46112 | D553: 15000 | E553: Bian makan siomay | F553: Personal | G553: Cashier
C554: 46112 | D554: 80000 | E554: batu asah dan baut | F554: Personal | G554: Cashier
C555: 46112 | D555: 365000 | E555: Makanan ayam | F555: Personal | G555: Cashier
... C666: 46145 | D666: 70000 | E666: nambah COD ibu | F666: Personal | G666: Cashier
C667: 46145
C668: 46146 | D668: 503000 | E668: Token listrik | F668: Store | G668: IBU
C669: 46146 | D669: 20000 | E669: Bensin scoopy | F669: Personal | G669: Cashier
C670: 46146 | D670: 20000 | E670: Nambah bian gofood | F670: Personal | G670: Cashier
C671: 46146 | D671: 50000 | E671: Ibu untuk mobil | F671: Personal | G671: Cashier
C672: 46146 | D672: 120000 | E672: Bayar barcode | F672: Personal | G672: Cashier
...

Sheet Sheet21
H3: Service
B4: Barang | C4: Jumlah | D4: Modal | E4: Laba | F4: Total | H4: Jenis Jasa | I4: Jumlah | J4: Harga | K4: Komisi montir | L4: Profit
B5: Advance 1000/20 GL662A+ | C5: 1 | D5: 4200000 | E5: 4450000 | F5: 250000 | H5: Bongkar Pasang
B6: BD 13 GT | C6: 2 | D6: 102000 | E6: 270000 | F6: 60000 | H6: SERVICE
B7: BD 15 GT | C7: 1 | D7: 161840 | E7: 200000 | F7: 35000 | H7: SPOORING
B8: Dunlop 155/80 12 SP10 | C8: 1 | D8: 415000 | E8: 470000 | F8: 55000 | H8: SPOORING SS/CARRY LOS BAK
B9: Dunlop 165/13 LT5 | C9: 2 | D9: 610000 | E9: 1400000 | F9: 180000
B10: Dunlop 175/13 LT5 | C10: 17 | D10: 5051000 | E10: 12200000 | F10: 1445000 | H10: OLi
B11: Dunlop 175/65 14 EC300 | C11: 3 | D11: 1100000 | E11: 1915000 | F11: 265000 | H11: Nama Barang | I11: Jumlah | J11: Total Harga | K11: Modal | L11: Profit
B12: Dunlop 185/14 LT5 | C12: 5 | D12: 2278500 | E12: 4250000 | F12: 450000
B13: Dunlop 185/60 15 TOURING | C13: 2 | D13: 620000 | E13: 1420000 | F13: 180000
B14: Dunlop 185/70 14 ENASEV | C14: 7 | D14: 2408000 | E14: 4900000 | F14: 665000
B15: Dunlop 195/50 16 EC300 | C15: 1 | D15: 814000 | E15: 920000 | F15: 105000
B16: Dunlop 205/65 15 EC300 | C16: 1 | D16: 779500 | E16: 880000 | F16: 100000
B17: Flap 15 Truckoor | C17: 1 | D17: 36630 | E17: 70000 | F17: 30000 | H17: Pembayaran Tempo
B18: GT 165/80 13 ECOTEC | C18: 16 | D18: 976640 | E18: 9140000 | F18: 1300000
B19: GT 185/14 MAXMILLER | C19: 1 | D19: 711000 | E19: 800000 | F19: 85000
B20: GT 185/70 14 ECOTEC | C20: 2 | D20: 548100 | E20: 1280000 | F20: 180000
B21: GT 195/65 15 ECOTEC | C21: 1 | D21: 628100 | E21: 720000 | F21: 90000
B22: GT 205/70 15 ECOTEC | C22: 2 | D22: 689900 | E22: 1500000 | F22: 120000
B23: GT 500/12 8PR | C23: 2 | D23: 653400 | E23: 760000 | F23: 100000 | H23: Penjualan Tempo
B24: GT 640/13 8PR | C24: 4 | D24: 505000 | E24: 2360000 | F24: 340000
B25: TIRON 750/15 12PR | C25: 4 | D25: 1475000 | E25: 6240000 | F25: 340000
B26: Velg 16 CEMAX 750-20 14 | C26: 1 | D26: 1170000 | E26: 1270000 | F26: 100000
B27: Aspira Filter Oli Avaza-Agya | C27: 1 | D27: 19200 | E27: 25000 | F27: 5000
B28: Balancing 30 | C28: 19 | D28: 90000 | E28: 535000 | F28: 345000
B29: Baut Camber | C29: 2 | D29: 150000 | E29: 500000 | F29: 200000
B30: ICOSON Filter Oli Avanza | C30: 3 | D30: 56700 | E30: 75000 | F30: 15000
B31: Lower Arm (Sayap) | C31: 1 | D31: 158530.2 | E31: 240000 | F31: 40000
B33: Total
B34: Uang Bian
B35: Gaji Karyawan
B36: Pengeluaran
B38: Pendapatan Bersih
B39: Pendapatan toko selama seminggu | E39: 31 Agustus - 5 September
B40: Ban keluar
B41: Toko
B42: Laba bersih
B43: Spooring
B44: OLI
B45: Jumlah barang keluar

Sheet PURCHASE
C1: Date In | D1: Date Invoice | E1: Distributor | F1: TAX | G1: Invoice | H1: Owned by | I1: Column 7 | J1: Quantity | K1: Price | L1: Price Fixed | M1: Payment | N1: SUM | O1: Due Date | P1: Category | Q1: Brand | R1: =COUNTA(C:C) -> 1485
C2: 45659 | D2: 45659 | E2: TS. SUDIRMAN/NAUFAL | F2: 1 | G2: SLS-SDR-2500012 | H2: IBU | I2: Bridgestone 205/65 15 Turanza | J2: 5 | K2: Rp1.085.500 | L2: 1085500 | M2: Tempo 2 Month | N2: =J2*L2 -> 5427500 | O2: =if(M2="Cash","LUNAS", IF(M2="Tempo 14 Days",D2+14, if(M2="Tempo 30 Days",D2+30, IF(M2="Tempo 2 Month",D2+60,if(M2="Tempo DUNLOP",D2+75,0))))) -> 45719 | P2: =VLOOKUP(I2,DATABASE!C:Q,11,FALSE) -> Tire | Q2: =VLOOKUP(I2,DATABASE!C:Q,4,FALSE) -> Bridgestone
C3: 45659 | D3: 45659 | E3: TS. SUDIRMAN/NAUFAL | F3: 1 | G3: SLS-SDR-2500006 | H3: IBU | I3: Bridgestone 175/13 Duravis | J3: 10 | K3: Rp700.000 | L3: 700000 | M3: Tempo 2 Month | N3: =J3*L3 -> 7000000 | O3: =if(M3="Cash","LUNAS", IF(M3="Tempo 14 Days",D3+14, if(M3="Tempo 30 Days",D3+30, IF(M3="Tempo 2 Month",D3+60,if(M3="Tempo DUNLOP",D3+75,0))))) -> 45719 | P3: =VLOOKUP(I3,DATABASE!C:Q,11,FALSE) -> Tire | Q3: =VLOOKUP(I3,DATABASE!C:Q,4,FALSE) -> Bridgestone
C4: 45659 | D4: 45659 | E4: TS. SUDIRMAN/NAUFAL | F4: 1 | G4: SLS-SDR-2500007 | H4: IBU | I4: Bridgestone 750/16 MRN | J4: 4 | K4: Rp1.570.000 | L4: 1570000 | M4: Tempo 2 Month | N4: =J4*L4 -> 6280000 | O4: =if(M4="Cash","LUNAS", IF(M4="Tempo 14 Days",D4+14, if(M4="Tempo 30 Days",D4+30, IF(M4="Tempo 2 Month",D4+60,if(M4="Tempo DUNLOP",D4+75,0))))) -> 45719 | P4: =VLOOKUP(I4,DATABASE!C:Q,11,FALSE) -> Tire | Q4: =VLOOKUP(I4,DATABASE!C:Q,4,FALSE) -> Bridgestone
C5: 45659 | D5: 45659 | E5: TS. SUDIRMAN/NAUFAL | F5: 1 | G5: SLS-SDR-2500007 | H5: IBU | I5: Bridgestone 750/15 MRD | J5: 10 | K5: Rp1.285.000 | L5: 1285000 | M5: Tempo 2 Month | N5: =J5*L5 -> 12850000 | O5: =if(M5="Cash","LUNAS", IF(M5="Tempo 14 Days",D5+14, if(M5="Tempo 30 Days",D5+30, IF(M5="Tempo 2 Month",D5+60,if(M5="Tempo DUNLOP",D5+75,0))))) -> 45719 | P5: =VLOOKUP(I5,DATABASE!C:Q,11,FALSE) -> Tire | Q5: =VLOOKUP(I5,DATABASE!C:Q,4,FALSE) -> Bridgestone
C6: 45659 | D6: 45659 | E6: TS. SUDIRMAN/NAUFAL | F6: 1 | G6: SLS-SDR-2500014 | H6: IBU | I6: Bridgestone 165/80 13 Ecopia | J6: 6 | K6: Rp577.500 | L6: 577500 | M6: Tempo 2 Month | N6: =J6*L6 -> 3465000 | O6: =if(M6="Cash","LUNAS", IF(M6="Tempo 14 Days",D6+14, if(M6="Tempo 30 Days",D6+30, IF(M6="Tempo 2 Month",D6+60,if(M6="Tempo DUNLOP",D6+75,0))))) -> 45719 | P6: =VLOOKUP(I6,DATABASE!C:Q,11,FALSE) -> Tire | Q6: =VLOOKUP(I6,DATABASE!C:Q,4,FALSE) -> Bridgestone
C7: 45659 | D7: 45659 | E7: TS. SUDIRMAN/NAUFAL | F7: 1 | G7: SLS-SDR-2500014 | H7: IBU | I7: Bridgestone 185/70 14 Ecopia | J7: 10 | K7: Rp676.728 | L7: 676728 | M7: Tempo 2 Month | N7: =J7*L7 -> 6767280 | O7: =if(M7="Cash","LUNAS", IF(M7="Tempo 14 Days",D7+14, if(M7="Tempo 30 Days",D7+30, IF(M7="Tempo 2 Month",D7+60,if(M7="Tempo DUNLOP",D7+75,0))))) -> 45719 | P7: =VLOOKUP(I7,DATABASE!C:Q,11,FALSE) -> Tire | Q7: =VLOOKUP(I7,DATABASE!C:Q,4,FALSE) -> Bridgestone
C8: 45659 | D8: 45659 | E8: TS. SUDIRMAN/NAUFAL | F8: 1 | G8: SLS-SDR-2500014 | H8: IBU | I8: Bridgestone 175/65 14 Ecopia | J8: 10 | K8: Rp655.500 | L8: 655500 | M8: Tempo 2 Month | N8: =J8*L8 -> 6555000 | O8: =if(M8="Cash","LUNAS", IF(M8="Tempo 14 Days",D8+14, if(M8="Tempo 30 Days",D8+30, IF(M8="Tempo 2 Month",D8+60,if(M8="Tempo DUNLOP",D8+75,0))))) -> 45719 | P8: =VLOOKUP(I8,DATABASE!C:Q,11,FALSE) -> Tire | Q8: =VLOOKUP(I8,DATABASE!C:Q,4,FALSE) -> Bridgestone
C9: 45659 | D9: 45659 | E9: TS. SUDIRMAN/NAUFAL | F9: 1 | G9: SLS-SDR-2500014 | H9: IBU | I9: Bridgestone 165/13 Duravis | J9: 8 | K9: Rp670.000 | L9: 670000 | M9: Tempo 2 Month | N9: =J9*L9 -> 5360000 | O9: =if(M9="Cash","LUNAS", IF(M9="Tempo 14 Days",D9+14, if(M9="Tempo 30 Days",D9+30, IF(M9="Tempo 2 Month",D9+60,if(M9="Tempo DUNLOP",D9+75,0))))) -> 45719 | P9: =VLOOKUP(I9,DATABASE!C:Q,11,FALSE) -> Tire | Q9: =VLOOKUP(I9,DATABASE!C:Q,4,FALSE) -> Bridgestone
C10: 45659 | D10: 45659 | E10: TS. SUDIRMAN/NAUFAL | F10: 1 | G10: SLS-SDR-2500014 | H10: IBU | I10: Bridgestone 185/65 15 Ecopia | J10: 6 | K10: Rp765.916 | L10: 765916 | M10: Tempo 2 Month | N10: =J10*L10 -> 4595496 | O10: =if(M10="Cash","LUNAS", IF(M10="Tempo 14 Days",D10+14, if(M10="Tempo 30 Days",D10+30, IF(M10="Tempo 2 Month",D10+60,if(M10="Tempo DUNLOP",D10+75,0))))) -> 45719 | P10: =VLOOKUP(I10,DATABASE!C:Q,11,FALSE) -> Tire | Q10: =VLOOKUP(I10,DATABASE!C:Q,4,FALSE) -> Bridgestone
C11: 45659 | D11: 45659 | E11: TS. SUDIRMAN/NAUFAL | F11: 1 | G11: SLS-SDR-2500007 | H11: IBU | I11: Bridgestone 195/65 15 Ecopia | J11: 6 | K11: Rp810.174 | L11: 810174 | M11: Tempo 2 Month | N11: =J11*L11 -> 4861044 | O11: =if(M11="Cash","LUNAS", IF(M11="Tempo 14 Days",D11+14, if(M11="Tempo 30 Days",D11+30, IF(M11="Tempo 2 Month",D11+60,if(M11="Tempo DUNLOP",D11+75,0))))) -> 45719 | P11: =VLOOKUP(I11,DATABASE!C:Q,11,FALSE) -> Tire | Q11: =VLOOKUP(I11,DATABASE!C:Q,4,FALSE) -> Bridgestone
C12: 45659 | D12: 45659 | E12: TS. SUDIRMAN/NAUFAL | F12: 1 | G12: SLS-SDR-2500014 | H12: IBU | I12: Bridgestone 205/65 15 Ecopia | J12: 2 | K12: Rp902.500 | L12: 902500 | M12: Tempo 2 Month | N12: =J12*L12 -> 1805000 | O12: =if(M12="Cash","LUNAS", IF(M12="Tempo 14 Days",D12+14, if(M12="Tempo 30 Days",D12+30, IF(M12="Tempo 2 Month",D12+60,if(M12="Tempo DUNLOP",D12+75,0))))) -> 45719 | P12: =VLOOKUP(I12,DATABASE!C:Q,11,FALSE) -> Tire | Q12: =VLOOKUP(I12,DATABASE!C:Q,4,FALSE) -> Bridgestone
C13: 45660 | D13: 45660 | E13: TS. SUDIRMAN/NAUFAL | F13: 1 | G13: SLS-SDR-2500054 | H13: IBU | I13: Bridgestone 235/70 15 Dueler | J13: 2 | K13: Rp1.170.500 | L13: 1170500 | M13: Tempo 2 Month | N13: =J13*L13 -> 2341000 | O13: =if(M13="Cash","LUNAS", IF(M13="Tempo 14 Days",D13+14, if(M13="Tempo 30 Days",D13+30, IF(M13="Tempo 2 Month",D13+60,if(M13="Tempo DUNLOP",D13+75,0))))) -> 45720 | P13: =VLOOKUP(I13,DATABASE!C:Q,11,FALSE) -> Tire | Q13: =VLOOKUP(I13,DATABASE!C:Q,4,FALSE) -> Bridgestone
... C62: 45688 | D62: 45688 | E62: KHARISMA MAKMUR ABADI/PAK DADI | F62: 1 | G62: FJ/PST/BDG/25/01/0274 | H62: IBU | I62: Dunlop 175/70 13 TOURING | J62: 6 | K62: Rp470.000 | L62: 470000 | M62: Tempo DUNLOP | N62: =J62*L62 -> 2820000 | O62: =if(M62="Cash","LUNAS", IF(M62="Tempo 14 Days",D62+14, if(M62="Tempo 30 Days",D62+30, IF(M62="Tempo 2 Month",D62+60,if(M62="Tempo DUNLOP",D62+75,0))))) -> 45763 | P62: =VLOOKUP(I62,DATABASE!C:Q,11,FALSE) -> Tire | Q62: =VLOOKUP(I62,DATABASE!C:Q,4,FALSE) -> Dunlop
C63: 45688 | D63: 45688 | E63: KHARISMA MAKMUR ABADI/PAK DADI | F63: 1 | G63: FJ/PST/BDG/25/01/0274 | H63: IBU | I63: Dunlop 165/13 LT5 | J63: 20 | K63: Rp590.000 | L63: =590000 -> 590000 | M63: Tempo DUNLOP | N63: =J63*L63 -> 11800000 | O63: =if(M63="Cash","LUNAS", IF(M63="Tempo 14 Days",D63+14, if(M63="Tempo 30 Days",D63+30, IF(M63="Tempo 2 Month",D63+60,if(M63="Tempo DUNLOP",D63+75,0))))) -> 45763 | P63: =VLOOKUP(I63,DATABASE!C:Q,11,FALSE) -> Tire | Q63: =VLOOKUP(I63,DATABASE!C:Q,4,FALSE) -> Dunlop
C64: 45688 | D64: 45688 | E64: KHARISMA MAKMUR ABADI/PAK DADI | F64: 1 | G64: FJ/PST/BDG/25/01/0274 | H64: IBU | I64: Dunlop 185/14 LT5 | J64: 20 | K64: Rp717.785 | L64: =730000-12215 -> 717785 | M64: Tempo DUNLOP | N64: =J64*L64 -> 14355700 | O64: =if(M64="Cash","LUNAS", IF(M64="Tempo 14 Days",D64+14, if(M64="Tempo 30 Days",D64+30, IF(M64="Tempo 2 Month",D64+60,if(M64="Tempo DUNLOP",D64+75,0))))) -> 45763 | P64: =VLOOKUP(I64,DATABASE!C:Q,11,FALSE) -> Tire | Q64: =VLOOKUP(I64,DATABASE!C:Q,4,FALSE) -> Dunlop
C65: 45688 | D65: 45688 | E65: KHARISMA MAKMUR ABADI/PAK DADI | F65: 1 | G65: FJ/PST/BDG/25/01/0274 | H65: IBU | I65: Dunlop 185/70 14 SP10 | J65: 25 | K65: Rp570.000 | L65: 570000 | M65: Tempo DUNLOP | N65: =J65*L65 -> 14250000 | O65: =if(M65="Cash","LUNAS", IF(M65="Tempo 14 Days",D65+14, if(M65="Tempo 30 Days",D65+30, IF(M65="Tempo 2 Month",D65+60,if(M65="Tempo DUNLOP",D65+75,0))))) -> 45763 | P65: =VLOOKUP(I65,DATABASE!C:Q,11,FALSE) -> Tire | Q65: =VLOOKUP(I65,DATABASE!C:Q,4,FALSE) -> Dunlop
C66: 45688 | D66: 45688 | E66: KHARISMA MAKMUR ABADI/PAK DADI | F66: 1 | G66: FJ/PST/BDG/25/01/0274 | H66: IBU | I66: Dunlop 750/16 12PR | J66: 4 | K66: Rp1.430.000 | L66: 1430000 | M66: Tempo DUNLOP | N66: =J66*L66 -> 5720000 | O66: =if(M66="Cash","LUNAS", IF(M66="Tempo 14 Days",D66+14, if(M66="Tempo 30 Days",D66+30, IF(M66="Tempo 2 Month",D66+60,if(M66="Tempo DUNLOP",D66+75,0))))) -> 45763 | P66: =VLOOKUP(I66,DATABASE!C:Q,11,FALSE) -> Tire | Q66: =VLOOKUP(I66,DATABASE!C:Q,4,FALSE) -> Dunlop
C67: 45689 | D67: 45689 | E67: CV. MEKAR BARU/CI NOVI | F67: 1 | G67: 25001443 | H67: BIAN | I67: GT 185/65 15 ECOTEC | J67: 10 | K67: Rp582.800 | L67: 582800 | M67: Tempo 30 Days | N67: =J67*L67 -> 5828000 | O67: =if(M67="Cash","LUNAS", IF(M67="Tempo 14 Days",D67+14, if(M67="Tempo 30 Days",D67+30, IF(M67="Tempo 2 Month",D67+60,if(M67="Tempo DUNLOP",D67+75,0))))) -> 45719 | P67: =VLOOKUP(I67,DATABASE!C:Q,11,FALSE) -> Tire | Q67: =VLOOKUP(I67,DATABASE!C:Q,4,FALSE) -> GT
C68: 45689 | D68: 45689 | E68: CV. MEKAR BARU/CI NOVI | F68: 1 | G68: 25001443 | H68: BIAN | I68: GT 165/80 13 ECOTEC | J68: 16 | K68: Rp445.800 | L68: 445800 | M68: Tempo 30 Days | N68: =J68*L68 -> 7132800 | O68: =if(M68="Cash","LUNAS", IF(M68="Tempo 14 Days",D68+14, if(M68="Tempo 30 Days",D68+30, IF(M68="Tempo 2 Month",D68+60,if(M68="Tempo DUNLOP",D68+75,0))))) -> 45719 | P68: =VLOOKUP(I68,DATABASE!C:Q,11,FALSE) -> Tire | Q68: =VLOOKUP(I68,DATABASE!C:Q,4,FALSE) -> GT
C69: 45689 | D69: 45689 | E69: PT. INDOTYRE MANDIRI SENTOSA | F69: 1 | G69: FKB250200006 | H69: BIAN | I69: Accelera 235/75 15 at omicron | J69: 1 | K69: Rp893.661 | L69: 893661 | M69: Cash | N69: =J69*L69 -> 893661 | O69: =if(M69="Cash","LUNAS", IF(M69="Tempo 14 Days",D69+14, if(M69="Tempo 30 Days",D69+30, IF(M69="Tempo 2 Month",D69+60,if(M69="Tempo DUNLOP",D69+75,0))))) -> LUNAS | P69: =VLOOKUP(I69,DATABASE!C:Q,11,FALSE) -> Tire | Q69: =VLOOKUP(I69,DATABASE!C:Q,4,FALSE) -> Accelera
C70: 45691 | D70: 45691 | E70: MAJU BERSAMA MOTOR/ANDRI | F70: 0 | G70: R43-030225001 | H70: BIAN | I70: Lower Arm (Sayap) | J70: 10 | K70: 151890 | L70: 151890 | M70: Tempo 30 Days | N70: =J70*L70 -> 1518900 | O70: =if(M70="Cash","LUNAS", IF(M70="Tempo 14 Days",D70+14, if(M70="Tempo 30 Days",D70+30, IF(M70="Tempo 2 Month",D70+60,if(M70="Tempo DUNLOP",D70+75,0))))) -> 45721 | P70: =VLOOKUP(I70,DATABASE!C:Q,11,FALSE) -> COMPLEMENTARY | Q70: =VLOOKUP(I70,DATABASE!C:Q,4,FALSE) -> Lower Arm
C71: 45691 | D71: 45691 | E71: PT. DIRGAPUTRA EKAPRATAMA | F71: 1 | G71: 03-FJ2501000779 | H71: BIAN | I71: BD 13 IBK | J71: 60 | K71: Rp45.310 | L71: 45309.6 | M71: Tempo 2 Month | N71: =J71*L71 -> 2718576 | O71: =if(M71="Cash","LUNAS", IF(M71="Tempo 14 Days",D71+14, if(M71="Tempo 30 Days",D71+30, IF(M71="Tempo 2 Month",D71+60,if(M71="Tempo DUNLOP",D71+75,0))))) -> 45751 | P71: =VLOOKUP(I71,DATABASE!C:Q,11,FALSE) -> Tire | Q71: =VLOOKUP(I71,DATABASE!C:Q,4,FALSE) -> BD
C72: 45691 | D72: 45691 | E72: KHARISMA MAKMUR ABADI/PAK DADI | F72: 1 | G72: FJ/PST/BDG/25/02/0012 | H72: IBU | I72: Dunlop 205/65 15 EC300 | J72: 4 | K72: Rp745.000 | L72: 745000 | M72: Tempo DUNLOP | N72: =J72*L72 -> 2980000 | O72: =if(M72="Cash","LUNAS", IF(M72="Tempo 14 Days",D72+14, if(M72="Tempo 30 Days",D72+30, IF(M72="Tempo 2 Month",D72+60,if(M72="Tempo DUNLOP",D72+75,0))))) -> 45766 | P72: =VLOOKUP(I72,DATABASE!C:Q,11,FALSE) -> Tire | Q72: =VLOOKUP(I72,DATABASE!C:Q,4,FALSE) -> Dunlop
C73: 45692 | D73: 45692 | E73: KHARISMA MAKMUR ABADI/PAK DADI | F73: 1 | G73: FJ/PST/BDG/25/02/0023 | H73: IBU | I73: Dunlop 195/14 LT5 | J73: 2 | K73: Rp870.000 | L73: 870000 | M73: Tempo DUNLOP | N73: =J73*L73 -> 1740000 | O73: =if(M73="Cash","LUNAS", IF(M73="Tempo 14 Days",D73+14, if(M73="Tempo 30 Days",D73+30, IF(M73="Tempo 2 Month",D73+60,if(M73="Tempo DUNLOP",D73+75,0))))) -> 45767 | P73: =VLOOKUP(I73,DATABASE!C:Q,11,FALSE) -> Tire | Q73: =VLOOKUP(I73,DATABASE!C:Q,4,FALSE) -> Dunlop
C74: 45692 | D74: 45692 | E74: KHARISMA MAKMUR ABADI/PAK DADI | F74: 0 | G74: 0 | H74: IBU | I74: Bridgestone 185/80 14 Techno 248 | J74: 5 | K74: Rp550.000 | L74: 550000 | M74: Tempo DUNLOP | N74: =J74*L74 -> 2750000 | O74: =if(M74="Cash","LUNAS", IF(M74="Tempo 14 Days",D74+14, if(M74="Tempo 30 Days",D74+30, IF(M74="Tempo 2 Month",D74+60,if(M74="Tempo DUNLOP",D74+75,0))))) -> 45767 | P74: =VLOOKUP(I74,DATABASE!C:Q,11,FALSE) -> Tire | Q74: =VLOOKUP(I74,DATABASE!C:Q,4,FALSE) -> Bridgestone
C75: 45694 | D75: 45694 | E75: CV. MEKAR BARU/CI NOVI | F75: 1 | G75: 0 | H75: BIAN | I75: GT 195/65 15 ECOTEC | J75: 4 | K75: Rp600.860 | L75: 600860 | M75: Tempo 30 Days | N75: =J75*L75 -> 2403440 | O75: =if(M75="Cash","LUNAS", IF(M75="Tempo 14 Days",D75+14, if(M75="Tempo 30 Days",D75+30, IF(M75="Tempo 2 Month",D75+60,if(M75="Tempo DUNLOP",D75+75,0))))) -> 45724 | P75: =VLOOKUP(I75,DATABASE!C:Q,11,FALSE) -> Tire | Q75: =VLOOKUP(I75,DATABASE!C:Q,4,FALSE) -> GT
C76: 45694 | D76: 45694 | E76: CV. MEKAR BARU/CI NOVI | F76: 1 | G76: 0 | H76: BIAN | I76: GT 205/65 15 CHAMPIRO ECOTEC | J76: 4 | K76: Rp655.960 | L76: 655960 | M76: Tempo 30 Days | N76: =J76*L76 -> 2623840 | O76: =if(M76="Cash","LUNAS", IF(M76="Tempo 14 Days",D76+14, if(M76="Tempo 30 Days",D76+30, IF(M76="Tempo 2 Month",D76+60,if(M76="Tempo DUNLOP",D76+75,0))))) -> 45724 | P76: =VLOOKUP(I76,DATABASE!C:Q,11,FALSE) -> Tire | Q76: =VLOOKUP(I76,DATABASE!C:Q,4,FALSE) -> GT
C77: 45694 | D77: 45694 | E77: CV. MEKAR BARU/CI NOVI | F77: 1 | G77: 0 | H77: BIAN | I77: GT 31X10.50 R15 MT | J77: 1 | K77: Rp1.285.000 | L77: 1285000 | M77: Tempo 30 Days | N77: =J77*L77 -> 1285000 | O77: =if(M77="Cash","LUNAS", IF(M77="Tempo 14 Days",D77+14, if(M77="Tempo 30 Days",D77+30, IF(M77="Tempo 2 Month",D77+60,if(M77="Tempo DUNLOP",D77+75,0))))) -> 45724 | P77: =VLOOKUP(I77,DATABASE!C:Q,11,FALSE) -> Tire | Q77: =VLOOKUP(I77,DATABASE!C:Q,4,FALSE) -> GT
C78: 45694 | D78: 45694 | E78: TS. SUDIRMAN/NAUFAL | F78: 1 | G78: SLS-SDR-2501079 | H78: IBU | I78: Bridgestone 750/16 MRN | J78: 10 | K78: Rp1.585.000 | L78: 1585000 | M78: Tempo 2 Month | N78: =J78*L78 -> 15850000 | O78: =if(M78="Cash","LUNAS", IF(M78="Tempo 14 Days",D78+14, if(M78="Tempo 30 Days",D78+30, IF(M78="Tempo 2 Month",D78+60,if(M78="Tempo DUNLOP",D78+75,0))))) -> 45754 | P78: =VLOOKUP(I78,DATABASE!C:Q,11,FALSE) -> Tire | Q78: =VLOOKUP(I78,DATABASE!C:Q,4,FALSE) -> Bridgestone
C79: 45694 | D79: 45694 | E79: TS. SUDIRMAN/NAUFAL | F79: 1 | G79: SLS-SDR-2501079 | H79: IBU | I79: Bridgestone 750/15 MRD | J79: 10 | K79: Rp1.285.000 | L79: 1285000 | M79: Tempo 2 Month | N79: =J79*L79 -> 12850000 | O79: =if(M79="Cash","LUNAS", IF(M79="Tempo 14 Days",D79+14, if(M79="Tempo 30 Days",D79+30, IF(M79="Tempo 2 Month",D79+60,if(M79="Tempo DUNLOP",D79+75,0))))) -> 45754 | P79: =VLOOKUP(I79,DATABASE!C:Q,11,FALSE) -> Tire | Q79: =VLOOKUP(I79,DATABASE!C:Q,4,FALSE) -> Bridgestone
C80: 45694 | D80: 45694 | E80: TS. SUDIRMAN/NAUFAL | F80: 1 | G80: SLS-SDR-2501079 | H80: IBU | I80: Bridgestone 175/13 Duravis | J80: 10 | K80: Rp700.000 | L80: 700000 | M80: Tempo 2 Month | N80: =J80*L80 -> 7000000 | O80: =if(M80="Cash","LUNAS", IF(M80="Tempo 14 Days",D80+14, if(M80="Tempo 30 Days",D80+30, IF(M80="Tempo 2 Month",D80+60,if(M80="Tempo DUNLOP",D80+75,0))))) -> 45754 | P80: =VLOOKUP(I80,DATABASE!C:Q,11,FALSE) -> Tire | Q80: =VLOOKUP(I80,DATABASE!C:Q,4,FALSE) -> Bridgestone
C81: 45694 | D81: 45694 | E81: TS. SUDIRMAN/NAUFAL | F81: 1 | G81: SLS-SDR-2501079 | H81: IBU | I81: Bridgestone 185/14 Duravis | J81: 10 | K81: Rp810.000 | L81: 810000 | M81: Tempo 2 Month | N81: =J81*L81 -> 8100000 | O81: =if(M81="Cash","LUNAS", IF(M81="Tempo 14 Days",D81+14, if(M81="Tempo 30 Days",D81+30, IF(M81="Tempo 2 Month",D81+60,if(M81="Tempo DUNLOP",D81+75,0))))) -> 45754 | P81: =VLOOKUP(I81,DATABASE!C:Q,11,FALSE) -> Tire | Q81: =VLOOKUP(I81,DATABASE!C:Q,4,FALSE) -> Bridgestone
C82: 45700 | D82: 45700 | E82: TS. SUDIRMAN/NAUFAL | F82: 1 | G82: SLS-SDR-2501337 | H82: IBU | I82: Bridgestone 205/65 15 Ecopia | J82: 1 | K82: Rp902.500 | L82: 902500 | M82: Tempo 2 Month | N82: =J82*L82 -> 902500 | O82: =if(M82="Cash","LUNAS", IF(M82="Tempo 14 Days",D82+14, if(M82="Tempo 30 Days",D82+30, IF(M82="Tempo 2 Month",D82+60,if(M82="Tempo DUNLOP",D82+75,0))))) -> 45760 | P82: =VLOOKUP(I82,DATABASE!C:Q,11,FALSE) -> Tire | Q82: =VLOOKUP(I82,DATABASE!C:Q,4,FALSE) -> Bridgestone
... C115: 45712 | D115: 45712 | E115: TS. SUDIRMAN/NAUFAL | F115: 1 | G115: SLS-SDR-2501721 | H115: IBU | I115: BD 900*20 Bridgestone | J115: 1 | K115: Rp510.000 | L115: 510000 | M115: Tempo 2 Month | N115: =J115*L115 -> 510000 | O115: =if(M115="Cash","LUNAS", IF(M115="Tempo 14 Days",D115+14, if(M115="Tempo 30 Days",D115+30, IF(M115="Tempo 2 Month",D115+60,if(M115="Tempo DUNLOP",D115+75,0))))) -> 45772 | P115: =VLOOKUP(I115,DATABASE!C:Q,11,FALSE) -> Tire | Q115: =VLOOKUP(I115,DATABASE!C:Q,4,FALSE) -> BD
C116: 45713 | D116: 45713 | E116: KHARISMA MAKMUR ABADI/PAK DADI | F116: 1 | G116: FJ/PST/BDG/25/02/0243 | H116: IBU | I116: Dunlop 175/13 LT5 | J116: 4 | K116: 613000 | L116: 613000 | M116: Tempo DUNLOP | N116: =J116*L116 -> 2452000 | O116: =if(M116="Cash","LUNAS", IF(M116="Tempo 14 Days",D116+14, if(M116="Tempo 30 Days",D116+30, IF(M116="Tempo 2 Month",D116+60,if(M116="Tempo DUNLOP",D116+75,0))))) -> 45788 | P116: =VLOOKUP(I116,DATABASE!C:Q,11,FALSE) -> Tire | Q116: =VLOOKUP(I116,DATABASE!C:Q,4,FALSE) -> Dunlop
C117: 45714 | D117: 45714 | E117: KHARISMA MAKMUR ABADI/PAK DADI | F117: 1 | G117: FJ/PST/BDG/25/02/0255 | H117: IBU | I117: Dunlop 195/60 16 EC300 | J117: 4 | K117: Rp794.000 | L117: 794000 | M117: Tempo DUNLOP | N117: =J117*L117 -> 3176000 | O117: =if(M117="Cash","LUNAS", IF(M117="Tempo 14 Days",D117+14, if(M117="Tempo 30 Days",D117+30, IF(M117="Tempo 2 Month",D117+60,if(M117="Tempo DUNLOP",D117+75,0))))) -> 45789 | P117: =VLOOKUP(I117,DATABASE!C:Q,11,FALSE) -> Tire | Q117: =VLOOKUP(I117,DATABASE!C:Q,4,FALSE) -> Dunlop
C118: 45714 | D118: 45714 | E118: KHARISMA MAKMUR ABADI/PAK DADI | F118: 1 | G118: FJ/PST/BDG/25/02/0255 | H118: IBU | I118: Dunlop 175/65 14 EC300 | J118: 10 | K118: Rp519.500 | L118: 519500 | M118: Tempo DUNLOP | N118: =J118*L118 -> 5195000 | O118: =if(M118="Cash","LUNAS", IF(M118="Tempo 14 Days",D118+14, if(M118="Tempo 30 Days",D118+30, IF(M118="Tempo 2 Month",D118+60,if(M118="Tempo DUNLOP",D118+75,0))))) -> 45789 | P118: =VLOOKUP(I118,DATABASE!C:Q,11,FALSE) -> Tire | Q118: =VLOOKUP(I118,DATABASE!C:Q,4,FALSE) -> Dunlop
C119: 45714 | D119: 45714 | E119: KHARISMA MAKMUR ABADI/PAK DADI | F119: 1 | G119: FJ/PST/BDG/25/02/0255 | H119: IBU | I119: Dunlop 205/55 17 ENASEV | J119: 3 | K119: Rp985.000 | L119: 985000 | M119: Tempo DUNLOP | N119: =J119*L119 -> 2955000 | O119: =if(M119="Cash","LUNAS", IF(M119="Tempo 14 Days",D119+14, if(M119="Tempo 30 Days",D119+30, IF(M119="Tempo 2 Month",D119+60,if(M119="Tempo DUNLOP",D119+75,0))))) -> 45789 | P119: =VLOOKUP(I119,DATABASE!C:Q,11,FALSE) -> Tire | Q119: =VLOOKUP(I119,DATABASE!C:Q,4,FALSE) -> Dunlop
C120: 45714 | D120: 45714 | E120: KHARISMA MAKMUR ABADI/PAK DADI | F120: 1 | G120: FJ/PST/BDG/25/02/0255 | H120: IBU | I120: Dunlop 215/45 17 DIREZA | J120: 2 | K120: Rp785.000 | L120: 785000 | M120: Tempo DUNLOP | N120: =J120*L120 -> 1570000 | O120: =if(M120="Cash","LUNAS", IF(M120="Tempo 14 Days",D120+14, if(M120="Tempo 30 Days",D120+30, IF(M120="Tempo 2 Month",D120+60,if(M120="Tempo DUNLOP",D120+75,0))))) -> 45789 | P120: =VLOOKUP(I120,DATABASE!C:Q,11,FALSE) -> Tire | Q120: =VLOOKUP(I120,DATABASE!C:Q,4,FALSE) -> Dunlop
C121: 45714 | D121: 45714 | E121: KHARISMA MAKMUR ABADI/PAK DADI | F121: 1 | G121: FJ/PST/BDG/25/02/0255 | H121: IBU | I121: Dunlop 205/45 17 DIREZA | J121: 1 | K121: Rp765.000 | L121: 765000 | M121: Tempo DUNLOP | N121: =J121*L121 -> 765000 | O121: =if(M121="Cash","LUNAS", IF(M121="Tempo 14 Days",D121+14, if(M121="Tempo 30 Days",D121+30, IF(M121="Tempo 2 Month",D121+60,if(M121="Tempo DUNLOP",D121+75,0))))) -> 45789 | P121: =VLOOKUP(I121,DATABASE!C:Q,11,FALSE) -> Tire | Q121: =VLOOKUP(I121,DATABASE!C:Q,4,FALSE) -> Dunlop
C122: 45714 | D122: 45714 | E122: KHARISMA MAKMUR ABADI/PAK DADI | F122: 1 | G122: FJ/PST/BDG/25/02/0255 | H122: IBU | I122: Dunlop 215/60 17 EC300 | J122: 2 | K122: Rp865.500 | L122: 865500 | M122: Tempo DUNLOP | N122: =J122*L122 -> 1731000 | O122: =if(M122="Cash","LUNAS", IF(M122="Tempo 14 Days",D122+14, if(M122="Tempo 30 Days",D122+30, IF(M122="Tempo 2 Month",D122+60,if(M122="Tempo DUNLOP",D122+75,0))))) -> 45789 | P122: =VLOOKUP(I122,DATABASE!C:Q,11,FALSE) -> Tire | Q122: =VLOOKUP(I122,DATABASE!C:Q,4,FALSE) -> Dunlop
C123: 45714 | D123: 45714 | E123: KHARISMA MAKMUR ABADI/PAK DADI | F123: 1 | G123: FJ/PST/BDG/25/02/0255 | H123: IBU | I123: Dunlop 175/13 LT5 | J123: 50 | K123: Rp613.000 | L123: 613000 | M123: Tempo DUNLOP | N123: =J123*L123 -> 30650000 | O123: =if(M123="Cash","LUNAS", IF(M123="Tempo 14 Days",D123+14, if(M123="Tempo 30 Days",D123+30, IF(M123="Tempo 2 Month",D123+60,if(M123="Tempo DUNLOP",D123+75,0))))) -> 45789 | P123: =VLOOKUP(I123,DATABASE!C:Q,11,FALSE) -> Tire | Q123: =VLOOKUP(I123,DATABASE!C:Q,4,FALSE) -> Dunlop
C124: 45715 | D124: 45715 | E124: KHARISMA MAKMUR ABADI/PAK DADI | F124: 1 | G124: FJ/PST/BDG/25/02/0259 | H124: IBU | I124: Dunlop 215/60 17 EC300 | J124: 2 | K124: Rp865.500 | L124: 865500 | M124: Tempo DUNLOP | N124: =J124*L124 -> 1731000 | O124: =if(M124="Cash","LUNAS", IF(M124="Tempo 14 Days",D124+14, if(M124="Tempo 30 Days",D124+30, IF(M124="Tempo 2 Month",D124+60,if(M124="Tempo DUNLOP",D124+75,0))))) -> 45790 | P124: =VLOOKUP(I124,DATABASE!C:Q,11,FALSE) -> Tire | Q124: =VLOOKUP(I124,DATABASE!C:Q,4,FALSE) -> Dunlop
C125: 45717 | D125: 45717 | E125: TS. SUDIRMAN/NAUFAL | F125: 1 | G125: SLS-SDR-2501959 | H125: IBU | I125: Bridgestone 205/65 16 Ecopia | J125: 4 | K125: Rp945.190 | L125: 945190.33 | M125: Tempo 2 Month | N125: =J125*L125 -> 3780761.3 | O125: =if(M125="Cash","LUNAS", IF(M125="Tempo 14 Days",D125+14, if(M125="Tempo 30 Days",D125+30, IF(M125="Tempo 2 Month",D125+60,if(M125="Tempo DUNLOP",D125+75,0))))) -> 45777 | P125: =VLOOKUP(I125,DATABASE!C:Q,11,FALSE) -> Tire | Q125: =VLOOKUP(I125,DATABASE!C:Q,4,FALSE) -> Bridgestone
C126: 45719 | D126: 45719 | E126: SAMUDERA GEMILANG/PAK KEMAN | F126: 1 | G126: FJ/HO/03/25/00028 | H126: BIAN | I126: GT 175/65 14 CHAMPIRO ECOTEC | J126: 15 | K126: Rp475.650 | L126: 475650 | M126: Tempo 30 Days | N126: =J126*L126 -> 7134750 | O126: =if(M126="Cash","LUNAS", IF(M126="Tempo 14 Days",D126+14, if(M126="Tempo 30 Days",D126+30, IF(M126="Tempo 2 Month",D126+60,if(M126="Tempo DUNLOP",D126+75,0))))) -> 45749 | P126: =VLOOKUP(I126,DATABASE!C:Q,11,FALSE) -> Tire | Q126: =VLOOKUP(I126,DATABASE!C:Q,4,FALSE) -> GT
C127: 45719 | D127: 45719 | E127: SAMUDERA GEMILANG/PAK KEMAN | F127: 1 | G127: FJ/HO/03/25/00028 | H127: BIAN | I127: GT 185/65 15 ECOTEC | J127: 14 | K127: Rp592.200 | L127: 592200 | M127: Tempo 30 Days | N127: =J127*L127 -> 8290800 | O127: =if(M127="Cash","LUNAS", IF(M127="Tempo 14 Days",D127+14, if(M127="Tempo 30 Days",D127+30, IF(M127="Tempo 2 Month",D127+60,if(M127="Tempo DUNLOP",D127+75,0))))) -> 45749 | P127: =VLOOKUP(I127,DATABASE!C:Q,11,FALSE) -> Tire | Q127: =VLOOKUP(I127,DATABASE!C:Q,4,FALSE) -> GT
C128: 45719 | D128: 45719 | E128: SAMUDERA GEMILANG/PAK KEMAN | F128: 1 | G128: FJ/HO/03/25/00028 | H128: BIAN | I128: GT 195/65 15 ECOTEC | J128: 10 | K128: Rp609.800 | L128: 609800 | M128: Tempo 30 Days | N128: =J128*L128 -> 6098000 | O128: =if(M128="Cash","LUNAS", IF(M128="Tempo 14 Days",D128+14, if(M128="Tempo 30 Days",D128+30, IF(M128="Tempo 2 Month",D128+60,if(M128="Tempo DUNLOP",D128+75,0))))) -> 45749 | P128: =VLOOKUP(I128,DATABASE!C:Q,11,FALSE) -> Tire | Q128: =VLOOKUP(I128,DATABASE!C:Q,4,FALSE) -> GT
... C174: 45729 | D174: 45729 | E174: KHARISMA MAKMUR ABADI/PAK DADI | F174: 1 | G174: FJ/PST/BDG/2503/0126 | H174: IBU | I174: DUNLOP 225/60 18 SPORTMAXX | J174: 2 | K174: Rp1.305.000 | L174: 1305000 | M174: Tempo DUNLOP | N174: =J174*L174 -> 2610000 | O174: =if(M174="Cash","LUNAS", IF(M174="Tempo 14 Days",D174+14, if(M174="Tempo 30 Days",D174+30, IF(M174="Tempo 2 Month",D174+60,if(M174="Tempo DUNLOP",D174+75,0))))) -> 45804 | P174: =VLOOKUP(I174,DATABASE!C:Q,11,FALSE) -> Tire | Q174: =VLOOKUP(I174,DATABASE!C:Q,4,FALSE) -> DUNLOP
C175: 45729 | D175: 45729 | E175: KHARISMA MAKMUR ABADI/PAK DADI | F175: 1 | G175: FJ/PST/BDG/2503/0126 | H175: IBU | I175: Dunlop 215/55 17 SPORTMAXX | J175: 5 | K175: 1305000 | L175: 1305000 | M175: Tempo DUNLOP | N175: =J175*L175 -> 6525000 | O175: =if(M175="Cash","LUNAS", IF(M175="Tempo 14 Days",D175+14, if(M175="Tempo 30 Days",D175+30, IF(M175="Tempo 2 Month",D175+60,if(M175="Tempo DUNLOP",D175+75,0))))) -> 45804 | P175: =VLOOKUP(I175,DATABASE!C:Q,11,FALSE) -> Tire | Q175: =VLOOKUP(I175,DATABASE!C:Q,4,FALSE) -> Dunlop
C176: 45729 | D176: 45729 | E176: KHARISMA MAKMUR ABADI/PAK DADI | F176: 1 | G176: FJ/PST/BDG/2503/0126 | H176: IBU | I176: Dunlop 215/65 16 ST20 | J176: 3 | K176: Rp935.000 | L176: 935000 | M176: Tempo DUNLOP | N176: =J176*L176 -> 2805000 | O176: =if(M176="Cash","LUNAS", IF(M176="Tempo 14 Days",D176+14, if(M176="Tempo 30 Days",D176+30, IF(M176="Tempo 2 Month",D176+60,if(M176="Tempo DUNLOP",D176+75,0))))) -> 45804 | P176: =VLOOKUP(I176,DATABASE!C:Q,11,FALSE) -> Tire | Q176: =VLOOKUP(I176,DATABASE!C:Q,4,FALSE) -> Dunlop
C177: 45729 | D177: 45729 | E177: KHARISMA MAKMUR ABADI/PAK DADI | F177: 1 | G177: FJ/PST/BDG/2503/0126 | H177: IBU | I177: Dunlop 235/60 16 ST20 | J177: 4 | K177: Rp1.170.000 | L177: 1170000 | M177: Tempo DUNLOP | N177: =J177*L177 -> 4680000 | O177: =if(M177="Cash","LUNAS", IF(M177="Tempo 14 Days",D177+14, if(M177="Tempo 30 Days",D177+30, IF(M177="Tempo 2 Month",D177+60,if(M177="Tempo DUNLOP",D177+75,0))))) -> 45804 | P177: =VLOOKUP(I177,DATABASE!C:Q,11,FALSE) -> Tire | Q177: =VLOOKUP(I177,DATABASE!C:Q,4,FALSE) -> Dunlop
C178: 45729 | D178: 45729 | E178: KHARISMA MAKMUR ABADI/PAK DADI | F178: 1 | G178: FJ/PST/BDG/2503/0126 | H178: IBU | I178: Dunlop 185/70 14 SP10 | J178: 10 | K178: Rp557.000 | L178: 557000 | M178: Tempo DUNLOP | N178: =J178*L178 -> 5570000 | O178: =if(M178="Cash","LUNAS", IF(M178="Tempo 14 Days",D178+14, if(M178="Tempo 30 Days",D178+30, IF(M178="Tempo 2 Month",D178+60,if(M178="Tempo DUNLOP",D178+75,0))))) -> 45804 | P178: =VLOOKUP(I178,DATABASE!C:Q,11,FALSE) -> Tire | Q178: =VLOOKUP(I178,DATABASE!C:Q,4,FALSE) -> Dunlop
C179: 45730 | D179: 45730 | E179: CV. MEKAR BARU/CI NOVI | F179: 1 | G179: 25003486 | H179: BIAN | I179: GT 205/45 17 GTX PRO | J179: 4 | K179: Rp700.600 | L179: 700600 | M179: Tempo 30 Days | N179: =J179*L179 -> 2802400 | O179: =if(M179="Cash","LUNAS", IF(M179="Tempo 14 Days",D179+14, if(M179="Tempo 30 Days",D179+30, IF(M179="Tempo 2 Month",D179+60,if(M179="Tempo DUNLOP",D179+75,0))))) -> 45760 | P179: =VLOOKUP(I179,DATABASE!C:Q,11,FALSE) -> Tire | Q179: =VLOOKUP(I179,DATABASE!C:Q,4,FALSE) -> GT
C180: 45730 | D180: 45730 | E180: KHARISMA MAKMUR ABADI/PAK DADI | F180: 1 | G180: FJ/PST/BDG/2503/0134 | H180: IBU | I180: Dunlop 205/65 15 EC300 | J180: 11 | K180: Rp760.000 | L180: 760000 | M180: Tempo DUNLOP | N180: =J180*L180 -> 8360000 | O180: =if(M180="Cash","LUNAS", IF(M180="Tempo 14 Days",D180+14, if(M180="Tempo 30 Days",D180+30, IF(M180="Tempo 2 Month",D180+60,if(M180="Tempo DUNLOP",D180+75,0))))) -> 45805 | P180: =VLOOKUP(I180,DATABASE!C:Q,11,FALSE) -> Tire | Q180: =VLOOKUP(I180,DATABASE!C:Q,4,FALSE) -> Dunlop
C181: 45730 | D181: 45730 | E181: KHARISMA MAKMUR ABADI/PAK DADI | F181: 1 | G181: FJ/PST/BDG/2503/0134 | H181: IBU | I181: Dunlop 215/60 17 EC300 | J181: 6 | K181: Rp870.000 | L181: 870000 | M181: Tempo DUNLOP | N181: =J181*L181 -> 5220000 | O181: =if(M181="Cash","LUNAS", IF(M181="Tempo 14 Days",D181+14, if(M181="Tempo 30 Days",D181+30, IF(M181="Tempo 2 Month",D181+60,if(M181="Tempo DUNLOP",D181+75,0))))) -> 45805 | P181: =VLOOKUP(I181,DATABASE!C:Q,11,FALSE) -> Tire | Q181: =VLOOKUP(I181,DATABASE!C:Q,4,FALSE) -> Dunlop
C182: 45730 | D182: 45730 | E182: KHARISMA MAKMUR ABADI/PAK DADI | F182: 1 | G182: FJ/PST/BDG/2503/0134 | H182: IBU | I182: Dunlop 185/70 14 ENASEV | J182: 10 | K182: Rp562.000 | L182: 562000 | M182: Tempo DUNLOP | N182: =J182*L182 -> 5620000 | O182: =if(M182="Cash","LUNAS", IF(M182="Tempo 14 Days",D182+14, if(M182="Tempo 30 Days",D182+30, IF(M182="Tempo 2 Month",D182+60,if(M182="Tempo DUNLOP",D182+75,0))))) -> 45805 | P182: =VLOOKUP(I182,DATABASE!C:Q,11,FALSE) -> Tire | Q182: =VLOOKUP(I182,DATABASE!C:Q,4,FALSE) -> Dunlop
C183: 45730 | D183: 45730 | E183: KHARISMA MAKMUR ABADI/PAK DADI | F183: 1 | G183: FJ/PST/BDG/2503/0134 | H183: IBU | I183: Dunlop 195/60 16 EC300 | J183: 6 | K183: Rp810.000 | L183: 810000 | M183: Tempo DUNLOP | N183: =J183*L183 -> 4860000 | O183: =if(M183="Cash","LUNAS", IF(M183="Tempo 14 Days",D183+14, if(M183="Tempo 30 Days",D183+30, IF(M183="Tempo 2 Month",D183+60,if(M183="Tempo DUNLOP",D183+75,0))))) -> 45805 | P183: =VLOOKUP(I183,DATABASE!C:Q,11,FALSE) -> Tire | Q183: =VLOOKUP(I183,DATABASE!C:Q,4,FALSE) -> Dunlop
C184: 45730 | D184: 45730 | E184: KHARISMA MAKMUR ABADI/PAK DADI | F184: 1 | G184: FJ/PST/BDG/2503/0134 | H184: IBU | I184: Dunlop 175/65 14 EC300 | J184: 20 | K184: Rp530.000 | L184: 530000 | M184: Tempo DUNLOP | N184: =J184*L184 -> 10600000 | O184: =if(M184="Cash","LUNAS", IF(M184="Tempo 14 Days",D184+14, if(M184="Tempo 30 Days",D184+30, IF(M184="Tempo 2 Month",D184+60,if(M184="Tempo DUNLOP",D184+75,0))))) -> 45805 | P184: =VLOOKUP(I184,DATABASE!C:Q,11,FALSE) -> Tire | Q184: =VLOOKUP(I184,DATABASE!C:Q,4,FALSE) -> Dunlop
C185: 45730 | D185: 45730 | E185: KHARISMA MAKMUR ABADI/PAK DADI | F185: 1 | G185: FJ/PST/BDG/2503/0134 | H185: IBU | I185: Dunlop 205/55 17 ENASEV | J185: 3 | K185: Rp1.000.000 | L185: 1000000 | M185: Tempo DUNLOP | N185: =J185*L185 -> 3000000 | O185: =if(M185="Cash","LUNAS", IF(M185="Tempo 14 Days",D185+14, if(M185="Tempo 30 Days",D185+30, IF(M185="Tempo 2 Month",D185+60,if(M185="Tempo DUNLOP",D185+75,0))))) -> 45805 | P185: =VLOOKUP(I185,DATABASE!C:Q,11,FALSE) -> Tire | Q185: =VLOOKUP(I185,DATABASE!C:Q,4,FALSE) -> Dunlop
C186: 45730 | D186: 45730 | E186: KHARISMA MAKMUR ABADI/PAK DADI | F186: 1 | G186: FJ/PST/BDG/2503/0134 | H186: IBU | I186: Dunlop 195/65 15 EC300 | J186: 2 | K186: Rp740.000 | L186: 740000 | M186: Tempo DUNLOP | N186: =J186*L186 -> 1480000 | O186: =if(M186="Cash","LUNAS", IF(M186="Tempo 14 Days",D186+14, if(M186="Tempo 30 Days",D186+30, IF(M186="Tempo 2 Month",D186+60,if(M186="Tempo DUNLOP",D186+75,0))))) -> 45805 | P186: =VLOOKUP(I186,DATABASE!C:Q,11,FALSE) -> Tire | Q186: =VLOOKUP(I186,DATABASE!C:Q,4,FALSE) -> Dunlop
C187: 45730 | D187: 45730 | E187: KHARISMA MAKMUR ABADI/PAK DADI | F187: 1 | G187: FJ/PST/BDG/2503/0134 | H187: IBU | I187: Dunlop 185/55 16 EC300 | J187: 3 | K187: Rp810.000 | L187: 810000 | M187: Tempo DUNLOP | N187: =J187*L187 -> 2430000 | O187: =if(M187="Cash","LUNAS", IF(M187="Tempo 14 Days",D187+14, if(M187="Tempo 30 Days",D187+30, IF(M187="Tempo 2 Month",D187+60,if(M187="Tempo DUNLOP",D187+75,0))))) -> 45805 | P187: =VLOOKUP(I187,DATABASE!C:Q,11,FALSE) -> Tire | Q187: =VLOOKUP(I187,DATABASE!C:Q,4,FALSE) -> Dunlop
... C198: 45733 | D198: 45733 | E198: TS. SUDIRMAN/NAUFAL | F198: 1 | G198: SLS-SDR-25002558 | H198: IBU | I198: Bridgestone 175/13 Duravis | J198: 8 | K198: Rp700.000 | L198: 700000 | M198: Tempo 2 Month | N198: =J198*L198 -> 5600000 | O198: =if(M198="Cash","LUNAS", IF(M198="Tempo 14 Days",D198+14, if(M198="Tempo 30 Days",D198+30, IF(M198="Tempo 2 Month",D198+60,if(M198="Tempo DUNLOP",D198+75,0))))) -> 45793 | P198: =VLOOKUP(I198,DATABASE!C:Q,11,FALSE) -> Tire | Q198: =VLOOKUP(I198,DATABASE!C:Q,4,FALSE) -> Bridgestone
C199: 45733 | D199: 45733 | E199: TS. SUDIRMAN/NAUFAL | F199: 1 | G199: SLS-SDR-25002558 | H199: IBU | I199: Bridgestone 185/14 Duravis | J199: 10 | K199: Rp810.000 | L199: 810000 | M199: Tempo 2 Month | N199: =J199*L199 -> 8100000 | O199: =if(M199="Cash","LUNAS", IF(M199="Tempo 14 Days",D199+14, if(M199="Tempo 30 Days",D199+30, IF(M199="Tempo 2 Month",D199+60,if(M199="Tempo DUNLOP",D199+75,0))))) -> 45793 | P199: =VLOOKUP(I199,DATABASE!C:Q,11,FALSE) -> Tire | Q199: =VLOOKUP(I199,DATABASE!C:Q,4,FALSE) -> Bridgestone | Y199: 45681 | AA199: =Y199+30 -> 45711
C200: 45733 | D200: 45733 | E200: TS. SUDIRMAN/NAUFAL | F200: 1 | G200: SLS-SDR-25002558 | H200: IBU | I200: Bridgestone 195/65 15 Ecopia | J200: 9 | K200: Rp810.342 | L200: 810342.44 | M200: Tempo 2 Month | N200: =J200*L200 -> 7293082 | O200: =if(M200="Cash","LUNAS", IF(M200="Tempo 14 Days",D200+14, if(M200="Tempo 30 Days",D200+30, IF(M200="Tempo 2 Month",D200+60,if(M200="Tempo DUNLOP",D200+75,0))))) -> 45793 | P200: =VLOOKUP(I200,DATABASE!C:Q,11,FALSE) -> Tire | Q200: =VLOOKUP(I200,DATABASE!C:Q,4,FALSE) -> Bridgestone | Y200: 45700 | AA200: =Y200+30 -> 45730
C201: 45733 | D201: 45733 | E201: TS. SUDIRMAN/NAUFAL | F201: 1 | G201: SLS-SDR-25002560 | H201: IBU | I201: Bridgestone 185/60 15 TECHNO | J201: 4 | K201: Rp671.104 | L201: 671104 | M201: Tempo 2 Month | N201: =J201*L201 -> 2684416 | O201: =if(M201="Cash","LUNAS", IF(M201="Tempo 14 Days",D201+14, if(M201="Tempo 30 Days",D201+30, IF(M201="Tempo 2 Month",D201+60,if(M201="Tempo DUNLOP",D201+75,0))))) -> 45793 | P201: =VLOOKUP(I201,DATABASE!C:Q,11,FALSE) -> Tire | Q201: =VLOOKUP(I201,DATABASE!C:Q,4,FALSE) -> Bridgestone | Y201: 45712 | AA201: =Y201+30 -> 45742
C202: 45733 | D202: 45733 | E202: TS. SUDIRMAN/NAUFAL | F202: 1 | G202: SLS-SDR-25002560 | H202: IBU | I202: Bridgestone 185/55 15 Techno | J202: 6 | K202: Rp680.512 | L202: 680512 | M202: Tempo 2 Month | N202: =J202*L202 -> 4083072 | O202: =if(M202="Cash","LUNAS", IF(M202="Tempo 14 Days",D202+14, if(M202="Tempo 30 Days",D202+30, IF(M202="Tempo 2 Month",D202+60,if(M202="Tempo DUNLOP",D202+75,0))))) -> 45793 | P202: =VLOOKUP(I202,DATABASE!C:Q,11,FALSE) -> Tire | Q202: =VLOOKUP(I202,DATABASE!C:Q,4,FALSE) -> Bridgestone | Y202: 45719 | AA202: =Y202+30 -> 45749
C203: 45733 | D203: 45733 | E203: TS. SUDIRMAN/NAUFAL | F203: 1 | G203: SLS-SDR-25002560 | H203: IBU | I203: Bridgestone 195/65 15 Ecopia | J203: 1 | K203: Rp810.342 | L203: 810342.44 | M203: Tempo 2 Month | N203: =J203*L203 -> 810342.44 | O203: =if(M203="Cash","LUNAS", IF(M203="Tempo 14 Days",D203+14, if(M203="Tempo 30 Days",D203+30, IF(M203="Tempo 2 Month",D203+60,if(M203="Tempo DUNLOP",D203+75,0))))) -> 45793 | P203: =VLOOKUP(I203,DATABASE!C:Q,11,FALSE) -> Tire | Q203: =VLOOKUP(I203,DATABASE!C:Q,4,FALSE) -> Bridgestone | Y203: 45719 | AA203: =Y203+30 -> 45749
C204: 45733 | D204: 45733 | E204: TS. SUDIRMAN/NAUFAL | F204: 1 | G204: SLS-SDR-25002560 | H204: IBU | I204: Bridgestone 185/70 14 Ecopia | J204: 15 | K204: Rp564.181 | L204: 564181 | M204: Tempo 2 Month | N204: =J204*L204 -> 8462715 | O204: =if(M204="Cash","LUNAS", IF(M204="Tempo 14 Days",D204+14, if(M204="Tempo 30 Days",D204+30, IF(M204="Tempo 2 Month",D204+60,if(M204="Tempo DUNLOP",D204+75,0))))) -> 45793 | P204: =VLOOKUP(I204,DATABASE!C:Q,11,FALSE) -> Tire | Q204: =VLOOKUP(I204,DATABASE!C:Q,4,FALSE) -> Bridgestone | Y204: 45761 | AA204: =Y204+30 -> 45791
C205: 45734 | D205: 45734 | E205: PT. Astra Otoparts Tbk | F205: 1 | G205: 4009773492 | H205: BIAN | I205: BD 15 Aspira P. Pendek | J205: 10 | K205: Rp111.800 | L205: 111800 | M205: Tempo 2 Month | N205: =J205*L205 -> 1118000 | O205: =if(M205="Cash","LUNAS", IF(M205="Tempo 14 Days",D205+14, if(M205="Tempo 30 Days",D205+30, IF(M205="Tempo 2 Month",D205+60,if(M205="Tempo DUNLOP",D205+75,0))))) -> 45794 | P205: =VLOOKUP(I205,DATABASE!C:Q,11,FALSE) -> Tire | Q205: =VLOOKUP(I205,DATABASE!C:Q,4,FALSE) -> BD | Y205: 45779 | AA205: =Y205+30 -> 45809
C206: 45735 | D206: 45735 | E206: CV. MEKAR BARU/CI NOVI | F206: 1 | G206: 25003737 | H206: BIAN | I206: GT 700/12 12PR GRIP | J206: 1 | K206: Rp1.003.000 | L206: 1003000 | M206: Tempo 30 Days | N206: =J206*L206 -> 1003000 | O206: =if(M206="Cash","LUNAS", IF(M206="Tempo 14 Days",D206+14, if(M206="Tempo 30 Days",D206+30, IF(M206="Tempo 2 Month",D206+60,if(M206="Tempo DUNLOP",D206+75,0))))) -> 45765 | P206: =VLOOKUP(I206,DATABASE!C:Q,11,FALSE) -> Tire | Q206: =VLOOKUP(I206,DATABASE!C:Q,4,FALSE) -> GT | Y206: 45779 | AA206: =Y206+30 -> 45809
C207: 45735 | D207: 45735 | E207: CV. MEKAR BARU/CI NOVI | F207: 1 | G207: 25003737 | H207: BIAN | I207: BD 700/12 Powerclip GT | J207: 1 | K207: Rp157.500 | L207: 157500 | M207: Tempo 30 Days | N207: =J207*L207 -> 157500 | O207: =if(M207="Cash","LUNAS", IF(M207="Tempo 14 Days",D207+14, if(M207="Tempo 30 Days",D207+30, IF(M207="Tempo 2 Month",D207+60,if(M207="Tempo DUNLOP",D207+75,0))))) -> 45765 | P207: =VLOOKUP(I207,DATABASE!C:Q,11,FALSE) -> Tire | Q207: =VLOOKUP(I207,DATABASE!C:Q,4,FALSE) -> BD | Y207: 45798 | AA207: =Y207+30 -> 45828
C208: 45735 | D208: 45735 | E208: CV. MEKAR BARU/CI NOVI | F208: 1 | G208: 25003737 | H208: BIAN | I208: Flap 12 Forklift GT | J208: 1 | K208: Rp76.000 | L208: 76000 | M208: Tempo 30 Days | N208: =J208*L208 -> 76000 | O208: =if(M208="Cash","LUNAS", IF(M208="Tempo 14 Days",D208+14, if(M208="Tempo 30 Days",D208+30, IF(M208="Tempo 2 Month",D208+60,if(M208="Tempo DUNLOP",D208+75,0))))) -> 45765 | P208: =VLOOKUP(I208,DATABASE!C:Q,11,FALSE) -> Tire | Q208: =VLOOKUP(I208,DATABASE!C:Q,4,FALSE) -> Flap | Y208: 45798 | AA208: =Y208+30 -> 45828
C209: 45735 | D209: 45735 | E209: CV. MEKAR BARU/CI NOVI | F209: 1 | G209: 25003774 | H209: BIAN | I209: GT 185/80 14 ECOTEC | J209: 6 | K209: Rp549.320 | L209: 549320 | M209: Tempo 30 Days | N209: =J209*L209 -> 3295920 | O209: =if(M209="Cash","LUNAS", IF(M209="Tempo 14 Days",D209+14, if(M209="Tempo 30 Days",D209+30, IF(M209="Tempo 2 Month",D209+60,if(M209="Tempo DUNLOP",D209+75,0))))) -> 45765 | P209: =VLOOKUP(I209,DATABASE!C:Q,11,FALSE) -> Tire | Q209: =VLOOKUP(I209,DATABASE!C:Q,4,FALSE) -> GT | Y209: 45821 | AA209: =Y209+30 -> 45851
C210: 45735 | D210: 45735 | E210: CV. MEKAR BARU/CI NOVI | F210: 1 | G210: 25003774 | H210: BIAN | I210: GT 235/60 16 SAVERO SUV | J210: 8 | K210: Rp822.740 | L210: 822740 | M210: Tempo 30 Days | N210: =J210*L210 -> 6581920 | O210: =if(M210="Cash","LUNAS", IF(M210="Tempo 14 Days",D210+14, if(M210="Tempo 30 Days",D210+30, IF(M210="Tempo 2 Month",D210+60,if(M210="Tempo DUNLOP",D210+75,0))))) -> 45765 | P210: =VLOOKUP(I210,DATABASE!C:Q,11,FALSE) -> Tire | Q210: =VLOOKUP(I210,DATABASE!C:Q,4,FALSE) -> GT | Y210: 45821 | AA210: =Y210+30 -> 45851
... C218: 45740 | D218: 45740 | E218: CV. MEKAR BARU/CI NOVI | F218: 1 | G218: 25004051 | H218: BIAN | I218: GT 750/16 HAPPY DUTY | J218: 10 | K218: Rp1.500.000 | L218: 1500000 | M218: Tempo 30 Days | N218: =J218*L218 -> 15000000 | O218: =if(M218="Cash","LUNAS", IF(M218="Tempo 14 Days",D218+14, if(M218="Tempo 30 Days",D218+30, IF(M218="Tempo 2 Month",D218+60,if(M218="Tempo DUNLOP",D218+75,0))))) -> 45770 | P218: =VLOOKUP(I218,DATABASE!C:Q,11,FALSE) -> Tire | Q218: =VLOOKUP(I218,DATABASE!C:Q,4,FALSE) -> GT | Y218: 45930 | AA218: =Y218+30 -> 45960
C219: 45741 | D219: 45741 | E219: TS. SUDIRMAN/NAUFAL | F219: 1 | G219: SLS-SDR-2502904 | H219: IBU | I219: Bridgestone 195/70 14 Ecopia | J219: 2 | K219: 715635 | L219: 715635 | M219: Tempo 2 Month | N219: =J219*L219 -> 1431270 | O219: =if(M219="Cash","LUNAS", IF(M219="Tempo 14 Days",D219+14, if(M219="Tempo 30 Days",D219+30, IF(M219="Tempo 2 Month",D219+60,if(M219="Tempo DUNLOP",D219+75,0))))) -> 45801 | P219: =VLOOKUP(I219,DATABASE!C:Q,11,FALSE) -> Tire | Q219: =VLOOKUP(I219,DATABASE!C:Q,4,FALSE) -> Bridgestone | Y219: 45930 | AA219: =Y219+30 -> 45960
C220: 45741 | D220: 45741 | E220: TS. SUDIRMAN/NAUFAL | F220: 1 | G220: SLS-SDR-2502904 | H220: IBU | I220: Bridgestone 205/65 15 Ecopia | J220: 10 | K220: 834889 | L220: 834889 | M220: Tempo 2 Month | N220: =J220*L220 -> 8348890 | O220: =if(M220="Cash","LUNAS", IF(M220="Tempo 14 Days",D220+14, if(M220="Tempo 30 Days",D220+30, IF(M220="Tempo 2 Month",D220+60,if(M220="Tempo DUNLOP",D220+75,0))))) -> 45801 | P220: =VLOOKUP(I220,DATABASE!C:Q,11,FALSE) -> Tire | Q220: =VLOOKUP(I220,DATABASE!C:Q,4,FALSE) -> Bridgestone
C221: 45741 | D221: 45741 | E221: TS. SUDIRMAN/NAUFAL | F221: 1 | G221: SLS-SDR-2502905 | H221: IBU | I221: Bridgestone 205/55 16 Techno Sport | J221: 3 | K221: Rp846.720 | L221: 846720 | M221: Tempo 2 Month | N221: =J221*L221 -> 2540160 | O221: =if(M221="Cash","LUNAS", IF(M221="Tempo 14 Days",D221+14, if(M221="Tempo 30 Days",D221+30, IF(M221="Tempo 2 Month",D221+60,if(M221="Tempo DUNLOP",D221+75,0))))) -> 45801 | P221: =VLOOKUP(I221,DATABASE!C:Q,11,FALSE) -> Tire | Q221: =VLOOKUP(I221,DATABASE!C:Q,4,FALSE) -> Bridgestone
C222: 45741 | D222: 45741 | E222: TS. SUDIRMAN/NAUFAL | F222: 1 | G222: SLS-SDR-2502905 | H222: IBU | I222: Bridgestone 185/65 15 Ecopia | J222: 10 | K222: Rp766.438 | L222: 766438.4 | M222: Tempo 2 Month | N222: =J222*L222 -> 7664384 | O222: =if(M222="Cash","LUNAS", IF(M222="Tempo 14 Days",D222+14, if(M222="Tempo 30 Days",D222+30, IF(M222="Tempo 2 Month",D222+60,if(M222="Tempo DUNLOP",D222+75,0))))) -> 45801 | P222: =VLOOKUP(I222,DATABASE!C:Q,11,FALSE) -> Tire | Q222: =VLOOKUP(I222,DATABASE!C:Q,4,FALSE) -> Bridgestone
C223: 45741 | D223: 45741 | E223: TS. SUDIRMAN/NAUFAL | F223: 1 | G223: SLS-SDR-2502916 | H223: IBU | I223: Bridgestone 175/70 13 Ecopia | J223: 4 | K223: Rp634.099 | L223: 634099.2 | M223: Tempo 2 Month | N223: =J223*L223 -> 2536396.8 | O223: =if(M223="Cash","LUNAS", IF(M223="Tempo 14 Days",D223+14, if(M223="Tempo 30 Days",D223+30, IF(M223="Tempo 2 Month",D223+60,if(M223="Tempo DUNLOP",D223+75,0))))) -> 45801 | P223: =VLOOKUP(I223,DATABASE!C:Q,11,FALSE) -> Tire | Q223: =VLOOKUP(I223,DATABASE!C:Q,4,FALSE) -> Bridgestone
C224: 45742 | D224: 45742 | E224: KHARISMA MAKMUR ABADI/PAK DADI | F224: 1 | G224: FJ/25/03/0331 | H224: IBU | I224: Dunlop 195/65 15 SPRILL Z | J224: 15 | K224: Rp580.000 | L224: 580000 | M224: Tempo DUNLOP | N224: =J224*L224 -> 8700000 | O224: =if(M224="Cash","LUNAS", IF(M224="Tempo 14 Days",D224+14, if(M224="Tempo 30 Days",D224+30, IF(M224="Tempo 2 Month",D224+60,if(M224="Tempo DUNLOP",D224+75,0))))) -> 45817 | P224: =VLOOKUP(I224,DATABASE!C:Q,11,FALSE) -> Tire | Q224: =VLOOKUP(I224,DATABASE!C:Q,4,FALSE) -> Dunlop
C225: 45742 | D225: 45742 | E225: KHARISMA MAKMUR ABADI/PAK DADI | F225: 1 | G225: FJ/25/03/0331 | H225: IBU | I225: Dunlop 750/16 12PR | J225: 1 | K225: Rp1.430.000 | L225: 1430000 | M225: Tempo DUNLOP | N225: =J225*L225 -> 1430000 | O225: =if(M225="Cash","LUNAS", IF(M225="Tempo 14 Days",D225+14, if(M225="Tempo 30 Days",D225+30, IF(M225="Tempo 2 Month",D225+60,if(M225="Tempo DUNLOP",D225+75,0))))) -> 45817 | P225: =VLOOKUP(I225,DATABASE!C:Q,11,FALSE) -> Tire | Q225: =VLOOKUP(I225,DATABASE!C:Q,4,FALSE) -> Dunlop
C226: 45742 | D226: 45742 | E226: KHARISMA MAKMUR ABADI/PAK DADI | F226: 1 | G226: FJ/25/03/0331 | H226: IBU | I226: Dunlop 235/60 16 ST20 | J226: 6 | K226: Rp1.170.000 | L226: 1170000 | M226: Tempo DUNLOP | N226: =J226*L226 -> 7020000 | O226: =if(M226="Cash","LUNAS", IF(M226="Tempo 14 Days",D226+14, if(M226="Tempo 30 Days",D226+30, IF(M226="Tempo 2 Month",D226+60,if(M226="Tempo DUNLOP",D226+75,0))))) -> 45817 | P226: =VLOOKUP(I226,DATABASE!C:Q,11,FALSE) -> Tire | Q226: =VLOOKUP(I226,DATABASE!C:Q,4,FALSE) -> Dunlop
C227: 45742 | D227: 45742 | E227: KHARISMA MAKMUR ABADI/PAK DADI | F227: 1 | G227: FJ/25/03/0331 | H227: IBU | I227: Dunlop 205/65 16 EC300 | J227: 4 | K227: Rp770.000 | L227: 770000 | M227: Tempo DUNLOP | N227: =J227*L227 -> 3080000 | O227: =if(M227="Cash","LUNAS", IF(M227="Tempo 14 Days",D227+14, if(M227="Tempo 30 Days",D227+30, IF(M227="Tempo 2 Month",D227+60,if(M227="Tempo DUNLOP",D227+75,0))))) -> 45817 | P227: =VLOOKUP(I227,DATABASE!C:Q,11,FALSE) -> Tire | Q227: =VLOOKUP(I227,DATABASE!C:Q,4,FALSE) -> Dunlop
C228: 45742 | D228: 45742 | E228: KHARISMA MAKMUR ABADI/PAK DADI | F228: 1 | G228: FJ/25/03/0331 | H228: IBU | I228: Dunlop 185/55 15 EC300 | J228: 6 | K228: Rp690.000 | L228: 690000 | M228: Tempo DUNLOP | N228: =J228*L228 -> 4140000 | O228: =if(M228="Cash","LUNAS", IF(M228="Tempo 14 Days",D228+14, if(M228="Tempo 30 Days",D228+30, IF(M228="Tempo 2 Month",D228+60,if(M228="Tempo DUNLOP",D228+75,0))))) -> 45817 | P228: =VLOOKUP(I228,DATABASE!C:Q,11,FALSE) -> Tire | Q228: =VLOOKUP(I228,DATABASE!C:Q,4,FALSE) -> Dunlop
C229: 45742 | D229: 45742 | E229: KHARISMA MAKMUR ABADI/PAK DADI | F229: 1 | G229: FJ/25/03/0331 | H229: IBU | I229: Dunlop 175/13 LT5 | J229: 50 | K229: Rp602.000 | L229: 602000 | M229: Tempo DUNLOP | N229: =J229*L229 -> 30100000 | O229: =if(M229="Cash","LUNAS", IF(M229="Tempo 14 Days",D229+14, if(M229="Tempo 30 Days",D229+30, IF(M229="Tempo 2 Month",D229+60,if(M229="Tempo DUNLOP",D229+75,0))))) -> 45817 | P229: =VLOOKUP(I229,DATABASE!C:Q,11,FALSE) -> Tire | Q229: =VLOOKUP(I229,DATABASE!C:Q,4,FALSE) -> Dunlop
C230: 45742 | D230: 45742 | E230: KHARISMA MAKMUR ABADI/PAK DADI | F230: 1 | G230: FJ/25/03/0332 | H230: IBU | I230: Dunlop 165/13 LT5 | J230: 16 | K230: Rp573.000 | L230: 573000 | M230: Tempo DUNLOP | N230: =J230*L230 -> 9168000 | O230: =if(M230="Cash","LUNAS", IF(M230="Tempo 14 Days",D230+14, if(M230="Tempo 30 Days",D230+30, IF(M230="Tempo 2 Month",D230+60,if(M230="Tempo DUNLOP",D230+75,0))))) -> 45817 | P230: =VLOOKUP(I230,DATABASE!C:Q,11,FALSE) -> Tire | Q230: =VLOOKUP(I230,DATABASE!C:Q,4,FALSE) -> Dunlop
C231: 45742 | D231: 45742 | E231: KHARISMA MAKMUR ABADI/PAK DADI | F231: 1 | G231: FJ/25/03/0332 | H231: IBU | I231: Dunlop 175/13 LT5 | J231: 30 | K231: Rp602.000 | L231: 602000 | M231: Tempo DUNLOP | N231: =J231*L231 -> 18060000 | O231: =if(M231="Cash","LUNAS", IF(M231="Tempo 14 Days",D231+14, if(M231="Tempo 30 Days",D231+30, IF(M231="Tempo 2 Month",D231+60,if(M231="Tempo DUNLOP",D231+75,0))))) -> 45817 | P231: =VLOOKUP(I231,DATABASE!C:Q,11,FALSE) -> Tire | Q231: =VLOOKUP(I231,DATABASE!C:Q,4,FALSE) -> Dunlop
C232: 45742 | D232: 45742 | E232: KHARISMA MAKMUR ABADI/PAK DADI | F232: 1 | G232: FJ/25/03/0332 | H232: IBU | I232: Dunlop 185/14 LT5 | J232: 16 | K232: Rp715.000 | L232: 715000 | M232: Tempo DUNLOP | N232: =J232*L232 -> 11440000 | O232: =if(M232="Cash","LUNAS", IF(M232="Tempo 14 Days",D232+14, if(M232="Tempo 30 Days",D232+30, IF(M232="Tempo 2 Month",D232+60,if(M232="Tempo DUNLOP",D232+75,0))))) -> 45817 | P232: =VLOOKUP(I232,DATABASE!C:Q,11,FALSE) -> Tire | Q232: =VLOOKUP(I232,DATABASE!C:Q,4,FALSE) -> Dunlop
... C238: 45743 | D238: 45743 | E238: KHARISMA MAKMUR ABADI/PAK DADI | F238: 1 | G238: FJ/PST/BDG/25/03/0358 | H238: IBU | I238: Dunlop 175/13 LT5 | J238: 7 | K238: Rp602.000 | L238: 602000 | M238: Tempo DUNLOP | N238: =J238*L238 -> 4214000 | O238: =if(M238="Cash","LUNAS", IF(M238="Tempo 14 Days",D238+14, if(M238="Tempo 30 Days",D238+30, IF(M238="Tempo 2 Month",D238+60,if(M238="Tempo DUNLOP",D238+75,0))))) -> 45818 | P238: =VLOOKUP(I238,DATABASE!C:Q,11,FALSE) -> Tire | Q238: =VLOOKUP(I238,DATABASE!C:Q,4,FALSE) -> Dunlop
C239: 45754 | D239: 45754 | E239: KHARISMA MAKMUR ABADI/PAK DADI | F239: 0 | G239: - | H239: 0 | I239: Dunlop 185/70 14 SP10 | J239: 1 | K239: 575000 | L239: 575000 | M239: Tempo DUNLOP | N239: =J239*L239 -> 575000 | O239: =if(M239="Cash","LUNAS", IF(M239="Tempo 14 Days",D239+14, if(M239="Tempo 30 Days",D239+30, IF(M239="Tempo 2 Month",D239+60,if(M239="Tempo DUNLOP",D239+75,0))))) -> 45829 | P239: =VLOOKUP(I239,DATABASE!C:Q,11,FALSE) -> Tire | Q239: =VLOOKUP(I239,DATABASE!C:Q,4,FALSE) -> Dunlop
C240: 45756 | D240: 45756 | E240: CV. MEKAR BARU/CI NOVI | F240: 1 | G240: 25004499 | H240: BIAN | I240: GiTi 750/16 GAR | J240: 2 | K240: Rp2.045.000 | L240: 2045000 | M240: Tempo 30 Days | N240: =J240*L240 -> 4090000 | O240: =if(M240="Cash","LUNAS", IF(M240="Tempo 14 Days",D240+14, if(M240="Tempo 30 Days",D240+30, IF(M240="Tempo 2 Month",D240+60,if(M240="Tempo DUNLOP",D240+75,0))))) -> 45786 | P240: =VLOOKUP(I240,DATABASE!C:Q,11,FALSE) -> Tire | Q240: =VLOOKUP(I240,DATABASE!C:Q,4,FALSE) -> GiTi
C241: 45757 | D241: 45757 | E241: PT. RODA ARTHA | F241: 1 | G241: SI/BDG/04/2025/00005 | H241: BIAN | I241: TIRON 750/16 | J241: 10 | K241: Rp1.650.000 | L241: 1650000 | M241: Tempo 2 Month | N241: =J241*L241 -> 16500000 | O241: =if(M241="Cash","LUNAS", IF(M241="Tempo 14 Days",D241+14, if(M241="Tempo 30 Days",D241+30, IF(M241="Tempo 2 Month",D241+60,if(M241="Tempo DUNLOP",D241+75,0))))) -> 45817 | P241: =VLOOKUP(I241,DATABASE!C:Q,11,FALSE) -> Tire | Q241: =VLOOKUP(I241,DATABASE!C:Q,4,FALSE) -> TIRON
C242: 45757 | D242: 45757 | E242: PT. RODA ARTHA | F242: 1 | G242: SI/BDG/04/2025/00005 | H242: BIAN | I242: Advance 750/16 GLG71A+ | J242: 6 | K242: Rp1.840.000 | L242: 1840000 | M242: Tempo 2 Month | N242: =J242*L242 -> 11040000 | O242: =if(M242="Cash","LUNAS", IF(M242="Tempo 14 Days",D242+14, if(M242="Tempo 30 Days",D242+30, IF(M242="Tempo 2 Month",D242+60,if(M242="Tempo DUNLOP",D242+75,0))))) -> 45817 | P242: =VLOOKUP(I242,DATABASE!C:Q,11,FALSE) -> Tire | Q242: =VLOOKUP(I242,DATABASE!C:Q,4,FALSE) -> Advance
C243: 45757 | D243: 45757 | E243: KHARISMA MAKMUR ABADI/PAK DADI | F243: 1 | G243: FJ/PST/BDG/25/04/0058 | H243: IBU | I243: Dunlop 185/70 14 SP10 | J243: 10 | K243: Rp575.000 | L243: 575000 | M243: Tempo DUNLOP | N243: =J243*L243 -> 5750000 | O243: =if(M243="Cash","LUNAS", IF(M243="Tempo 14 Days",D243+14, if(M243="Tempo 30 Days",D243+30, IF(M243="Tempo 2 Month",D243+60,if(M243="Tempo DUNLOP",D243+75,0))))) -> 45832 | P243: =VLOOKUP(I243,DATABASE!C:Q,11,FALSE) -> Tire | Q243: =VLOOKUP(I243,DATABASE!C:Q,4,FALSE) -> Dunlop
C244: 45757 | D244: 45757 | E244: KHARISMA MAKMUR ABADI/PAK DADI | F244: 1 | G244: FJ/PST/BDG/25/04/0058 | H244: IBU | I244: Dunlop 165/13 LT5 | J244: 5 | K244: Rp573.000 | L244: 573000 | M244: Tempo DUNLOP | N244: =J244*L244 -> 2865000 | O244: =if(M244="Cash","LUNAS", IF(M244="Tempo 14 Days",D244+14, if(M244="Tempo 30 Days",D244+30, IF(M244="Tempo 2 Month",D244+60,if(M244="Tempo DUNLOP",D244+75,0))))) -> 45832 | P244: =VLOOKUP(I244,DATABASE!C:Q,11,FALSE) -> Tire | Q244: =VLOOKUP(I244,DATABASE!C:Q,4,FALSE) -> Dunlop
C245: 45757 | D245: 45757 | E245: KHARISMA MAKMUR ABADI/PAK DADI | F245: 1 | G245: FJ/PST/BDG/25/04/0058 | H245: IBU | I245: Dunlop 185/14 LT5 | J245: 4 | K245: Rp715.000 | L245: 715000 | M245: Tempo DUNLOP | N245: =J245*L245 -> 2860000 | O245: =if(M245="Cash","LUNAS", IF(M245="Tempo 14 Days",D245+14, if(M245="Tempo 30 Days",D245+30, IF(M245="Tempo 2 Month",D245+60,if(M245="Tempo DUNLOP",D245+75,0))))) -> 45832 | P245: =VLOOKUP(I245,DATABASE!C:Q,11,FALSE) -> Tire | Q245: =VLOOKUP(I245,DATABASE!C:Q,4,FALSE) -> Dunlop
C246: 45759 | D246: 45759 | E246: PT BANCORE SENTRAL UTAMA | F246: 1 | G246: M001150 | H246: BIAN | I246: Laufen 185/70 14 | J246: 4 | K246: Rp454.000 | L246: 454000 | M246: Tempo 2 Month | N246: =J246*L246 -> 1816000 | O246: =if(M246="Cash","LUNAS", IF(M246="Tempo 14 Days",D246+14, if(M246="Tempo 30 Days",D246+30, IF(M246="Tempo 2 Month",D246+60,if(M246="Tempo DUNLOP",D246+75,0))))) -> 45819 | P246: =VLOOKUP(I246,DATABASE!C:Q,11,FALSE) -> Tire | Q246: =VLOOKUP(I246,DATABASE!C:Q,4,FALSE) -> Laufen
C247: 45761 | D247: 45761 | E247: KHARISMA MAKMUR ABADI/PAK DADI | F247: 0 | G247: 0 | H247: POLOSAN | I247: Dunlop 185/14 LT5 | J247: 2 | K247: Rp735.000 | L247: 735000 | M247: Tempo DUNLOP | N247: =J247*L247 -> 1470000 | O247: =if(M247="Cash","LUNAS", IF(M247="Tempo 14 Days",D247+14, if(M247="Tempo 30 Days",D247+30, IF(M247="Tempo 2 Month",D247+60,if(M247="Tempo DUNLOP",D247+75,0))))) -> 45836 | P247: =VLOOKUP(I247,DATABASE!C:Q,11,FALSE) -> Tire | Q247: =VLOOKUP(I247,DATABASE!C:Q,4,FALSE) -> Dunlop
...

Sheet TRANSACTION
A1: Perkasa Jaya Sistem Informasi
B4: ! | C4: Add Items | H4: ! | I4: Selling Cash | N4: ! | O4: Pucchase | U4: Payment of Receivables
D6: Size | J6: Date | K6: =today() -> 46291 | P6: Date In | Q6: =TODAY() -> 46291 | V6: Date | W6: =TODAY() -> 46291
D8: Tipe | J8: Invoice | P8: Date Invoice | Q8: 46289 | V8: Date Invoice | W8: 46256
D10: Brand | J10: Item | P10: Distributor | V10: Nama
D12: Stock | J12: QTY | P12: Tax | V12: Amount
W13: 2
D14: Selling Price | J14: PRICE | K14: =VLOOKUP(K10,DATABASE!C:Q,6,false) -> #N/A | P14: Invoice | V14: Profit | W14: =IF(COUNTIFS('PAYMENT CREDIT'!D:D, W8, 'PAYMENT CREDIT'!E:E, W10) > 0, 0, SUMIFS('SELLING CREDIT'!Q:Q, 'SELLING CREDIT'!C:C, W8, 'SELLING CREDIT'!E:E, W10) + SUMIFS('SELLING CREDIT'!K:K, 'SELLING CREDIT'!C:C, W8, 'SELLING CREDIT'!E:E, W10) ) -> 0
E15: 1 | K15: 5000
D16: Cost Price | J16: DISCON | P16: Owned by
D18: Owned by | P18: Item
D20: TAX | P20: Quantity
D22: Service Fee | K22: =IF(B9="Transfer", (B7-B8)*B6, IF(B9="Mix", B11, "")) | P22: Price | Q22: =VLOOKUP(Q18,DATABASE!C:Q,7,FALSE) -> #N/A
D24: Category | P24: Price Fixed
P26: Payment
B36: ! | C36: Add Customers | H36: ! | I36: Selling Credit | N36: ! | O36: Payment to Supplier/Distributor | U36: Expenses
D38: Code | E38: =IFERROR(__xludf.DUMMYFUNCTION("""C-""&TEXT(IFERROR(MAX(ARRAYFORMULA(IF(ISNUMBER(SEARCH(""C-"",DATABASE!V:V)),VALUE(REGEXEXTRACT(DATABASE!V:V,""[0-9]+"")),0))),0)+1,""0000"")"),"C-0114") -> C-0114 | J38: Date | K38: =TODAY() -> 46291 | P38: Date | Q38: =TODAY() -> 46291 | V38: Date | W38: =TODAY() -> 46291
D40: Name | E40: Fajar travel | J40: No. Invoice | P40: Nama | V40: Amount
J42: Customer | P42: Amount | V42: Explain | X42: WD
J44: Item | V44: Category
J46: QTY | V46: Payment
K47: 1
J48: Cash Price
J50: Credit Price
J52: Due Date | K52: =K38+30 -> 46321
C66: Add Distributor | I66: Transfer
D68: Code | E68: =IFERROR(__xludf.DUMMYFUNCTION("""D-""&TEXT(IFERROR(MAX(ARRAYFORMULA(IF(ISNUMBER(SEARCH(""D-"",DATABASE!AD:AD)),VALUE(REGEXEXTRACT(DATABASE!AD:AD,""[0-9]+"")),0))),0)+1,""0000"")"),"D-0023") -> D-0023 | J68: Date | K68: =TODAY() -> 46291
D70: Name | J70: Amount
K71: 1420
J72: VIA

Sheet DATA_PIVOT
D1: Top Ukuran BAN
A2: {={"Item", "Terjual"}} -> Item | B2: Terjual
A3: =IFERROR(__xludf.DUMMYFUNCTION("QUERY({ FILTER({'SELLING CASH'!E:F, TRIM('SELLING CASH'!R:R)}, YEAR('SELLING CASH'!C:C) = VALUE(DASHBOARD!B4), TRIM('SELLING CASH'!R:R) = ""Tire""); FILTER({'SELLING CREDIT'!F:G, TRIM('SELLING CREDIT'!S:S)}, YEAR('SELLING "&"CREDIT'!C:C) = VALUE(DASHBOARD!B4), TRIM('SELLING CREDIT'!S:S) = ""Tire"") }, ""SELECT Col1, SUM(Col2) WHERE Col1 IS NOT NULL GROUP BY Col1 ORDER BY SUM(Col2) DESC LIMIT 15"")"),"") | B3: =IFERROR(__xludf.DUMMYFUNCTION("""COMPUTED_VALUE"""),"sum ") -> sum
A4: =IFERROR(__xludf.DUMMYFUNCTION("""COMPUTED_VALUE"""),"Dunlop 175/13 LT5") -> Dunlop 175/13 LT5 | B4: =IFERROR(__xludf.DUMMYFUNCTION("""COMPUTED_VALUE"""),438.0) -> 438
A5: =IFERROR(__xludf.DUMMYFUNCTION("""COMPUTED_VALUE"""),"Dunlop 185/14 LT5") -> Dunlop 185/14 LT5 | B5: =IFERROR(__xludf.DUMMYFUNCTION("""COMPUTED_VALUE"""),238.0) -> 238
A6: =IFERROR(__xludf.DUMMYFUNCTION("""COMPUTED_VALUE"""),"GT 165/80 13 ECOTEC") -> GT 165/80 13 ECOTEC | B6: =IFERROR(__xludf.DUMMYFUNCTION("""COMPUTED_VALUE"""),199.0) -> 199
A7: =IFERROR(__xludf.DUMMYFUNCTION("""COMPUTED_VALUE"""),"Dunlop 185/70 14 SP10") -> Dunlop 185/70 14 SP10 | B7: =IFERROR(__xludf.DUMMYFUNCTION("""COMPUTED_VALUE"""),159.0) -> 159
A8: =IFERROR(__xludf.DUMMYFUNCTION("""COMPUTED_VALUE"""),"Dunlop 165/13 LT5") -> Dunlop 165/13 LT5 | B8: =IFERROR(__xludf.DUMMYFUNCTION("""COMPUTED_VALUE"""),128.0) -> 128
A9: =IFERROR(__xludf.DUMMYFUNCTION("""COMPUTED_VALUE"""),"BD 13 IBK") -> BD 13 IBK | B9: =IFERROR(__xludf.DUMMYFUNCTION("""COMPUTED_VALUE"""),114.0) -> 114
A10: =IFERROR(__xludf.DUMMYFUNCTION("""COMPUTED_VALUE"""),"Flap 16 GT") -> Flap 16 GT | B10: =IFERROR(__xludf.DUMMYFUNCTION("""COMPUTED_VALUE"""),97.0) -> 97
A11: =IFERROR(__xludf.DUMMYFUNCTION("""COMPUTED_VALUE"""),"TIRON 750/16") -> TIRON 750/16 | B11: =IFERROR(__xludf.DUMMYFUNCTION("""COMPUTED_VALUE"""),86.0) -> 86
A12: =IFERROR(__xludf.DUMMYFUNCTION("""COMPUTED_VALUE"""),"Dunlop 185/65 15 EC300") -> Dunlop 185/65 15 EC300 | B12: =IFERROR(__xludf.DUMMYFUNCTION("""COMPUTED_VALUE"""),75.0) -> 75
A13: =IFERROR(__xludf.DUMMYFUNCTION("""COMPUTED_VALUE"""),"Dunlop 175/65 14 EC300") -> Dunlop 175/65 14 EC300 | B13: =IFERROR(__xludf.DUMMYFUNCTION("""COMPUTED_VALUE"""),74.0) -> 74
A14: =IFERROR(__xludf.DUMMYFUNCTION("""COMPUTED_VALUE"""),"GT 550/13 8PR") -> GT 550/13 8PR | B14: =IFERROR(__xludf.DUMMYFUNCTION("""COMPUTED_VALUE"""),74.0) -> 74
A15: =IFERROR(__xludf.DUMMYFUNCTION("""COMPUTED_VALUE"""),"TIRON 750/15 12PR") -> TIRON 750/15 12PR | B15: =IFERROR(__xludf.DUMMYFUNCTION("""COMPUTED_VALUE"""),73.0) -> 73
A16: =IFERROR(__xludf.DUMMYFUNCTION("""COMPUTED_VALUE"""),"Bridgestone 185/70 14 Ecopia") -> Bridgestone 185/70 14 Ecopia | B16: =IFERROR(__xludf.DUMMYFUNCTION("""COMPUTED_VALUE"""),69.0) -> 69
A17: =IFERROR(__xludf.DUMMYFUNCTION("""COMPUTED_VALUE"""),"Advance 750/16 k. tahu GL909A") -> Advance 750/16 k. tahu GL909A | B17: =IFERROR(__xludf.DUMMYFUNCTION("""COMPUTED_VALUE"""),67.0) -> 67
A18: =IFERROR(__xludf.DUMMYFUNCTION("""COMPUTED_VALUE"""),"Bridgestone 175/13 Duravis") -> Bridgestone 175/13 Duravis | B18: =IFERROR(__xludf.DUMMYFUNCTION("""COMPUTED_VALUE"""),64.0) -> 64
A21: Bulan | B21: Jumlah | C21: Profit | F21: saya ingin mengambil data dari SHEET SELLING CASH dan PAYMENT CREDIT. Berikut beberapa ketentuanya 1. nilai yang diambil berupa bulan, penjualan, pendapatan dan profit berdasarkan filter tahun pada dashboard B4 2. pada kolom bulan mengambil data kolom C pada sheet selling cash dan selling credit, namun pada sheet tersebut formatnya berupa tanggal, bulan dan tahun sementara yang saya mau hanya bulannya saja, sementara tahunya hasiil filter dari cell B4 pada sheet dashboard 3. kolom jumlah berupa jumlah pada kolom I pada sheet selling cash dan jumlah pada kolom F pada sheet payment credit 4. kolom profit berupa jumlah laba kotor, nilai didapat dari kolom N sheet selling cash, dan kolom G pada sheet payment credit.
A22: =DATE($B$4, 1, 1) -> 159978 | B22: =SUMIFS(SELLING CASH!$I:$I, SELLING CASH!$C:$C, ">=" & DATE(DASHBOARD!$B$4, $A22, 1), SELLING CASH!$C:$C, "<=" & EOMONTH(DATE(DASHBOARD!$B$4, $A22, 1), 0)) + SUMIFS(PAYMENT CREDIT!$F:$F, PAYMENT CREDIT!$C:$C, ">=" & DATE(DASHBOARD!$B$4, $A22, 1), PAYMENT CREDIT!$C:$C, "<=" & EOMONTH(DATE(DASHBOARD!$B$4, $A22, 1), 0)) -> #ERROR!
A23: =DATE($B$4, 2, 1) -> 160009
A24: =DATE($B$4, 3, 1) -> 160037
A25: =DATE($B$4, 4, 1) -> 160068
A26: =DATE($B$4, 5, 1) -> 160098
A27: =DATE($B$4, 6, 1) -> 160129
A28: =DATE($B$4, 7, 1) -> 160159
A29: =DATE($B$4, 8, 1) -> 160190
A30: =DATE($B$4, 9, 1) -> 160221
A31: =DATE($B$4, 10, 1) -> 160251
A32: =DATE($B$4, 11, 1) -> 160282
A33: =DATE($B$4, 12, 1) -> 160312

Sheet SELLING CASH
C1: Date | D1: Invoice | E1: Item | F1: QTY | G1: Price | H1: Discon | I1: Total | J1: Service Fee | K1: Cost Price VLOOKUP | L1: Coist Price Absolute | M1: Cost Price Fixed | N1: Profit | O1: Owned by | P1: Tax | Q1: Brand | R1: Category | S1: =COUNTA(C:C) -> 10490
C2: 45658 | D2: 3761 | E2: GT 185/65 15 ECOTEC | F2: 2 | G2: 670000 | H2: 0 | I2: =(G2-H2)*F2 -> 1340000 | J2: =IF(E2="SERVICE",I2-(I2*50%),Vlookup(E2,DATABASE!C:Q,10,false)*F2) -> 0 | K2: 582500 | L2: 582500 | M2: =CEILING(L2, 5000) -> 585000 | N2: =if(R2="SERVICE",I2-(J2+M2), IF(R2="COMPLEMENTARY",I2-((M2*F2)+J2),I2-(M2*F2))) -> 170000 | O2: =VLOOKUP(E2,DATABASE!C:Q,8,false) -> BIAN | P2: =VLOOKUP(E2,DATABASE!C:Q,9,False) -> 1 | Q2: =VLOOKUP(E2,DATABASE!C:Q,4,false) -> GT | R2: =VLOOKUP(E2,DATABASE!C:Q,11,false) -> Tire
C3: 45658 | D3: 3761 | E3: Balancing 30 | F3: 2 | G3: 30000 | H3: 0 | I3: =(G3-H3)*F3 -> 60000 | J3: =IF(E3="SERVICE",I3-(I3*50%),Vlookup(E3,DATABASE!C:Q,10,false)*F3) -> 0 | K3: 0 | L3: 0 | M3: =CEILING(L3, 5000) -> 0 | N3: =if(R3="SERVICE",I3-(J3+M3), IF(R3="COMPLEMENTARY",I3-((M3*F3)+J3),I3-(M3*F3))) -> 60000 | O3: =VLOOKUP(E3,DATABASE!C:Q,8,false) -> BIAN | P3: =VLOOKUP(E3,DATABASE!C:Q,9,False) -> 0 | Q3: =VLOOKUP(E3,DATABASE!C:Q,4,false) -> Balancing | R3: =VLOOKUP(E3,DATABASE!C:Q,11,false) -> COMPLEMENTARY
C4: 45658 | D4: 3762 | E4: Bongkar Pasang | F4: 1 | G4: 30000 | H4: 0 | I4: =(G4-H4)*F4 -> 30000 | J4: =IF(E4="SERVICE",I4-(I4*50%),Vlookup(E4,DATABASE!C:Q,10,false)*F4) -> 0 | K4: =VLOOKUP(E4,DATABASE!C:Q,7,false) -> 0 | L4: 0 | M4: =CEILING(L4, 5000) -> 0 | N4: =if(R4="SERVICE",I4-(J4+M4), IF(R4="COMPLEMENTARY",I4-((M4*F4)+J4),I4-(M4*F4))) -> 30000 | O4: =VLOOKUP(E4,DATABASE!C:Q,8,false) -> IBU | P4: =VLOOKUP(E4,DATABASE!C:Q,9,False) -> 0 | Q4: =VLOOKUP(E4,DATABASE!C:Q,4,false) -> Bongkar Pasang | R4: =VLOOKUP(E4,DATABASE!C:Q,11,false) -> SERVICE
C5: 45658 | D5: 3764 | E5: SPOORING | F5: 1 | G5: 130000 | H5: 0 | I5: =(G5-H5)*F5 -> 130000 | J5: =IF(E5="SERVICE",I5-(I5*50%),Vlookup(E5,DATABASE!C:Q,10,false)*F5) -> 10000 | K5: =VLOOKUP(E5,DATABASE!C:Q,7,false) -> 0 | L5: 0 | M5: =CEILING(L5, 5000) -> 0 | N5: =if(R5="SERVICE",I5-(J5+M5), IF(R5="COMPLEMENTARY",I5-((M5*F5)+J5),I5-(M5*F5))) -> 120000 | O5: =VLOOKUP(E5,DATABASE!C:Q,8,false) -> IBU | P5: =VLOOKUP(E5,DATABASE!C:Q,9,False) -> 0 | Q5: =VLOOKUP(E5,DATABASE!C:Q,4,false) -> SPOORING | R5: =VLOOKUP(E5,DATABASE!C:Q,11,false) -> SERVICE
C6: 45659 | D6: 3765 | E6: HANKOOK 185/70 14 | F6: 2 | G6: 625000 | H6: 0 | I6: =(G6-H6)*F6 -> 1250000 | J6: =IF(E6="SERVICE",I6-(I6*50%),Vlookup(E6,DATABASE!C:Q,10,false)*F6) -> 0 | K6: =VLOOKUP(E6,DATABASE!C:Q,7,false) -> 517000 | L6: 517000 | M6: =CEILING(L6, 5000) -> 520000 | N6: =if(R6="SERVICE",I6-(J6+M6), IF(R6="COMPLEMENTARY",I6-((M6*F6)+J6),I6-(M6*F6))) -> 210000 | O6: =VLOOKUP(E6,DATABASE!C:Q,8,false) -> BIAN | P6: =VLOOKUP(E6,DATABASE!C:Q,9,False) -> 1 | Q6: =VLOOKUP(E6,DATABASE!C:Q,4,false) -> HANKOOK | R6: =VLOOKUP(E6,DATABASE!C:Q,11,false) -> Tire
C7: 45659 | D7: 3766 | E7: Dunlop 205/65 15 SP SPORT | F7: 1 | G7: 900000 | H7: 0 | I7: =(G7-H7)*F7 -> 900000 | J7: =IF(E7="SERVICE",I7-(I7*50%),Vlookup(E7,DATABASE!C:Q,10,false)*F7) -> 0 | K7: 805000 | L7: 805000 | M7: =CEILING(L7, 5000) -> 805000 | N7: =if(R7="SERVICE",I7-(J7+M7), IF(R7="COMPLEMENTARY",I7-((M7*F7)+J7),I7-(M7*F7))) -> 95000 | O7: =VLOOKUP(E7,DATABASE!C:Q,8,false) -> IBU | P7: =VLOOKUP(E7,DATABASE!C:Q,9,False) -> 1 | Q7: =VLOOKUP(E7,DATABASE!C:Q,4,false) -> Dunlop | R7: =VLOOKUP(E7,DATABASE!C:Q,11,false) -> Tire
C8: 45659 | D8: 3768 | E8: Dunlop 175/13 LT5 | F8: 2 | G8: 700000 | H8: 0 | I8: =(G8-H8)*F8 -> 1400000 | J8: =IF(E8="SERVICE",I8-(I8*50%),Vlookup(E8,DATABASE!C:Q,10,false)*F8) -> 0 | K8: 613000 | L8: 613000 | M8: =CEILING(L8, 5000) -> 615000 | N8: =if(R8="SERVICE",I8-(J8+M8), IF(R8="COMPLEMENTARY",I8-((M8*F8)+J8),I8-(M8*F8))) -> 170000 | O8: =VLOOKUP(E8,DATABASE!C:Q,8,false) -> IBU | P8: =VLOOKUP(E8,DATABASE!C:Q,9,False) -> 1 | Q8: =VLOOKUP(E8,DATABASE!C:Q,4,false) -> Dunlop | R8: =VLOOKUP(E8,DATABASE!C:Q,11,false) -> Tire
C9: 45659 | D9: 3769 | E9: SPOORING | F9: 1 | G9: 130000 | H9: 0 | I9: =(G9-H9)*F9 -> 130000 | J9: =IF(E9="SERVICE",I9-(I9*50%),Vlookup(E9,DATABASE!C:Q,10,false)*F9) -> 10000 | K9: =VLOOKUP(E9,DATABASE!C:Q,7,false) -> 0 | L9: 0 | M9: =CEILING(L9, 5000) -> 0 | N9: =if(R9="SERVICE",I9-(J9+M9), IF(R9="COMPLEMENTARY",I9-((M9*F9)+J9),I9-(M9*F9))) -> 120000 | O9: =VLOOKUP(E9,DATABASE!C:Q,8,false) -> IBU | P9: =VLOOKUP(E9,DATABASE!C:Q,9,False) -> 0 | Q9: =VLOOKUP(E9,DATABASE!C:Q,4,false) -> SPOORING | R9: =VLOOKUP(E9,DATABASE!C:Q,11,false) -> SERVICE
C10: 45659 | D10: 3769 | E10: Balancing 30 | F10: 2 | G10: 30000 | H10: 0 | I10: =(G10-H10)*F10 -> 60000 | J10: =IF(E10="SERVICE",I10-(I10*50%),Vlookup(E10,DATABASE!C:Q,10,false)*F10) -> 0 | K10: 0 | L10: 0 | M10: =CEILING(L10, 5000) -> 0 | N10: =if(R10="SERVICE",I10-(J10+M10), IF(R10="COMPLEMENTARY",I10-((M10*F10)+J10),I10-(M10*F10))) -> 60000 | O10: =VLOOKUP(E10,DATABASE!C:Q,8,false) -> BIAN | P10: =VLOOKUP(E10,DATABASE!C:Q,9,False) -> 0 | Q10: =VLOOKUP(E10,DATABASE!C:Q,4,false) -> Balancing | R10: =VLOOKUP(E10,DATABASE!C:Q,11,false) -> COMPLEMENTARY
C11: 45659 | D11: 3770 | E11: Dunlop 185/14 LT5 | F11: 1 | G11: 830000 | H11: 0 | I11: =(G11-H11)*F11 -> 830000 | J11: =IF(E11="SERVICE",I11-(I11*50%),Vlookup(E11,DATABASE!C:Q,10,false)*F11) -> 0 | K11: 735000 | L11: 735000 | M11: =CEILING(L11, 5000) -> 735000 | N11: =if(R11="SERVICE",I11-(J11+M11), IF(R11="COMPLEMENTARY",I11-((M11*F11)+J11),I11-(M11*F11))) -> 95000 | O11: =VLOOKUP(E11,DATABASE!C:Q,8,false) -> IBU | P11: =VLOOKUP(E11,DATABASE!C:Q,9,False) -> 1 | Q11: =VLOOKUP(E11,DATABASE!C:Q,4,false) -> Dunlop | R11: =VLOOKUP(E11,DATABASE!C:Q,11,false) -> Tire
C12: 45659 | D12: 3771 | E12: SPOORING | F12: 1 | G12: 130000 | H12: 0 | I12: =(G12-H12)*F12 -> 130000 | J12: =IF(E12="SERVICE",I12-(I12*50%),Vlookup(E12,DATABASE!C:Q,10,false)*F12) -> 10000 | K12: =VLOOKUP(E12,DATABASE!C:Q,7,false) -> 0 | L12: 0 | M12: =CEILING(L12, 5000) -> 0 | N12: =if(R12="SERVICE",I12-(J12+M12), IF(R12="COMPLEMENTARY",I12-((M12*F12)+J12),I12-(M12*F12))) -> 120000 | O12: =VLOOKUP(E12,DATABASE!C:Q,8,false) -> IBU | P12: =VLOOKUP(E12,DATABASE!C:Q,9,False) -> 0 | Q12: =VLOOKUP(E12,DATABASE!C:Q,4,false) -> SPOORING | R12: =VLOOKUP(E12,DATABASE!C:Q,11,false) -> SERVICE
C13: 45659 | D13: 3771 | E13: Baut Camber | F13: 1 | G13: 250000 | H13: 0 | I13: =(G13-H13)*F13 -> 250000 | J13: =IF(E13="SERVICE",I13-(I13*50%),Vlookup(E13,DATABASE!C:Q,10,false)*F13) -> 75000 | K13: =VLOOKUP(E13,DATABASE!C:Q,7,false) -> 75000 | L13: 75000 | M13: =CEILING(L13, 5000) -> 75000 | N13: =if(R13="SERVICE",I13-(J13+M13), IF(R13="COMPLEMENTARY",I13-((M13*F13)+J13),I13-(M13*F13))) -> 100000 | O13: =VLOOKUP(E13,DATABASE!C:Q,8,false) -> BIAN | P13: =VLOOKUP(E13,DATABASE!C:Q,9,False) -> 0 | Q13: =VLOOKUP(E13,DATABASE!C:Q,4,false) -> Baut Camber | R13: =VLOOKUP(E13,DATABASE!C:Q,11,false) -> COMPLEMENTARY
C14: 45659 | D14: 3772 | E14: Advance 750/16 GL672D | F14: 4 | G14: 2050000 | H14: 0 | I14: =(G14-H14)*F14 -> 8200000 | J14: =IF(E14="SERVICE",I14-(I14*50%),Vlookup(E14,DATABASE!C:Q,10,false)*F14) -> 0 | K14: 1950000 | L14: 1950000 | M14: =CEILING(L14, 5000) -> 1950000 | N14: =if(R14="SERVICE",I14-(J14+M14), IF(R14="COMPLEMENTARY",I14-((M14*F14)+J14),I14-(M14*F14))) -> 400000 | O14: =VLOOKUP(E14,DATABASE!C:Q,8,false) -> BIAN | P14: =VLOOKUP(E14,DATABASE!C:Q,9,False) -> 1 | Q14: =VLOOKUP(E14,DATABASE!C:Q,4,false) -> Advance | R14: =VLOOKUP(E14,DATABASE!C:Q,11,false) -> Tire
C15: 45659 | D15: 3773 | E15: GT 175/13 MAXMILLER | F15: 1 | G15: 640000 | H15: 0 | I15: =(G15-H15)*F15 -> 640000 | J15: =IF(E15="SERVICE",I15-(I15*50%),Vlookup(E15,DATABASE!C:Q,10,false)*F15) -> 0 | K15: 560000 | L15: 560000 | M15: =CEILING(L15, 5000) -> 560000 | N15: =if(R15="SERVICE",I15-(J15+M15), IF(R15="COMPLEMENTARY",I15-((M15*F15)+J15),I15-(M15*F15))) -> 80000 | O15: =VLOOKUP(E15,DATABASE!C:Q,8,false) -> BIAN | P15: =VLOOKUP(E15,DATABASE!C:Q,9,False) -> 1 | Q15: =VLOOKUP(E15,DATABASE!C:Q,4,false) -> GT | R15: =VLOOKUP(E15,DATABASE!C:Q,11,false) -> Tire
C16: 45659 | D16: 3774 | E16: Bridgestone 185/14 Duravis | F16: 2 | G16: 900000 | H16: 0 | I16: =(G16-H16)*F16 -> 1800000 | J16: =IF(E16="SERVICE",I16-(I16*50%),Vlookup(E16,DATABASE!C:Q,10,false)*F16) -> 0 | K16: =VLOOKUP(E16,DATABASE!C:Q,7,false) -> 825000 | L16: 790000 | M16: =CEILING(L16, 5000) -> 790000 | N16: =if(R16="SERVICE",I16-(J16+M16), IF(R16="COMPLEMENTARY",I16-((M16*F16)+J16),I16-(M16*F16))) -> 220000 | O16: =VLOOKUP(E16,DATABASE!C:Q,8,false) -> IBU | P16: =VLOOKUP(E16,DATABASE!C:Q,9,False) -> 1 | Q16: =VLOOKUP(E16,DATABASE!C:Q,4,false) -> Bridgestone | R16: =VLOOKUP(E16,DATABASE!C:Q,11,false) -> Tire
C17: 45659 | D17: 3775 | E17: Dunlop 185/14 LT5 | F17: 1 | G17: 830000 | H17: 0 | I17: =(G17-H17)*F17 -> 830000 | J17: =IF(E17="SERVICE",I17-(I17*50%),Vlookup(E17,DATABASE!C:Q,10,false)*F17) -> 0 | K17: 735000 | L17: 735000 | M17: =CEILING(L17, 5000) -> 735000 | N17: =if(R17="SERVICE",I17-(J17+M17), IF(R17="COMPLEMENTARY",I17-((M17*F17)+J17),I17-(M17*F17))) -> 95000 | O17: =VLOOKUP(E17,DATABASE!C:Q,8,false) -> IBU | P17: =VLOOKUP(E17,DATABASE!C:Q,9,False) -> 1 | Q17: =VLOOKUP(E17,DATABASE!C:Q,4,false) -> Dunlop | R17: =VLOOKUP(E17,DATABASE!C:Q,11,false) -> Tire
C18: 45659 | D18: 3776 | E18: Dunlop 175/13 LT5 | F18: 1 | G18: 700000 | H18: 0 | I18: =(G18-H18)*F18 -> 700000 | J18: =IF(E18="SERVICE",I18-(I18*50%),Vlookup(E18,DATABASE!C:Q,10,false)*F18) -> 0 | K18: 613000 | L18: 613000 | M18: =CEILING(L18, 5000) -> 615000 | N18: =if(R18="SERVICE",I18-(J18+M18), IF(R18="COMPLEMENTARY",I18-((M18*F18)+J18),I18-(M18*F18))) -> 85000 | O18: =VLOOKUP(E18,DATABASE!C:Q,8,false) -> IBU | P18: =VLOOKUP(E18,DATABASE!C:Q,9,False) -> 1 | Q18: =VLOOKUP(E18,DATABASE!C:Q,4,false) -> Dunlop | R18: =VLOOKUP(E18,DATABASE!C:Q,11,false) -> Tire
C19: 45659 | D19: 3777 | E19: GT 215/55 17 CHAMPIRO GTX PRO | F19: 2 | G19: 1020000 | H19: 0 | I19: =(G19-H19)*F19 -> 2040000 | J19: =IF(E19="SERVICE",I19-(I19*50%),Vlookup(E19,DATABASE!C:Q,10,false)*F19) -> 0 | K19: =VLOOKUP(E19,DATABASE!C:Q,7,false) -> 904050 | L19: 904050 | M19: =CEILING(L19, 5000) -> 905000 | N19: =if(R19="SERVICE",I19-(J19+M19), IF(R19="COMPLEMENTARY",I19-((M19*F19)+J19),I19-(M19*F19))) -> 230000 | O19: =VLOOKUP(E19,DATABASE!C:Q,8,false) -> BIAN | P19: =VLOOKUP(E19,DATABASE!C:Q,9,False) -> 1 | Q19: =VLOOKUP(E19,DATABASE!C:Q,4,false) -> GT | R19: =VLOOKUP(E19,DATABASE!C:Q,11,false) -> Tire
C20: 45659 | D20: 3778 | E20: Flap 15 GT | F20: 1 | G20: 60000 | H20: 0 | I20: =(G20-H20)*F20 -> 60000 | J20: =IF(E20="SERVICE",I20-(I20*50%),Vlookup(E20,DATABASE!C:Q,10,false)*F20) -> 0 | K20: =VLOOKUP(E20,DATABASE!C:Q,7,false) -> 39440 | L20: 39440 | M20: =CEILING(L20, 5000) -> 40000 | N20: =if(R20="SERVICE",I20-(J20+M20), IF(R20="COMPLEMENTARY",I20-((M20*F20)+J20),I20-(M20*F20))) -> 20000 | O20: =VLOOKUP(E20,DATABASE!C:Q,8,false) -> BIAN | P20: =VLOOKUP(E20,DATABASE!C:Q,9,False) -> 1 | Q20: =VLOOKUP(E20,DATABASE!C:Q,4,false) -> Flap | R20: =VLOOKUP(E20,DATABASE!C:Q,11,false) -> Tire
C21: 45659 | D21: 3780 | E21: Dunlop 165/13 LT5 | F21: 1 | G21: 670000 | H21: 0 | I21: =(G21-H21)*F21 -> 670000 | J21: =IF(E21="SERVICE",I21-(I21*50%),Vlookup(E21,DATABASE!C:Q,10,false)*F21) -> 0 | K21: 590000 | L21: 590000 | M21: =CEILING(L21, 5000) -> 590000 | N21: =if(R21="SERVICE",I21-(J21+M21), IF(R21="COMPLEMENTARY",I21-((M21*F21)+J21),I21-(M21*F21))) -> 80000 | O21: =VLOOKUP(E21,DATABASE!C:Q,8,false) -> IBU | P21: =VLOOKUP(E21,DATABASE!C:Q,9,False) -> 1 | Q21: =VLOOKUP(E21,DATABASE!C:Q,4,false) -> Dunlop | R21: =VLOOKUP(E21,DATABASE!C:Q,11,false) -> Tire
C22: 45659 | D22: 3781 | E22: SERVICE | F22: 1 | G22: 150000 | H22: 0 | I22: =(G22-H22)*F22 -> 150000 | J22: =IF(E22="SERVICE",I22-(I22*50%),Vlookup(E22,DATABASE!C:Q,10,false)*F22) -> 75000 | K22: =VLOOKUP(E22,DATABASE!C:Q,7,false) -> 0 | L22: 0 | M22: =CEILING(L22, 5000) -> 0 | N22: =if(R22="SERVICE",I22-(J22+M22), IF(R22="COMPLEMENTARY",I22-((M22*F22)+J22),I22-(M22*F22))) -> 75000 | O22: =VLOOKUP(E22,DATABASE!C:Q,8,false) -> IBU | P22: =VLOOKUP(E22,DATABASE!C:Q,9,False) -> 0 | Q22: =VLOOKUP(E22,DATABASE!C:Q,4,false) -> SERVICE | R22: =VLOOKUP(E22,DATABASE!C:Q,11,false) -> SERVICE
C23: 45659 | D23: 3781 | E23: SPOORING SS/CARRY LOS BAK | F23: 1 | G23: 110000 | H23: 0 | I23: =(G23-H23)*F23 -> 110000 | J23: =IF(E23="SERVICE",I23-(I23*50%),Vlookup(E23,DATABASE!C:Q,10,false)*F23) -> 5000 | K23: =VLOOKUP(E23,DATABASE!C:Q,7,false) -> 0 | L23: 0 | M23: =CEILING(L23, 5000) -> 0 | N23: =if(R23="SERVICE",I23-(J23+M23), IF(R23="COMPLEMENTARY",I23-((M23*F23)+J23),I23-(M23*F23))) -> 105000 | O23: =VLOOKUP(E23,DATABASE!C:Q,8,false) -> IBU | P23: =VLOOKUP(E23,DATABASE!C:Q,9,False) -> 0 | Q23: =VLOOKUP(E23,DATABASE!C:Q,4,false) -> SPOORING SS/CARRY LOS BAK | R23: =VLOOKUP(E23,DATABASE!C:Q,11,false) -> SERVICE
C24: 45659 | D24: 3782 | E24: Bridgestone 175/13 Duravis | F24: 2 | G24: 790000 | H24: 0 | I24: =(G24-H24)*F24 -> 1580000 | J24: =IF(E24="SERVICE",I24-(I24*50%),Vlookup(E24,DATABASE!C:Q,10,false)*F24) -> 0 | K24: =VLOOKUP(E24,DATABASE!C:Q,7,false) -> 710000 | L24: 680000 | M24: =CEILING(L24, 5000) -> 680000 | N24: =if(R24="SERVICE",I24-(J24+M24), IF(R24="COMPLEMENTARY",I24-((M24*F24)+J24),I24-(M24*F24))) -> 220000 | O24: =VLOOKUP(E24,DATABASE!C:Q,8,false) -> IBU | P24: =VLOOKUP(E24,DATABASE!C:Q,9,False) -> 1 | Q24: =VLOOKUP(E24,DATABASE!C:Q,4,false) -> Bridgestone | R24: =VLOOKUP(E24,DATABASE!C:Q,11,false) -> Tire
C25: 45659 | D25: 3783 | E25: Dunlop 175/13 LT5 | F25: 2 | G25: 700000 | H25: 0 | I25: =(G25-H25)*F25 -> 1400000 | J25: =IF(E25="SERVICE",I25-(I25*50%),Vlookup(E25,DATABASE!C:Q,10,false)*F25) -> 0 | K25: 613000 | L25: 613000 | M25: =CEILING(L25, 5000) -> 615000 | N25: =if(R25="SERVICE",I25-(J25+M25), IF(R25="COMPLEMENTARY",I25-((M25*F25)+J25),I25-(M25*F25))) -> 170000 | O25: =VLOOKUP(E25,DATABASE!C:Q,8,false) -> IBU | P25: =VLOOKUP(E25,DATABASE!C:Q,9,False) -> 1 | Q25: =VLOOKUP(E25,DATABASE!C:Q,4,false) -> Dunlop | R25: =VLOOKUP(E25,DATABASE!C:Q,11,false) -> Tire
C26: 45659 | D26: 3784 | E26: GT 165/80 13 ECOTEC | F26: 7 | G26: 530000 | H26: 0 | I26: =(G26-H26)*F26 -> 3710000 | J26: =IF(E26="SERVICE",I26-(I26*50%),Vlookup(E26,DATABASE!C:Q,10,false)*F26) -> 0 | K26: 441450 | L26: 441450 | M26: =CEILING(L26, 5000) -> 445000 | N26: =if(R26="SERVICE",I26-(J26+M26), IF(R26="COMPLEMENTARY",I26-((M26*F26)+J26),I26-(M26*F26))) -> 595000 | O26: =VLOOKUP(E26,DATABASE!C:Q,8,false) -> BIAN | P26: =VLOOKUP(E26,DATABASE!C:Q,9,False) -> 1 | Q26: =VLOOKUP(E26,DATABASE!C:Q,4,false) -> GT | R26: =VLOOKUP(E26,DATABASE!C:Q,11,false) -> Tire
C27: 45659 | D27: 3785 | E27: Dunlop 185/14 LT5 | F27: 2 | G27: 830000 | H27: 0 | I27: =(G27-H27)*F27 -> 1660000 | J27: =IF(E27="SERVICE",I27-(I27*50%),Vlookup(E27,DATABASE!C:Q,10,false)*F27) -> 0 | K27: 735000 | L27: 735000 | M27: =CEILING(L27, 5000) -> 735000 | N27: =if(R27="SERVICE",I27-(J27+M27), IF(R27="COMPLEMENTARY",I27-((M27*F27)+J27),I27-(M27*F27))) -> 190000 | O27: =VLOOKUP(E27,DATABASE!C:Q,8,false) -> IBU | P27: =VLOOKUP(E27,DATABASE!C:Q,9,False) -> 1 | Q27: =VLOOKUP(E27,DATABASE!C:Q,4,false) -> Dunlop | R27: =VLOOKUP(E27,DATABASE!C:Q,11,false) -> Tire
C28: 45659 | D28: 3786 | E28: Dunlop 205/65 15 SP SPORT | F28: 1 | G28: 890000 | H28: 0 | I28: =(G28-H28)*F28 -> 890000 | J28: =IF(E28="SERVICE",I28-(I28*50%),Vlookup(E28,DATABASE!C:Q,10,false)*F28) -> 0 | K28: =VLOOKUP(E28,DATABASE!C:Q,7,false) -> 818000 | L28: 818000 | M28: =CEILING(L28, 5000) -> 820000 | N28: =if(R28="SERVICE",I28-(J28+M28), IF(R28="COMPLEMENTARY",I28-((M28*F28)+J28),I28-(M28*F28))) -> 70000 | O28: =VLOOKUP(E28,DATABASE!C:Q,8,false) -> IBU | P28: =VLOOKUP(E28,DATABASE!C:Q,9,False) -> 1 | Q28: =VLOOKUP(E28,DATABASE!C:Q,4,false) -> Dunlop | R28: =VLOOKUP(E28,DATABASE!C:Q,11,false) -> Tire
C29: 45660 | D29: 3788 | E29: Dunlop 175/13 LT5 | F29: 2 | G29: 700000 | H29: 0 | I29: =(G29-H29)*F29 -> 1400000 | J29: =IF(E29="SERVICE",I29-(I29*50%),Vlookup(E29,DATABASE!C:Q,10,false)*F29) -> 0 | K29: 613000 | L29: 613000 | M29: =CEILING(L29, 5000) -> 615000 | N29: =if(R29="SERVICE",I29-(J29+M29), IF(R29="COMPLEMENTARY",I29-((M29*F29)+J29),I29-(M29*F29))) -> 170000 | O29: =VLOOKUP(E29,DATABASE!C:Q,8,false) -> IBU | P29: =VLOOKUP(E29,DATABASE!C:Q,9,False) -> 1 | Q29: =VLOOKUP(E29,DATABASE!C:Q,4,false) -> Dunlop | R29: =VLOOKUP(E29,DATABASE!C:Q,11,false) -> Tire
C30: 45660 | D30: 3789 | E30: Dunlop 185/14 LT5 | F30: 2 | G30: 830000 | H30: 0 | I30: =(G30-H30)*F30 -> 1660000 | J30: =IF(E30="SERVICE",I30-(I30*50%),Vlookup(E30,DATABASE!C:Q,10,false)*F30) -> 0 | K30: 735000 | L30: 735000 | M30: =CEILING(L30, 5000) -> 735000 | N30: =if(R30="SERVICE",I30-(J30+M30), IF(R30="COMPLEMENTARY",I30-((M30*F30)+J30),I30-(M30*F30))) -> 190000 | O30: =VLOOKUP(E30,DATABASE!C:Q,8,false) -> IBU | P30: =VLOOKUP(E30,DATABASE!C:Q,9,False) -> 1 | Q30: =VLOOKUP(E30,DATABASE!C:Q,4,false) -> Dunlop | R30: =VLOOKUP(E30,DATABASE!C:Q,11,false) -> Tire
C31: 45660 | D31: 3790 | E31: Dunlop 185/14 LT5 | F31: 1 | G31: 830000 | H31: 0 | I31: =(G31-H31)*F31 -> 830000 | J31: =IF(E31="SERVICE",I31-(I31*50%),Vlookup(E31,DATABASE!C:Q,10,false)*F31) -> 0 | K31: 735000 | L31: 735000 | M31: =CEILING(L31, 5000) -> 735000 | N31: =if(R31="SERVICE",I31-(J31+M31), IF(R31="COMPLEMENTARY",I31-((M31*F31)+J31),I31-(M31*F31))) -> 95000 | O31: =VLOOKUP(E31,DATABASE!C:Q,8,false) -> IBU | P31: =VLOOKUP(E31,DATABASE!C:Q,9,False) -> 1 | Q31: =VLOOKUP(E31,DATABASE!C:Q,4,false) -> Dunlop | R31: =VLOOKUP(E31,DATABASE!C:Q,11,false) -> Tire
C32: 45660 | D32: 3791 | E32: SPOORING SS/CARRY LOS BAK | F32: 1 | G32: 110000 | H32: 0 | I32: =(G32-H32)*F32 -> 110000 | J32: =IF(E32="SERVICE",I32-(I32*50%),Vlookup(E32,DATABASE!C:Q,10,false)*F32) -> 5000 | K32: =VLOOKUP(E32,DATABASE!C:Q,7,false) -> 0 | L32: 0 | M32: =CEILING(L32, 5000) -> 0 | N32: =if(R32="SERVICE",I32-(J32+M32), IF(R32="COMPLEMENTARY",I32-((M32*F32)+J32),I32-(M32*F32))) -> 105000 | O32: =VLOOKUP(E32,DATABASE!C:Q,8,false) -> IBU | P32: =VLOOKUP(E32,DATABASE!C:Q,9,False) -> 0 | Q32: =VLOOKUP(E32,DATABASE!C:Q,4,false) -> SPOORING SS/CARRY LOS BAK | R32: =VLOOKUP(E32,DATABASE!C:Q,11,false) -> SERVICE
C33: 45660 | D33: 3791 | E33: Baut Camber ss-carry | F33: 1 | G33: 200000 | H33: 0 | I33: =(G33-H33)*F33 -> 200000 | J33: =IF(E33="SERVICE",I33-(I33*50%),Vlookup(E33,DATABASE!C:Q,10,false)*F33) -> 25000 | K33: =VLOOKUP(E33,DATABASE!C:Q,7,false) -> 75000 | L33: 75000 | M33: =CEILING(L33, 5000) -> 75000 | N33: =if(R33="SERVICE",I33-(J33+M33), IF(R33="COMPLEMENTARY",I33-((M33*F33)+J33),I33-(M33*F33))) -> 100000 | O33: =VLOOKUP(E33,DATABASE!C:Q,8,false) -> BIAN | P33: =VLOOKUP(E33,DATABASE!C:Q,9,False) -> 0 | Q33: =VLOOKUP(E33,DATABASE!C:Q,4,false) -> Baut Camber ss-carry | R33: =VLOOKUP(E33,DATABASE!C:Q,11,false) -> COMPLEMENTARY
C34: 45660 | D34: 3792 | E34: GT 175/13 MAXMILLER | F34: 4 | G34: 640000 | H34: 0 | I34: =(G34-H34)*F34 -> 2560000 | J34: =IF(E34="SERVICE",I34-(I34*50%),Vlookup(E34,DATABASE!C:Q,10,false)*F34) -> 0 | K34: 560000 | L34: 560000 | M34: =CEILING(L34, 5000) -> 560000 | N34: =if(R34="SERVICE",I34-(J34+M34), IF(R34="COMPLEMENTARY",I34-((M34*F34)+J34),I34-(M34*F34))) -> 320000 | O34: =VLOOKUP(E34,DATABASE!C:Q,8,false) -> BIAN | P34: =VLOOKUP(E34,DATABASE!C:Q,9,False) -> 1 | Q34: =VLOOKUP(E34,DATABASE!C:Q,4,false) -> GT | R34: =VLOOKUP(E34,DATABASE!C:Q,11,false) -> Tire
C35: 45660 | D35: 3792 | E35: Baut Camber | F35: 1 | G35: 250000 | H35: 0 | I35: =(G35-H35)*F35 -> 250000 | J35: =IF(E35="SERVICE",I35-(I35*50%),Vlookup(E35,DATABASE!C:Q,10,false)*F35) -> 75000 | K35: =VLOOKUP(E35,DATABASE!C:Q,7,false) -> 75000 | L35: 75000 | M35: =CEILING(L35, 5000) -> 75000 | N35: =if(R35="SERVICE",I35-(J35+M35), IF(R35="COMPLEMENTARY",I35-((M35*F35)+J35),I35-(M35*F35))) -> 100000 | O35: =VLOOKUP(E35,DATABASE!C:Q,8,false) -> BIAN | P35: =VLOOKUP(E35,DATABASE!C:Q,9,False) -> 0 | Q35: =VLOOKUP(E35,DATABASE!C:Q,4,false) -> Baut Camber | R35: =VLOOKUP(E35,DATABASE!C:Q,11,false) -> COMPLEMENTARY
C36: 45660 | D36: 3792 | E36: SPOORING | F36: 1 | G36: 130000 | H36: 0 | I36: =(G36-H36)*F36 -> 130000 | J36: =IF(E36="SERVICE",I36-(I36*50%),Vlookup(E36,DATABASE!C:Q,10,false)*F36) -> 10000 | K36: =VLOOKUP(E36,DATABASE!C:Q,7,false) -> 0 | L36: 0 | M36: =CEILING(L36, 5000) -> 0 | N36: =if(R36="SERVICE",I36-(J36+M36), IF(R36="COMPLEMENTARY",I36-((M36*F36)+J36),I36-(M36*F36))) -> 120000 | O36: =VLOOKUP(E36,DATABASE!C:Q,8,false) -> IBU | P36: =VLOOKUP(E36,DATABASE!C:Q,9,False) -> 0 | Q36: =VLOOKUP(E36,DATABASE!C:Q,4,false) -> SPOORING | R36: =VLOOKUP(E36,DATABASE!C:Q,11,false) -> SERVICE
C37: 45660 | D37: 3794 | E37: Dunlop 185/70 14 SP10 | F37: 2 | G37: 660000 | H37: 0 | I37: =(G37-H37)*F37 -> 1320000 | J37: =IF(E37="SERVICE",I37-(I37*50%),Vlookup(E37,DATABASE!C:Q,10,false)*F37) -> 0 | K37: 575000 | L37: 575000 | M37: =CEILING(L37, 5000) -> 575000 | N37: =if(R37="SERVICE",I37-(J37+M37), IF(R37="COMPLEMENTARY",I37-((M37*F37)+J37),I37-(M37*F37))) -> 170000 | O37: =VLOOKUP(E37,DATABASE!C:Q,8,false) -> IBU | P37: =VLOOKUP(E37,DATABASE!C:Q,9,False) -> 1 | Q37: =VLOOKUP(E37,DATABASE!C:Q,4,false) -> Dunlop | R37: =VLOOKUP(E37,DATABASE!C:Q,11,false) -> Tire
C38: 45660 | D38: 3795 | E38: Dunlop 175/13 LT5 | F38: 4 | G38: 700000 | H38: 0 | I38: =(G38-H38)*F38 -> 2800000 | J38: =IF(E38="SERVICE",I38-(I38*50%),Vlookup(E38,DATABASE!C:Q,10,false)*F38) -> 0 | K38: 613000 | L38: 613000 | M38: =CEILING(L38, 5000) -> 615000 | N38: =if(R38="SERVICE",I38-(J38+M38), IF(R38="COMPLEMENTARY",I38-((M38*F38)+J38),I38-(M38*F38))) -> 340000 | O38: =VLOOKUP(E38,DATABASE!C:Q,8,false) -> IBU | P38: =VLOOKUP(E38,DATABASE!C:Q,9,False) -> 1 | Q38: =VLOOKUP(E38,DATABASE!C:Q,4,false) -> Dunlop | R38: =VLOOKUP(E38,DATABASE!C:Q,11,false) -> Tire
C39: 45660 | D39: 3796 | E39: SPOORING | F39: 1 | G39: 130000 | H39: 0 | I39: =(G39-H39)*F39 -> 130000 | J39: =IF(E39="SERVICE",I39-(I39*50%),Vlookup(E39,DATABASE!C:Q,10,false)*F39) -> 10000 | K39: =VLOOKUP(E39,DATABASE!C:Q,7,false) -> 0 | L39: 0 | M39: =CEILING(L39, 5000) -> 0 | N39: =if(R39="SERVICE",I39-(J39+M39), IF(R39="COMPLEMENTARY",I39-((M39*F39)+J39),I39-(M39*F39))) -> 120000 | O39: =VLOOKUP(E39,DATABASE!C:Q,8,false) -> IBU | P39: =VLOOKUP(E39,DATABASE!C:Q,9,False) -> 0 | Q39: =VLOOKUP(E39,DATABASE!C:Q,4,false) -> SPOORING | R39: =VLOOKUP(E39,DATABASE!C:Q,11,false) -> SERVICE
C40: 45660 | D40: 3796 | E40: Baut Camber | F40: 1 | G40: 250000 | H40: 0 | I40: =(G40-H40)*F40 -> 250000 | J40: =IF(E40="SERVICE",I40-(I40*50%),Vlookup(E40,DATABASE!C:Q,10,false)*F40) -> 75000 | K40: =VLOOKUP(E40,DATABASE!C:Q,7,false) -> 75000 | L40: 75000 | M40: =CEILING(L40, 5000) -> 75000 | N40: =if(R40="SERVICE",I40-(J40+M40), IF(R40="COMPLEMENTARY",I40-((M40*F40)+J40),I40-(M40*F40))) -> 100000 | O40: =VLOOKUP(E40,DATABASE!C:Q,8,false) -> BIAN | P40: =VLOOKUP(E40,DATABASE!C:Q,9,False) -> 0 | Q40: =VLOOKUP(E40,DATABASE!C:Q,4,false) -> Baut Camber | R40: =VLOOKUP(E40,DATABASE!C:Q,11,false) -> COMPLEMENTARY
C41: 45660 | D41: 3797 | E41: Baut Camber | F41: 1 | G41: 250000 | H41: 0 | I41: =(G41-H41)*F41 -> 250000 | J41: =IF(E41="SERVICE",I41-(I41*50%),Vlookup(E41,DATABASE!C:Q,10,false)*F41) -> 75000 | K41: =VLOOKUP(E41,DATABASE!C:Q,7,false) -> 75000 | L41: 75000 | M41: =CEILING(L41, 5000) -> 75000 | N41: =if(R41="SERVICE",I41-(J41+M41), IF(R41="COMPLEMENTARY",I41-((M41*F41)+J41),I41-(M41*F41))) -> 100000 | O41: =VLOOKUP(E41,DATABASE!C:Q,8,false) -> BIAN | P41: =VLOOKUP(E41,DATABASE!C:Q,9,False) -> 0 | Q41: =VLOOKUP(E41,DATABASE!C:Q,4,false) -> Baut Camber | R41: =VLOOKUP(E41,DATABASE!C:Q,11,false) -> COMPLEMENTARY
C42: 45660 | D42: 3798 | E42: Balancing 30 | F42: 2 | G42: 30000 | H42: 0 | I42: =(G42-H42)*F42 -> 60000 | J42: =IF(E42="SERVICE",I42-(I42*50%),Vlookup(E42,DATABASE!C:Q,10,false)*F42) -> 0 | K42: 0 | L42: 0 | M42: =CEILING(L42, 5000) -> 0 | N42: =if(R42="SERVICE",I42-(J42+M42), IF(R42="COMPLEMENTARY",I42-((M42*F42)+J42),I42-(M42*F42))) -> 60000 | O42: =VLOOKUP(E42,DATABASE!C:Q,8,false) -> BIAN | P42: =VLOOKUP(E42,DATABASE!C:Q,9,False) -> 0 | Q42: =VLOOKUP(E42,DATABASE!C:Q,4,false) -> Balancing | R42: =VLOOKUP(E42,DATABASE!C:Q,11,false) -> COMPLEMENTARY
C43: 45660 | D43: 3799 | E43: Bridgestone 235/75 15 Dueler H/T 689 | F43: 2 | G43: 1285000 | H43: 0 | I43: =(G43-H43)*F43 -> 2570000 | J43: =IF(E43="SERVICE",I43-(I43*50%),Vlookup(E43,DATABASE!C:Q,10,false)*F43) -> 0 | K43: 1136064 | L43: 1136064 | M43: =CEILING(L43, 5000) -> 1140000 | N43: =if(R43="SERVICE",I43-(J43+M43), IF(R43="COMPLEMENTARY",I43-((M43*F43)+J43),I43-(M43*F43))) -> 290000 | O43: =VLOOKUP(E43,DATABASE!C:Q,8,false) -> IBU | P43: =VLOOKUP(E43,DATABASE!C:Q,9,False) -> 1 | Q43: =VLOOKUP(E43,DATABASE!C:Q,4,false) -> Bridgestone | R43: =VLOOKUP(E43,DATABASE!C:Q,11,false) -> Tire
C44: 45660 | D44: 3799 | E44: NITROGEN | F44: 2 | G44: 15000 | H44: 0 | I44: =(G44-H44)*F44 -> 30000 | J44: =IF(E44="SERVICE",I44-(I44*50%),Vlookup(E44,DATABASE!C:Q,10,false)*F44) -> 0 | K44: =VLOOKUP(E44,DATABASE!C:Q,7,false) -> 0 | L44: 0 | M44: =CEILING(L44, 5000) -> 0 | N44: =if(R44="SERVICE",I44-(J44+M44), IF(R44="COMPLEMENTARY",I44-((M44*F44)+J44),I44-(M44*F44))) -> 30000 | O44: =VLOOKUP(E44,DATABASE!C:Q,8,false) -> IBU | P44: =VLOOKUP(E44,DATABASE!C:Q,9,False) -> 0 | Q44: =VLOOKUP(E44,DATABASE!C:Q,4,false) -> NITROGEN | R44: =VLOOKUP(E44,DATABASE!C:Q,11,false) -> COMPLEMENTARY
C45: 45660 | D45: 3800 | E45: Bridgestone 235/75 15 Dueler H/T 689 | F45: 1 | G45: 1230000 | H45: 0 | I45: =(G45-H45)*F45 -> 1230000 | J45: =IF(E45="SERVICE",I45-(I45*50%),Vlookup(E45,DATABASE!C:Q,10,false)*F45) -> 0 | K45: 1136064 | L45: 1136064 | M45: =CEILING(L45, 5000) -> 1140000 | N45: =if(R45="SERVICE",I45-(J45+M45), IF(R45="COMPLEMENTARY",I45-((M45*F45)+J45),I45-(M45*F45))) -> 90000 | O45: =VLOOKUP(E45,DATABASE!C:Q,8,false) -> IBU | P45: =VLOOKUP(E45,DATABASE!C:Q,9,False) -> 1 | Q45: =VLOOKUP(E45,DATABASE!C:Q,4,false) -> Bridgestone | R45: =VLOOKUP(E45,DATABASE!C:Q,11,false) -> Tire
C46: 45660 | D46: 3801 | E46: Bridgestone 175/13 Duravis | F46: 1 | G46: 790000 | H46: 0 | I46: =(G46-H46)*F46 -> 790000 | J46: =IF(E46="SERVICE",I46-(I46*50%),Vlookup(E46,DATABASE!C:Q,10,false)*F46) -> 0 | K46: =VLOOKUP(E46,DATABASE!C:Q,7,false) -> 710000 | L46: 680000 | M46: =CEILING(L46, 5000) -> 680000 | N46: =if(R46="SERVICE",I46-(J46+M46), IF(R46="COMPLEMENTARY",I46-((M46*F46)+J46),I46-(M46*F46))) -> 110000 | O46: =VLOOKUP(E46,DATABASE!C:Q,8,false) -> IBU | P46: =VLOOKUP(E46,DATABASE!C:Q,9,False) -> 1 | Q46: =VLOOKUP(E46,DATABASE!C:Q,4,false) -> Bridgestone | R46: =VLOOKUP(E46,DATABASE!C:Q,11,false) -> Tire
C47: 45660 | D47: 3802 | E47: G. YEAR 195/70 14 ADP2 | F47: 2 | G47: 645000 | H47: 0 | I47: =(G47-H47)*F47 -> 1290000 | J47: =IF(E47="SERVICE",I47-(I47*50%),Vlookup(E47,DATABASE!C:Q,10,false)*F47) -> 0 | K47: =VLOOKUP(E47,DATABASE!C:Q,7,false) -> 595000 | L47: 595000 | M47: =CEILING(L47, 5000) -> 595000 | N47: =if(R47="SERVICE",I47-(J47+M47), IF(R47="COMPLEMENTARY",I47-((M47*F47)+J47),I47-(M47*F47))) -> 100000 | O47: =VLOOKUP(E47,DATABASE!C:Q,8,false) -> BIAN | P47: =VLOOKUP(E47,DATABASE!C:Q,9,False) -> 1 | Q47: =VLOOKUP(E47,DATABASE!C:Q,4,false) -> G. YEAR | R47: =VLOOKUP(E47,DATABASE!C:Q,11,false) -> Tire
C48: 45660 | D48: 3802 | E48: NITROGEN | F48: 1 | G48: 15000 | H48: 0 | I48: =(G48-H48)*F48 -> 15000 | J48: =IF(E48="SERVICE",I48-(I48*50%),Vlookup(E48,DATABASE!C:Q,10,false)*F48) -> 0 | K48: =VLOOKUP(E48,DATABASE!C:Q,7,false) -> 0 | L48: 0 | M48: =CEILING(L48, 5000) -> 0 | N48: =if(R48="SERVICE",I48-(J48+M48), IF(R48="COMPLEMENTARY",I48-((M48*F48)+J48),I48-(M48*F48))) -> 15000 | O48: =VLOOKUP(E48,DATABASE!C:Q,8,false) -> IBU | P48: =VLOOKUP(E48,DATABASE!C:Q,9,False) -> 0 | Q48: =VLOOKUP(E48,DATABASE!C:Q,4,false) -> NITROGEN | R48: =VLOOKUP(E48,DATABASE!C:Q,11,false) -> COMPLEMENTARY
C49: 45660 | D49: 3803 | E49: Dunlop 175/70 13 TOURING | F49: 2 | G49: 560000 | H49: 0 | I49: =(G49-H49)*F49 -> 1120000 | J49: =IF(E49="SERVICE",I49-(I49*50%),Vlookup(E49,DATABASE!C:Q,10,false)*F49) -> 0 | K49: =VLOOKUP(E49,DATABASE!C:Q,7,false) -> 501500 | L49: 491000 | M49: =CEILING(L49, 5000) -> 495000 | N49: =if(R49="SERVICE",I49-(J49+M49), IF(R49="COMPLEMENTARY",I49-((M49*F49)+J49),I49-(M49*F49))) -> 130000 | O49: =VLOOKUP(E49,DATABASE!C:Q,8,false) -> IBU | P49: =VLOOKUP(E49,DATABASE!C:Q,9,False) -> 1 | Q49: =VLOOKUP(E49,DATABASE!C:Q,4,false) -> Dunlop | R49: =VLOOKUP(E49,DATABASE!C:Q,11,false) -> Tire
C50: 45660 | D50: 3804 | E50: Bongkar Pasang 17 | F50: 4 | G50: 50000 | H50: 0 | I50: =(G50-H50)*F50 -> 200000 | J50: =IF(E50="SERVICE",I50-(I50*50%),Vlookup(E50,DATABASE!C:Q,10,false)*F50) -> 0 | K50: =VLOOKUP(E50,DATABASE!C:Q,7,false) -> 0 | L50: 0 | M50: =CEILING(L50, 5000) -> 0 | N50: =if(R50="SERVICE",I50-(J50+M50), IF(R50="COMPLEMENTARY",I50-((M50*F50)+J50),I50-(M50*F50))) -> 200000 | O50: =VLOOKUP(E50,DATABASE!C:Q,8,false) -> IBU | P50: =VLOOKUP(E50,DATABASE!C:Q,9,False) -> 0 | Q50: =VLOOKUP(E50,DATABASE!C:Q,4,false) -> Bongkar Pasang 17 | R50: =VLOOKUP(E50,DATABASE!C:Q,11,false) -> SERVICE
C51: 45660 | D51: 3804 | E51: Balancing 60 | F51: 2 | G51: 45000 | H51: 0 | I51: =(G51-H51)*F51 -> 90000 | J51: =IF(E51="SERVICE",I51-(I51*50%),Vlookup(E51,DATABASE!C:Q,10,false)*F51) -> 0 | K51: 0 | L51: 0 | M51: =CEILING(L51, 5000) -> 0 | N51: =if(R51="SERVICE",I51-(J51+M51), IF(R51="COMPLEMENTARY",I51-((M51*F51)+J51),I51-(M51*F51))) -> 90000 | O51: =VLOOKUP(E51,DATABASE!C:Q,8,false) -> BIAN | P51: =VLOOKUP(E51,DATABASE!C:Q,9,False) -> 0 | Q51: =VLOOKUP(E51,DATABASE!C:Q,4,false) -> Balancing | R51: =VLOOKUP(E51,DATABASE!C:Q,11,false) -> COMPLEMENTARY
C52: 45660 | D52: 3805 | E52: SPOORING | F52: 1 | G52: 130000 | H52: 0 | I52: =(G52-H52)*F52 -> 130000 | J52: =IF(E52="SERVICE",I52-(I52*50%),Vlookup(E52,DATABASE!C:Q,10,false)*F52) -> 10000 | K52: =VLOOKUP(E52,DATABASE!C:Q,7,false) -> 0 | L52: 0 | M52: =CEILING(L52, 5000) -> 0 | N52: =if(R52="SERVICE",I52-(J52+M52), IF(R52="COMPLEMENTARY",I52-((M52*F52)+J52),I52-(M52*F52))) -> 120000 | O52: =VLOOKUP(E52,DATABASE!C:Q,8,false) -> IBU | P52: =VLOOKUP(E52,DATABASE!C:Q,9,False) -> 0 | Q52: =VLOOKUP(E52,DATABASE!C:Q,4,false) -> SPOORING | R52: =VLOOKUP(E52,DATABASE!C:Q,11,false) -> SERVICE
C53: 45660 | D53: 3805 | E53: Balancing 30 | F53: 2 | G53: 30000 | H53: 0 | I53: =(G53-H53)*F53 -> 60000 | J53: =IF(E53="SERVICE",I53-(I53*50%),Vlookup(E53,DATABASE!C:Q,10,false)*F53) -> 0 | K53: 0 | L53: 0 | M53: =CEILING(L53, 5000) -> 0 | N53: =if(R53="SERVICE",I53-(J53+M53), IF(R53="COMPLEMENTARY",I53-((M53*F53)+J53),I53-(M53*F53))) -> 60000 | O53: =VLOOKUP(E53,DATABASE!C:Q,8,false) -> BIAN | P53: =VLOOKUP(E53,DATABASE!C:Q,9,False) -> 0 | Q53: =VLOOKUP(E53,DATABASE!C:Q,4,false) -> Balancing | R53: =VLOOKUP(E53,DATABASE!C:Q,11,false) -> COMPLEMENTARY
C54: 45660 | D54: 3805 | E54: SERVICE | F54: 1 | G54: 150000 | H54: 0 | I54: =(G54-H54)*F54 -> 150000 | J54: =IF(E54="SERVICE",I54-(I54*50%),Vlookup(E54,DATABASE!C:Q,10,false)*F54) -> 75000 | K54: =VLOOKUP(E54,DATABASE!C:Q,7,false) -> 0 | L54: 0 | M54: =CEILING(L54, 5000) -> 0 | N54: =if(R54="SERVICE",I54-(J54+M54), IF(R54="COMPLEMENTARY",I54-((M54*F54)+J54),I54-(M54*F54))) -> 75000 | O54: =VLOOKUP(E54,DATABASE!C:Q,8,false) -> IBU | P54: =VLOOKUP(E54,DATABASE!C:Q,9,False) -> 0 | Q54: =VLOOKUP(E54,DATABASE!C:Q,4,false) -> SERVICE | R54: =VLOOKUP(E54,DATABASE!C:Q,11,false) -> SERVICE
C55: 45660 | D55: 3807 | E55: Dunlop 215/65 16 ST20 | F55: 1 | G55: 1035000 | H55: 0 | I55: =(G55-H55)*F55 -> 1035000 | J55: =IF(E55="SERVICE",I55-(I55*50%),Vlookup(E55,DATABASE!C:Q,10,false)*F55) -> 0 | K55: =VLOOKUP(E55,DATABASE!C:Q,7,false) -> 959000 | L55: 949000 | M55: =CEILING(L55, 5000) -> 950000 | N55: =if(R55="SERVICE",I55-(J55+M55), IF(R55="COMPLEMENTARY",I55-((M55*F55)+J55),I55-(M55*F55))) -> 85000 | O55: =VLOOKUP(E55,DATABASE!C:Q,8,false) -> IBU | P55: =VLOOKUP(E55,DATABASE!C:Q,9,False) -> 1 | Q55: =VLOOKUP(E55,DATABASE!C:Q,4,false) -> Dunlop | R55: =VLOOKUP(E55,DATABASE!C:Q,11,false) -> Tire
C56: 45661 | D56: 3808 | E56: BD 14 Truckoor | F56: 1 | G56: 115000 | H56: 0 | I56: =(G56-H56)*F56 -> 115000 | J56: =IF(E56="SERVICE",I56-(I56*50%),Vlookup(E56,DATABASE!C:Q,10,false)*F56) -> 0 | K56: =VLOOKUP(E56,DATABASE!C:Q,7,false) -> 81200 | L56: 81200 | M56: =CEILING(L56, 5000) -> 85000 | N56: =if(R56="SERVICE",I56-(J56+M56), IF(R56="COMPLEMENTARY",I56-((M56*F56)+J56),I56-(M56*F56))) -> 30000 | O56: =VLOOKUP(E56,DATABASE!C:Q,8,false) -> BIAN | P56: =VLOOKUP(E56,DATABASE!C:Q,9,False) -> 1 | Q56: =VLOOKUP(E56,DATABASE!C:Q,4,false) -> BD | R56: =VLOOKUP(E56,DATABASE!C:Q,11,false) -> Tire
C57: 45661 | D57: 3809 | E57: BD 13 Truckoor | F57: 1 | G57: 95000 | H57: 0 | I57: =(G57-H57)*F57 -> 95000 | J57: =IF(E57="SERVICE",I57-(I57*50%),Vlookup(E57,DATABASE!C:Q,10,false)*F57) -> 0 | K57: =VLOOKUP(E57,DATABASE!C:Q,7,false) -> 61600 | L57: 61600 | M57: =CEILING(L57, 5000) -> 65000 | N57: =if(R57="SERVICE",I57-(J57+M57), IF(R57="COMPLEMENTARY",I57-((M57*F57)+J57),I57-(M57*F57))) -> 30000 | O57: =VLOOKUP(E57,DATABASE!C:Q,8,false) -> BIAN | P57: =VLOOKUP(E57,DATABASE!C:Q,9,False) -> 1 | Q57: =VLOOKUP(E57,DATABASE!C:Q,4,false) -> BD | R57: =VLOOKUP(E57,DATABASE!C:Q,11,false) -> Tire
C58: 45661 | D58: 3810 | E58: GT 195/50 16 GTX PRO | F58: 2 | G58: 730000 | H58: 0 | I58: =(G58-H58)*F58 -> 1460000 | J58: =IF(E58="SERVICE",I58-(I58*50%),Vlookup(E58,DATABASE!C:Q,10,false)*F58) -> 0 | K58: =VLOOKUP(E58,DATABASE!C:Q,7,false) -> 643230 | L58: 643230 | M58: =CEILING(L58, 5000) -> 645000 | N58: =if(R58="SERVICE",I58-(J58+M58), IF(R58="COMPLEMENTARY",I58-((M58*F58)+J58),I58-(M58*F58))) -> 170000 | O58: =VLOOKUP(E58,DATABASE!C:Q,8,false) -> BIAN | P58: =VLOOKUP(E58,DATABASE!C:Q,9,False) -> 1 | Q58: =VLOOKUP(E58,DATABASE!C:Q,4,false) -> GT | R58: =VLOOKUP(E58,DATABASE!C:Q,11,false) -> Tire
C59: 45661 | D59: 3810 | E59: Balancing 30 | F59: 2 | G59: 30000 | H59: 0 | I59: =(G59-H59)*F59 -> 60000 | J59: =IF(E59="SERVICE",I59-(I59*50%),Vlookup(E59,DATABASE!C:Q,10,false)*F59) -> 0 | K59: 0 | L59: 0 | M59: =CEILING(L59, 5000) -> 0 | N59: =if(R59="SERVICE",I59-(J59+M59), IF(R59="COMPLEMENTARY",I59-((M59*F59)+J59),I59-(M59*F59))) -> 60000 | O59: =VLOOKUP(E59,DATABASE!C:Q,8,false) -> BIAN | P59: =VLOOKUP(E59,DATABASE!C:Q,9,False) -> 0 | Q59: =VLOOKUP(E59,DATABASE!C:Q,4,false) -> Balancing | R59: =VLOOKUP(E59,DATABASE!C:Q,11,false) -> COMPLEMENTARY
C60: 45661 | D60: 3811 | E60: Dunlop 205/65 16 EC300 | F60: 2 | G60: 880000 | H60: 0 | I60: =(G60-H60)*F60 -> 1760000 | J60: =IF(E60="SERVICE",I60-(I60*50%),Vlookup(E60,DATABASE!C:Q,10,false)*F60) -> 0 | K60: =VLOOKUP(E60,DATABASE!C:Q,7,false) -> 809000 | L60: 809000 | M60: =CEILING(L60, 5000) -> 810000 | N60: =if(R60="SERVICE",I60-(J60+M60), IF(R60="COMPLEMENTARY",I60-((M60*F60)+J60),I60-(M60*F60))) -> 140000 | O60: =VLOOKUP(E60,DATABASE!C:Q,8,false) -> IBU | P60: =VLOOKUP(E60,DATABASE!C:Q,9,False) -> 1 | Q60: =VLOOKUP(E60,DATABASE!C:Q,4,false) -> Dunlop | R60: =VLOOKUP(E60,DATABASE!C:Q,11,false) -> Tire
C61: 45661 | D61: 3812 | E61: Dunlop 175/13 LT5 | F61: 2 | G61: 700000 | H61: 0 | I61: =(G61-H61)*F61 -> 1400000 | J61: =IF(E61="SERVICE",I61-(I61*50%),Vlookup(E61,DATABASE!C:Q,10,false)*F61) -> 0 | K61: 613000 | L61: 613000 | M61: =CEILING(L61, 5000) -> 615000 | N61: =if(R61="SERVICE",I61-(J61+M61), IF(R61="COMPLEMENTARY",I61-((M61*F61)+J61),I61-(M61*F61))) -> 170000 | O61: =VLOOKUP(E61,DATABASE!C:Q,8,false) -> IBU | P61: =VLOOKUP(E61,DATABASE!C:Q,9,False) -> 1 | Q61: =VLOOKUP(E61,DATABASE!C:Q,4,false) -> Dunlop | R61: =VLOOKUP(E61,DATABASE!C:Q,11,false) -> Tire
